Workbook
Name БонусНПД: НАСТРОЙКИ!$B$18
Name Виды: СПРАВОЧНИКИ!$J$7:$J$13
Name ВычетУСН: НАСТРОЙКИ!$B$22
Name Год: НАСТРОЙКИ!$B$9
Name ДатаОтчета: НАСТРОЙКИ!$B$10
Name ДоходПрошлыйГод: НАСТРОЙКИ!$B$21
Name Категории: СПРАВОЧНИКИ!$F$7:$F$66
Name Контрагенты: СПРАВОЧНИКИ!$G$7:$G$66
Name ЛимитНПД: НАЛОГИ!$B$39
Name ЛимитУСН: НАЛОГИ!$B$41
Name МаксВзносы: НАСТРОЙКИ!$B$20
Name МесяцыРезерва: НАСТРОЙКИ!$B$24
Name НачалоУчета: НАСТРОЙКИ!$B$11
Name ПорогНДС: НАЛОГИ!$B$40
Name Проекты: СПРАВОЧНИКИ!$I$7:$I$66
Name Режим: НАСТРОЙКИ!$B$8
Name РежимыИП: СПРАВОЧНИКИ!$K$7:$K$10
Name РежимыООО: СПРАВОЧНИКИ!$L$7:$L$9
Name Сотрудники: НАСТРОЙКИ!$B$12
Name СтавкаДоход: НАСТРОЙКИ!$B$14
Name СтавкаДР: НАСТРОЙКИ!$B$15
Name СтавкаНПДФЛ: НАСТРОЙКИ!$B$16
Name СтавкаНПДЮЛ: НАСТРОЙКИ!$B$17
Name Сценарий: НАСТРОЙКИ!$B$23
Name Счета: СЧЕТА!$A$7:$A$16
Name Типы: СПРАВОЧНИКИ!$A$7:$A$22
Name ФиксВзносы: НАСТРОЙКИ!$B$19
Name Форма: НАСТРОЙКИ!$B$7

Sheet ПАНЕЛЬ
A1: Главная панель | D1: Настройки | F1: Контроль
A2: FINCORE BUSINESS PRO
A4: LEO STUDIO. Демонстрационный проект. Все данные вымышлены.
A5: =Форма&" · "&Режим -> ИП · УСН Доходы | F5: =TEXT(DAY(ДатаОтчета),"00")&"."&TEXT(MONTH(ДатаОтчета),"00")&"."&YEAR(ДатаОтчета)&" · RUB" -> 31.12.2026 · RUB | K5: =Сценарий -> Базовый
A7: Выручка | F7: Финансовый результат | K7: Денежные средства
A8: =ОПиУ!N7 -> 6597000 | F8: =ОПиУ!N16 -> 872197.89 | K8: =СЧЕТА!B19 -> 1675043.2
A11: Дебиторская задолженность | F11: Кредиты и займы | K11: Налоги и взносы к уплате
A12: =БАЛАНС!B8 -> 59040 | F12: =БАЛАНС!B15 -> 136028.15 | K12: =БАЛАНС!B16 -> 319657.2
A33: =БАЛАНС!B29&". Резерв: "&РЕЗЕРВЫ!B16 -> Баланс сходится. Резерв: Резерв ниже цели
A34: =НАЛОГИ!B4 -> ПРЕДВАРИТЕЛЬНЫЙ РАСЧЁТ
A35: Проверяйте лист КОНТРОЛЬ перед принятием решений. Просрочки и ошибки выделяются цветом.
A37: НАСТРОЙКИ | C37: ДДС | E37: ОПиУ | G37: БАЛАНС | I37: НАЛОГИ | K37: БЮДЖЕТ | M37: РЕЗЕРВЫ
A38: РЕИНВЕСТИЦИИ | C38: ПРОГНОЗ | E38: РИСКИ | G38: ПОКАЗАТЕЛИ | I38: АНАЛИТИКА | K38: КРЕДИТ | M38: АКТИВЫ
A39: ИНВЕСТПРОЕКТ | C39: ОПЕРАЦИИ | E39: НАЧИСЛЕНИЯ | G39: СЧЕТА | I39: СПРАВОЧНИКИ | K39: КОНТРОЛЬ | M39: ИНСТРУКЦИЯ
A41: Показатель | B41: =CHOOSE(MONTH(ОПиУ!B6),"янв","фев","мар","апр","май","июн","июл","авг","сен","окт","ноя","дек") -> янв | C41: =CHOOSE(MONTH(ОПиУ!C6),"янв","фев","мар","апр","май","июн","июл","авг","сен","окт","ноя","дек") -> фев | D41: =CHOOSE(MONTH(ОПиУ!D6),"янв","фев","мар","апр","май","июн","июл","авг","сен","окт","ноя","дек") -> мар | E41: =CHOOSE(MONTH(ОПиУ!E6),"янв","фев","мар","апр","май","июн","июл","авг","сен","окт","ноя","дек") -> апр | F41: =CHOOSE(MONTH(ОПиУ!F6),"янв","фев","мар","апр","май","июн","июл","авг","сен","окт","ноя","дек") -> май | G41: =CHOOSE(MONTH(ОПиУ!G6),"янв","фев","мар","апр","май","июн","июл","авг","сен","окт","ноя","дек") -> июн | H41: =CHOOSE(MONTH(ОПиУ!H6),"янв","фев","мар","апр","май","июн","июл","авг","сен","окт","ноя","дек") -> июл | I41: =CHOOSE(MONTH(ОПиУ!I6),"янв","фев","мар","апр","май","июн","июл","авг","сен","окт","ноя","дек") -> авг | ... M41: =CHOOSE(MONTH(ОПиУ!M6),"янв","фев","мар","апр","май","июн","июл","авг","сен","окт","ноя","дек") -> дек
A42: Выручка | B42: =ОПиУ!B7 -> 420000 | C42: =ОПиУ!C7 -> 180000 | D42: =ОПиУ!D7 -> 507000 | E42: =ОПиУ!E7 -> 550000 | F42: =ОПиУ!F7 -> 580000 | G42: =ОПиУ!G7 -> 620000 | H42: =ОПиУ!H7 -> 590000 | I42: =ОПиУ!I7 -> 210000 | ... M42: =ОПиУ!M7 -> 820000
A43: Результат | B43: =ОПиУ!B16 -> 4917.5 | C43: =ОПиУ!C16 -> -149325.34 | D43: =ОПиУ!D16 -> 49344.17 | E43: =ОПиУ!E16 -> 76696.08 | F43: =ОПиУ!F16 -> 95160.42 | G43: =ОПиУ!G16 -> 119727.22 | H43: =ОПиУ!H16 -> 101971.53 | I43: =ОПиУ!I16 -> -194651 | ... M43: =ОПиУ!M16 -> 247318.69
A44: Денежный остаток | B44: =ДДС!B14 -> 645622.77 | C44: =ДДС!C14 -> 508045.54 | D44: =ДДС!D14 -> 566868.31 | E44: =ДДС!E14 -> 635891.08 | F44: =ДДС!F14 -> 770313.85 | G44: =ДДС!G14 -> 881936.62 | H44: =ДДС!H14 -> 978159.39 | I44: =ДДС!I14 -> 795982.16 | ... M44: =ДДС!M14 -> 1675043.2

Sheet НАСТРОЙКИ
A1: Главная панель | D1: Настройки | F1: Контроль
A2: НАСТРОЙКИ
A3: LEO STUDIO • Управленческий учёт • RUB
A6: Параметр | B6: Значение | C6: Пояснение
A7: Форма бизнеса | B7: ИП | C7: ИП или ООО
A8: Налоговый режим | B8: УСН Доходы | C8: ОСНО / ПСН: только ручной режим
A9: Отчётный год | B9: 2026 | C9: Одна книга на финансовый год
A10: Дата отчёта | B10: 46387 | C10: В демо весь 2026 год — вымышленный сценарий
A11: Начало учёта | B11: 46023 | C11: Не менять без переноса начальных остатков
A12: Сотрудники | B12: Да | C12: Для ООО: взносы и НДФЛ задаются отдельно
A13: Регион | B13: Москва | C13: Региональные льготы подтвердите отдельно
A14: Ставка УСН доходы | B14: 0.06 | C14: Базовая ставка, редактируется при подтверждённой льготе
A15: Ставка УСН Д-Р | B15: 0.15 | C15: Базовая ставка, региональные условия проверяются
A16: НПД ФЛ | B16: 0.04 | C16: Поступления от физических лиц
A17: НПД ЮЛ / ИП | B17: 0.06 | C17: Поступления от организаций и ИП
A18: Остаток бонуса НПД | B18: 10000 | C18: От 0 до 10000; остаток на начало года
A19: Взносы ИП фиксированные | B19: 57390 | C19: Полный 2026 год, без специальных освобождений
A20: Дополнительные взносы максимум | B20: 321818 | C20: Только дополнительная часть 1% в 2026 году
A21: Доход прошлого года | B21: 0 | C21: Для контроля освобождения от НДС
A22: Взносы к уменьшению УСН | B22: 0 | C22: Подтверждённая сумма нарастающим итогом; без повторного вычета
A23: Выбранный сценарий | B23: Базовый | C23: Сценарий изменяет единый прогноз
A24: Месяцев резерва | B24: 3 | C24: Целевое покрытие обязательных расходов
A25: Пополнение резерва | B25: 15000 | C25: План, не является расходом
A26: План обязательных расходов | B26: 0 | C26: Если нет истории, заполнить вручную
A27: НПД условия подтверждены | B27: Нет | C27: Нет работников, запрещённых видов деятельности и прочих ограничений
A28: Автоналог разрешён | B28: Да | C28: Нет при НДС, неподдерживаемом режиме или году
A29: Фиксированные расходы в месяц | B29: 0 | C29: 0: средние операционные затраты из истории
A30: Прогноз: поступления из старой ДЗ | B30: 0 | C30: Сумма, планируемая в первом месяце прогноза
A31: Прогноз: погашение старой КЗ | B31: 0 | C31: Сумма, планируемая в первом месяце прогноза
A32: Начальный капитал | B32: 0 | C32: Вводится независимо от активов, не балансирующая формула
A33: Начальный кредит | B33: 0 | C33: Остаток на начало учёта; график только нового кредита
A34: Начальные налоги | B34: 0 | C34: Сальдо обязательств на начало учёта
A35: Начальная прибыль | B35: 0 | C35: Накопленный результат до начала книги
A36: Начальная ДЗ | B36: 0 | C36: Для детализации начальной ДЗ нужны документы переноса
A37: Начальная КЗ | B37: 0 | C37: Для детализации начальной КЗ нужны документы переноса
A38: Начальные прочие активы | B38: 0 | C38: Запасы и прочие активы: без автоматического движения
A39: Начальные прочие обязательства | B39: 0 | C39: Без автоматического движения
A40: Ручной налог на результат | B40: 0 | C40: Для неподдерживаемых режимов: задаётся по месяцам в НАЛОГИ

Sheet ДДС
A1: Главная панель | D1: Настройки | F1: Контроль
A2: ДДС
A3: LEO STUDIO • Управленческий учёт • RUB
A6: Показатель | B6: =DATE(Год,1,1) -> 46023 | C6: =DATE(Год,2,1) -> 46054 | D6: =DATE(Год,3,1) -> 46082 | E6: =DATE(Год,4,1) -> 46113 | F6: =DATE(Год,5,1) -> 46143 | G6: =DATE(Год,6,1) -> 46174 | H6: =DATE(Год,7,1) -> 46204 | I6: =DATE(Год,8,1) -> 46235 | J6: =DATE(Год,9,1) -> 46266 | K6: =DATE(Год,10,1) -> 46296 | L6: =DATE(Год,11,1) -> 46327 | M6: =DATE(Год,12,1) -> 46357 | N6: Год / итог
A7: Начальный остаток | B7: =SUM(Accounts[Начальный]) -> 0 | C7: =B14 -> 645622.77 | D7: =C14 -> 508045.54 | E7: =D14 -> 566868.31 | F7: =E14 -> 635891.08 | G7: =F14 -> 770313.85 | H7: =G14 -> 881936.62 | I7: =H14 -> 978159.39 | J7: =I14 -> 795982.16 | ... M7: =L14 -> 1387650.5 | N7: =B7 -> 0
A8: Операционные поступления | B8: =SUMIFS(Cash[Поток],Cash[Дата],"<="&ДатаОтчета,Cash[Статус],"Проведён",Cash[Дата],">="&B$6,Cash[Дата],"<"&EDATE(B$6,1),Cash[Класс ДДС],"Операционный",Cash[Поток],">0") -> 420000 | C8: =SUMIFS(Cash[Поток],Cash[Дата],"<="&ДатаОтчета,Cash[Статус],"Проведён",Cash[Дата],">="&C$6,Cash[Дата],"<"&EDATE(C$6,1),Cash[Класс ДДС],"Операционный",Cash[Поток],">0") -> 180000 | D8: =SUMIFS(Cash[Поток],Cash[Дата],"<="&ДатаОтчета,Cash[Статус],"Проведён",Cash[Дата],">="&D$6,Cash[Дата],"<"&EDATE(D$6,1),Cash[Класс ДДС],"Операционный",Cash[Поток],">0") -> 510000 | E8: =SUMIFS(Cash[Поток],Cash[Дата],"<="&ДатаОтчета,Cash[Статус],"Проведён",Cash[Дата],">="&E$6,Cash[Дата],"<"&EDATE(E$6,1),Cash[Класс ДДС],"Операционный",Cash[Поток],">0") -> 550000 | F8: =SUMIFS(Cash[Поток],Cash[Дата],"<="&ДатаОтчета,Cash[Статус],"Проведён",Cash[Дата],">="&F$6,Cash[Дата],"<"&EDATE(F$6,1),Cash[Класс ДДС],"Операционный",Cash[Поток],">0") -> 580000 | G8: =SUMIFS(Cash[Поток],Cash[Дата],"<="&ДатаОтчета,Cash[Статус],"Проведён",Cash[Дата],">="&G$6,Cash[Дата],"<"&EDATE(G$6,1),Cash[Класс ДДС],"Операционный",Cash[Поток],">0") -> 620000 | H8: =SUMIFS(Cash[Поток],Cash[Дата],"<="&ДатаОтчета,Cash[Статус],"Проведён",Cash[Дата],">="&H$6,Cash[Дата],"<"&EDATE(H$6,1),Cash[Класс ДДС],"Операционный",Cash[Поток],">0") -> 590000 | I8: =SUMIFS(Cash[Поток],Cash[Дата],"<="&ДатаОтчета,Cash[Статус],"Проведён",Cash[Дата],">="&I$6,Cash[Дата],"<"&EDATE(I$6,1),Cash[Класс ДДС],"Операционный",Cash[Поток],">0") -> 210000 | ... M8: =SUMIFS(Cash[Поток],Cash[Дата],"<="&ДатаОтчета,Cash[Статус],"Проведён",Cash[Дата],">="&M$6,Cash[Дата],"<"&EDATE(M$6,1),Cash[Класс ДДС],"Операционный",Cash[Поток],">0") -> 760960 | N8: =SUM(B8:M8) -> 6540960
A9: Операционные выплаты | B9: =-SUMIFS(Cash[Поток],Cash[Дата],"<="&ДатаОтчета,Cash[Статус],"Проведён",Cash[Дата],">="&B$6,Cash[Дата],"<"&EDATE(B$6,1),Cash[Класс ДДС],"Операционный",Cash[Поток],"<0") -> 383900 | C9: =-SUMIFS(Cash[Поток],Cash[Дата],"<="&ДатаОтчета,Cash[Статус],"Проведён",Cash[Дата],">="&C$6,Cash[Дата],"<"&EDATE(C$6,1),Cash[Класс ДДС],"Операционный",Cash[Поток],"<0") -> 306942.84 | D9: =-SUMIFS(Cash[Поток],Cash[Дата],"<="&ДатаОтчета,Cash[Статус],"Проведён",Cash[Дата],">="&D$6,Cash[Дата],"<"&EDATE(D$6,1),Cash[Класс ДДС],"Операционный",Cash[Поток],"<0") -> 415383.33 | E9: =-SUMIFS(Cash[Поток],Cash[Дата],"<="&ДатаОтчета,Cash[Статус],"Проведён",Cash[Дата],">="&E$6,Cash[Дата],"<"&EDATE(E$6,1),Cash[Класс ДДС],"Операционный",Cash[Поток],"<0") -> 470021.42 | F9: =-SUMIFS(Cash[Поток],Cash[Дата],"<="&ДатаОтчета,Cash[Статус],"Проведён",Cash[Дата],">="&F$6,Cash[Дата],"<"&EDATE(F$6,1),Cash[Класс ДДС],"Операционный",Cash[Поток],"<0") -> 434457.08 | G9: =-SUMIFS(Cash[Поток],Cash[Дата],"<="&ДатаОтчета,Cash[Статус],"Проведён",Cash[Дата],">="&G$6,Cash[Дата],"<"&EDATE(G$6,1),Cash[Класс ДДС],"Операционный",Cash[Поток],"<0") -> 447090.28 | H9: =-SUMIFS(Cash[Поток],Cash[Дата],"<="&ДатаОтчета,Cash[Статус],"Проведён",Cash[Дата],">="&H$6,Cash[Дата],"<"&EDATE(H$6,1),Cash[Класс ДДС],"Операционный",Cash[Поток],"<0") -> 481945.97 | I9: =-SUMIFS(Cash[Поток],Cash[Дата],"<="&ДатаОтчета,Cash[Статус],"Проведён",Cash[Дата],">="&I$6,Cash[Дата],"<"&EDATE(I$6,1),Cash[Класс ДДС],"Операционный",Cash[Поток],"<0") -> 380168.5 | ... M9: =-SUMIFS(Cash[Поток],Cash[Дата],"<="&ДатаОтчета,Cash[Статус],"Проведён",Cash[Дата],">="&M$6,Cash[Дата],"<"&EDATE(M$6,1),Cash[Класс ДДС],"Операционный",Cash[Поток],"<0") -> 435821.61 | N9: =SUM(B9:M9) -> 5221944.9
A10: Операционный поток | B10: =B8-B9 -> 36100 | C10: =C8-C9 -> -126942.84 | D10: =D8-D9 -> 94616.67 | E10: =E8-E9 -> 79978.58 | F10: =F8-F9 -> 145542.92 | G10: =G8-G9 -> 172909.72 | H10: =H8-H9 -> 108054.03 | I10: =I8-I9 -> -170168.5 | ... M10: =M8-M9 -> 325138.39 | N10: =SUM(B10:M10) -> 1319015.1
A11: Инвестиционный поток | B11: =SUMIFS(Cash[Поток],Cash[Дата],"<="&ДатаОтчета,Cash[Статус],"Проведён",Cash[Дата],">="&B$6,Cash[Дата],"<"&EDATE(B$6,1),Cash[Класс ДДС],"Инвестиционный") -> -180000 | C11: =SUMIFS(Cash[Поток],Cash[Дата],"<="&ДатаОтчета,Cash[Статус],"Проведён",Cash[Дата],">="&C$6,Cash[Дата],"<"&EDATE(C$6,1),Cash[Класс ДДС],"Инвестиционный") -> 0 | D11: =SUMIFS(Cash[Поток],Cash[Дата],"<="&ДатаОтчета,Cash[Статус],"Проведён",Cash[Дата],">="&D$6,Cash[Дата],"<"&EDATE(D$6,1),Cash[Класс ДДС],"Инвестиционный") -> 0 | E11: =SUMIFS(Cash[Поток],Cash[Дата],"<="&ДатаОтчета,Cash[Статус],"Проведён",Cash[Дата],">="&E$6,Cash[Дата],"<"&EDATE(E$6,1),Cash[Класс ДДС],"Инвестиционный") -> 0 | F11: =SUMIFS(Cash[Поток],Cash[Дата],"<="&ДатаОтчета,Cash[Статус],"Проведён",Cash[Дата],">="&F$6,Cash[Дата],"<"&EDATE(F$6,1),Cash[Класс ДДС],"Инвестиционный") -> 0 | G11: =SUMIFS(Cash[Поток],Cash[Дата],"<="&ДатаОтчета,Cash[Статус],"Проведён",Cash[Дата],">="&G$6,Cash[Дата],"<"&EDATE(G$6,1),Cash[Класс ДДС],"Инвестиционный") -> 0 | H11: =SUMIFS(Cash[Поток],Cash[Дата],"<="&ДатаОтчета,Cash[Статус],"Проведён",Cash[Дата],">="&H$6,Cash[Дата],"<"&EDATE(H$6,1),Cash[Класс ДДС],"Инвестиционный") -> 0 | I11: =SUMIFS(Cash[Поток],Cash[Дата],"<="&ДатаОтчета,Cash[Статус],"Проведён",Cash[Дата],">="&I$6,Cash[Дата],"<"&EDATE(I$6,1),Cash[Класс ДДС],"Инвестиционный") -> 0 | ... M11: =SUMIFS(Cash[Поток],Cash[Дата],"<="&ДатаОтчета,Cash[Статус],"Проведён",Cash[Дата],">="&M$6,Cash[Дата],"<"&EDATE(M$6,1),Cash[Класс ДДС],"Инвестиционный") -> 0 | N11: =SUM(B11:M11) -> -180000
A12: Финансовый поток | B12: =SUMIFS(Cash[Поток],Cash[Дата],"<="&ДатаОтчета,Cash[Статус],"Проведён",Cash[Дата],">="&B$6,Cash[Дата],"<"&EDATE(B$6,1),Cash[Класс ДДС],"Финансовый") -> 789522.77 | C12: =SUMIFS(Cash[Поток],Cash[Дата],"<="&ДатаОтчета,Cash[Статус],"Проведён",Cash[Дата],">="&C$6,Cash[Дата],"<"&EDATE(C$6,1),Cash[Класс ДДС],"Финансовый") -> -10634.39 | D12: =SUMIFS(Cash[Поток],Cash[Дата],"<="&ДатаОтчета,Cash[Статус],"Проведён",Cash[Дата],">="&D$6,Cash[Дата],"<"&EDATE(D$6,1),Cash[Класс ДДС],"Финансовый") -> -35793.9 | E12: =SUMIFS(Cash[Поток],Cash[Дата],"<="&ДатаОтчета,Cash[Статус],"Проведён",Cash[Дата],">="&E$6,Cash[Дата],"<"&EDATE(E$6,1),Cash[Класс ДДС],"Финансовый") -> -10955.81 | F12: =SUMIFS(Cash[Поток],Cash[Дата],"<="&ДатаОтчета,Cash[Статус],"Проведён",Cash[Дата],">="&F$6,Cash[Дата],"<"&EDATE(F$6,1),Cash[Класс ДДС],"Финансовый") -> -11120.15 | G12: =SUMIFS(Cash[Поток],Cash[Дата],"<="&ДатаОтчета,Cash[Статус],"Проведён",Cash[Дата],">="&G$6,Cash[Дата],"<"&EDATE(G$6,1),Cash[Класс ДДС],"Финансовый") -> -61286.95 | H12: =SUMIFS(Cash[Поток],Cash[Дата],"<="&ДатаОтчета,Cash[Статус],"Проведён",Cash[Дата],">="&H$6,Cash[Дата],"<"&EDATE(H$6,1),Cash[Класс ДДС],"Финансовый") -> -11831.26 | I12: =SUMIFS(Cash[Поток],Cash[Дата],"<="&ДатаОтчета,Cash[Статус],"Проведён",Cash[Дата],">="&I$6,Cash[Дата],"<"&EDATE(I$6,1),Cash[Класс ДДС],"Финансовый") -> -12008.73 | ... M12: =SUMIFS(Cash[Поток],Cash[Дата],"<="&ДатаОтчета,Cash[Статус],"Проведён",Cash[Дата],">="&M$6,Cash[Дата],"<"&EDATE(M$6,1),Cash[Класс ДДС],"Финансовый") -> -37745.62 | N12: =SUM(B12:M12) -> 536028.15
A13: Чистый денежный поток | B13: =SUM(B10:B12) -> 645622.77 | C13: =SUM(C10:C12) -> -137577.23 | D13: =SUM(D10:D12) -> 58822.77 | E13: =SUM(E10:E12) -> 69022.77 | F13: =SUM(F10:F12) -> 134422.77 | G13: =SUM(G10:G12) -> 111622.77 | H13: =SUM(H10:H12) -> 96222.77 | I13: =SUM(I10:I12) -> -182177.23 | ... M13: =SUM(M10:M12) -> 287392.77 | N13: =SUM(B13:M13) -> 1675043.2
A14: Конечный остаток | B14: =B7+B13 -> 645622.77 | C14: =C7+C13 -> 508045.54 | D14: =D7+D13 -> 566868.31 | E14: =E7+E13 -> 635891.08 | F14: =F7+F13 -> 770313.85 | G14: =G7+G13 -> 881936.62 | H14: =H7+H13 -> 978159.39 | I14: =I7+I13 -> 795982.16 | ... M14: =M7+M13 -> 1675043.2 | N14: =M14 -> 1675043.2
A16: Поступления всего | B16: =SUMIFS(Cash[Поток],Cash[Дата],"<="&ДатаОтчета,Cash[Статус],"Проведён",Cash[Дата],">="&B$6,Cash[Дата],"<"&EDATE(B$6,1),Cash[Класс ДДС],"<>Внутренний",Cash[Поток],">0") -> 1220000 | C16: =SUMIFS(Cash[Поток],Cash[Дата],"<="&ДатаОтчета,Cash[Статус],"Проведён",Cash[Дата],">="&C$6,Cash[Дата],"<"&EDATE(C$6,1),Cash[Класс ДДС],"<>Внутренний",Cash[Поток],">0") -> 180000 | D16: =SUMIFS(Cash[Поток],Cash[Дата],"<="&ДатаОтчета,Cash[Статус],"Проведён",Cash[Дата],">="&D$6,Cash[Дата],"<"&EDATE(D$6,1),Cash[Класс ДДС],"<>Внутренний",Cash[Поток],">0") -> 510000 | E16: =SUMIFS(Cash[Поток],Cash[Дата],"<="&ДатаОтчета,Cash[Статус],"Проведён",Cash[Дата],">="&E$6,Cash[Дата],"<"&EDATE(E$6,1),Cash[Класс ДДС],"<>Внутренний",Cash[Поток],">0") -> 550000 | F16: =SUMIFS(Cash[Поток],Cash[Дата],"<="&ДатаОтчета,Cash[Статус],"Проведён",Cash[Дата],">="&F$6,Cash[Дата],"<"&EDATE(F$6,1),Cash[Класс ДДС],"<>Внутренний",Cash[Поток],">0") -> 580000 | G16: =SUMIFS(Cash[Поток],Cash[Дата],"<="&ДатаОтчета,Cash[Статус],"Проведён",Cash[Дата],">="&G$6,Cash[Дата],"<"&EDATE(G$6,1),Cash[Класс ДДС],"<>Внутренний",Cash[Поток],">0") -> 620000 | H16: =SUMIFS(Cash[Поток],Cash[Дата],"<="&ДатаОтчета,Cash[Статус],"Проведён",Cash[Дата],">="&H$6,Cash[Дата],"<"&EDATE(H$6,1),Cash[Класс ДДС],"<>Внутренний",Cash[Поток],">0") -> 590000 | I16: =SUMIFS(Cash[Поток],Cash[Дата],"<="&ДатаОтчета,Cash[Статус],"Проведён",Cash[Дата],">="&I$6,Cash[Дата],"<"&EDATE(I$6,1),Cash[Класс ДДС],"<>Внутренний",Cash[Поток],">0") -> 210000 | ... M16: =SUMIFS(Cash[Поток],Cash[Дата],"<="&ДатаОтчета,Cash[Статус],"Проведён",Cash[Дата],">="&M$6,Cash[Дата],"<"&EDATE(M$6,1),Cash[Класс ДДС],"<>Внутренний",Cash[Поток],">0") -> 760960 | N16: =SUM(B16:M16) -> 7340960
A17: Выплаты всего | B17: =-SUMIFS(Cash[Поток],Cash[Дата],"<="&ДатаОтчета,Cash[Статус],"Проведён",Cash[Дата],">="&B$6,Cash[Дата],"<"&EDATE(B$6,1),Cash[Класс ДДС],"<>Внутренний",Cash[Поток],"<0") -> 574377.23 | C17: =-SUMIFS(Cash[Поток],Cash[Дата],"<="&ДатаОтчета,Cash[Статус],"Проведён",Cash[Дата],">="&C$6,Cash[Дата],"<"&EDATE(C$6,1),Cash[Класс ДДС],"<>Внутренний",Cash[Поток],"<0") -> 317577.23 | D17: =-SUMIFS(Cash[Поток],Cash[Дата],"<="&ДатаОтчета,Cash[Статус],"Проведён",Cash[Дата],">="&D$6,Cash[Дата],"<"&EDATE(D$6,1),Cash[Класс ДДС],"<>Внутренний",Cash[Поток],"<0") -> 451177.23 | E17: =-SUMIFS(Cash[Поток],Cash[Дата],"<="&ДатаОтчета,Cash[Статус],"Проведён",Cash[Дата],">="&E$6,Cash[Дата],"<"&EDATE(E$6,1),Cash[Класс ДДС],"<>Внутренний",Cash[Поток],"<0") -> 480977.23 | F17: =-SUMIFS(Cash[Поток],Cash[Дата],"<="&ДатаОтчета,Cash[Статус],"Проведён",Cash[Дата],">="&F$6,Cash[Дата],"<"&EDATE(F$6,1),Cash[Класс ДДС],"<>Внутренний",Cash[Поток],"<0") -> 445577.23 | G17: =-SUMIFS(Cash[Поток],Cash[Дата],"<="&ДатаОтчета,Cash[Статус],"Проведён",Cash[Дата],">="&G$6,Cash[Дата],"<"&EDATE(G$6,1),Cash[Класс ДДС],"<>Внутренний",Cash[Поток],"<0") -> 508377.23 | H17: =-SUMIFS(Cash[Поток],Cash[Дата],"<="&ДатаОтчета,Cash[Статус],"Проведён",Cash[Дата],">="&H$6,Cash[Дата],"<"&EDATE(H$6,1),Cash[Класс ДДС],"<>Внутренний",Cash[Поток],"<0") -> 493777.23 | I17: =-SUMIFS(Cash[Поток],Cash[Дата],"<="&ДатаОтчета,Cash[Статус],"Проведён",Cash[Дата],">="&I$6,Cash[Дата],"<"&EDATE(I$6,1),Cash[Класс ДДС],"<>Внутренний",Cash[Поток],"<0") -> 392177.23 | ... M17: =-SUMIFS(Cash[Поток],Cash[Дата],"<="&ДатаОтчета,Cash[Статус],"Проведён",Cash[Дата],">="&M$6,Cash[Дата],"<"&EDATE(M$6,1),Cash[Класс ДДС],"<>Внутренний",Cash[Поток],"<0") -> 473567.23 | N17: =SUM(B17:M17) -> 5665916.8
A18: Переводы внутри компании | B18: =SUMIFS(Cash[Сумма],Cash[Дата],"<="&ДатаОтчета,Cash[Статус],"Проведён",Cash[Тип],"Перевод",Cash[Дата],">="&B$6,Cash[Дата],"<"&EDATE(B$6,1)) -> 15000 | C18: =SUMIFS(Cash[Сумма],Cash[Дата],"<="&ДатаОтчета,Cash[Статус],"Проведён",Cash[Тип],"Перевод",Cash[Дата],">="&C$6,Cash[Дата],"<"&EDATE(C$6,1)) -> 15000 | D18: =SUMIFS(Cash[Сумма],Cash[Дата],"<="&ДатаОтчета,Cash[Статус],"Проведён",Cash[Тип],"Перевод",Cash[Дата],">="&D$6,Cash[Дата],"<"&EDATE(D$6,1)) -> 15000 | E18: =SUMIFS(Cash[Сумма],Cash[Дата],"<="&ДатаОтчета,Cash[Статус],"Проведён",Cash[Тип],"Перевод",Cash[Дата],">="&E$6,Cash[Дата],"<"&EDATE(E$6,1)) -> 15000 | F18: =SUMIFS(Cash[Сумма],Cash[Дата],"<="&ДатаОтчета,Cash[Статус],"Проведён",Cash[Тип],"Перевод",Cash[Дата],">="&F$6,Cash[Дата],"<"&EDATE(F$6,1)) -> 15000 | G18: =SUMIFS(Cash[Сумма],Cash[Дата],"<="&ДатаОтчета,Cash[Статус],"Проведён",Cash[Тип],"Перевод",Cash[Дата],">="&G$6,Cash[Дата],"<"&EDATE(G$6,1)) -> 15000 | H18: =SUMIFS(Cash[Сумма],Cash[Дата],"<="&ДатаОтчета,Cash[Статус],"Проведён",Cash[Тип],"Перевод",Cash[Дата],">="&H$6,Cash[Дата],"<"&EDATE(H$6,1)) -> 15000 | I18: =SUMIFS(Cash[Сумма],Cash[Дата],"<="&ДатаОтчета,Cash[Статус],"Проведён",Cash[Тип],"Перевод",Cash[Дата],">="&I$6,Cash[Дата],"<"&EDATE(I$6,1)) -> 15000 | ... M18: =SUMIFS(Cash[Сумма],Cash[Дата],"<="&ДатаОтчета,Cash[Статус],"Проведён",Cash[Тип],"Перевод",Cash[Дата],">="&M$6,Cash[Дата],"<"&EDATE(M$6,1)) -> 15000 | N18: =SUM(B18:M18) -> 180000

Sheet ОПиУ
A1: Главная панель | D1: Настройки | F1: Контроль
A2: ОПиУ
A3: LEO STUDIO • Управленческий учёт • RUB
A6: Показатель | B6: =DATE(Год,1,1) -> 46023 | C6: =DATE(Год,2,1) -> 46054 | D6: =DATE(Год,3,1) -> 46082 | E6: =DATE(Год,4,1) -> 46113 | F6: =DATE(Год,5,1) -> 46143 | G6: =DATE(Год,6,1) -> 46174 | H6: =DATE(Год,7,1) -> 46204 | I6: =DATE(Год,8,1) -> 46235 | J6: =DATE(Год,9,1) -> 46266 | K6: =DATE(Год,10,1) -> 46296 | L6: =DATE(Год,11,1) -> 46327 | M6: =DATE(Год,12,1) -> 46357 | N6: Год / итог
A7: Выручка | B7: =SUMIFS(Docs[Сумма],Docs[Дата],"<="&ДатаОтчета,Docs[Статус],"Проведён",Docs[Вид],"Выручка",Docs[Дата],">="&B$6,Docs[Дата],"<"&EDATE(B$6,1)) -> 420000 | C7: =SUMIFS(Docs[Сумма],Docs[Дата],"<="&ДатаОтчета,Docs[Статус],"Проведён",Docs[Вид],"Выручка",Docs[Дата],">="&C$6,Docs[Дата],"<"&EDATE(C$6,1)) -> 180000 | D7: =SUMIFS(Docs[Сумма],Docs[Дата],"<="&ДатаОтчета,Docs[Статус],"Проведён",Docs[Вид],"Выручка",Docs[Дата],">="&D$6,Docs[Дата],"<"&EDATE(D$6,1)) -> 507000 | E7: =SUMIFS(Docs[Сумма],Docs[Дата],"<="&ДатаОтчета,Docs[Статус],"Проведён",Docs[Вид],"Выручка",Docs[Дата],">="&E$6,Docs[Дата],"<"&EDATE(E$6,1)) -> 550000 | F7: =SUMIFS(Docs[Сумма],Docs[Дата],"<="&ДатаОтчета,Docs[Статус],"Проведён",Docs[Вид],"Выручка",Docs[Дата],">="&F$6,Docs[Дата],"<"&EDATE(F$6,1)) -> 580000 | G7: =SUMIFS(Docs[Сумма],Docs[Дата],"<="&ДатаОтчета,Docs[Статус],"Проведён",Docs[Вид],"Выручка",Docs[Дата],">="&G$6,Docs[Дата],"<"&EDATE(G$6,1)) -> 620000 | H7: =SUMIFS(Docs[Сумма],Docs[Дата],"<="&ДатаОтчета,Docs[Статус],"Проведён",Docs[Вид],"Выручка",Docs[Дата],">="&H$6,Docs[Дата],"<"&EDATE(H$6,1)) -> 590000 | I7: =SUMIFS(Docs[Сумма],Docs[Дата],"<="&ДатаОтчета,Docs[Статус],"Проведён",Docs[Вид],"Выручка",Docs[Дата],">="&I$6,Docs[Дата],"<"&EDATE(I$6,1)) -> 210000 | ... M7: =SUMIFS(Docs[Сумма],Docs[Дата],"<="&ДатаОтчета,Docs[Статус],"Проведён",Docs[Вид],"Выручка",Docs[Дата],">="&M$6,Docs[Дата],"<"&EDATE(M$6,1)) -> 820000 | N7: =SUM(B7:M7) -> 6597000
A8: Себестоимость | B8: =SUMIFS(Docs[Сумма],Docs[Дата],"<="&ДатаОтчета,Docs[Статус],"Проведён",Docs[Вид],"Себестоимость",Docs[Дата],">="&B$6,Docs[Дата],"<"&EDATE(B$6,1)) -> 134400 | C8: =SUMIFS(Docs[Сумма],Docs[Дата],"<="&ДатаОтчета,Docs[Статус],"Проведён",Docs[Вид],"Себестоимость",Docs[Дата],">="&C$6,Docs[Дата],"<"&EDATE(C$6,1)) -> 57600 | D8: =SUMIFS(Docs[Сумма],Docs[Дата],"<="&ДатаОтчета,Docs[Статус],"Проведён",Docs[Вид],"Себестоимость",Docs[Дата],">="&D$6,Docs[Дата],"<"&EDATE(D$6,1)) -> 163200 | E8: =SUMIFS(Docs[Сумма],Docs[Дата],"<="&ДатаОтчета,Docs[Статус],"Проведён",Docs[Вид],"Себестоимость",Docs[Дата],">="&E$6,Docs[Дата],"<"&EDATE(E$6,1)) -> 176000 | F8: =SUMIFS(Docs[Сумма],Docs[Дата],"<="&ДатаОтчета,Docs[Статус],"Проведён",Docs[Вид],"Себестоимость",Docs[Дата],">="&F$6,Docs[Дата],"<"&EDATE(F$6,1)) -> 185600 | G8: =SUMIFS(Docs[Сумма],Docs[Дата],"<="&ДатаОтчета,Docs[Статус],"Проведён",Docs[Вид],"Себестоимость",Docs[Дата],">="&G$6,Docs[Дата],"<"&EDATE(G$6,1)) -> 198400 | H8: =SUMIFS(Docs[Сумма],Docs[Дата],"<="&ДатаОтчета,Docs[Статус],"Проведён",Docs[Вид],"Себестоимость",Docs[Дата],">="&H$6,Docs[Дата],"<"&EDATE(H$6,1)) -> 188800 | I8: =SUMIFS(Docs[Сумма],Docs[Дата],"<="&ДатаОтчета,Docs[Статус],"Проведён",Docs[Вид],"Себестоимость",Docs[Дата],">="&I$6,Docs[Дата],"<"&EDATE(I$6,1)) -> 67200 | ... M8: =SUMIFS(Docs[Сумма],Docs[Дата],"<="&ДатаОтчета,Docs[Статус],"Проведён",Docs[Вид],"Себестоимость",Docs[Дата],">="&M$6,Docs[Дата],"<"&EDATE(M$6,1)) -> 262400 | N8: =SUM(B8:M8) -> 2112000
A9: Валовая прибыль | B9: =B7-B8 -> 285600 | C9: =C7-C8 -> 122400 | D9: =D7-D8 -> 343800 | E9: =E7-E8 -> 374000 | F9: =F7-F8 -> 394400 | G9: =G7-G8 -> 421600 | H9: =H7-H8 -> 401200 | I9: =I7-I8 -> 142800 | ... M9: =M7-M8 -> 557600 | N9: =SUM(B9:M9) -> 4485000
A10: Операционные расходы | B10: =SUMIFS(Docs[Сумма],Docs[Дата],"<="&ДатаОтчета,Docs[Статус],"Проведён",Docs[Вид],"Операционные",Docs[Дата],">="&B$6,Docs[Дата],"<"&EDATE(B$6,1)) -> 245000 | C10: =SUMIFS(Docs[Сумма],Docs[Дата],"<="&ДатаОтчета,Docs[Статус],"Проведён",Docs[Вид],"Операционные",Docs[Дата],">="&C$6,Docs[Дата],"<"&EDATE(C$6,1)) -> 245000 | D10: =SUMIFS(Docs[Сумма],Docs[Дата],"<="&ДатаОтчета,Docs[Статус],"Проведён",Docs[Вид],"Операционные",Docs[Дата],">="&D$6,Docs[Дата],"<"&EDATE(D$6,1)) -> 245000 | E10: =SUMIFS(Docs[Сумма],Docs[Дата],"<="&ДатаОтчета,Docs[Статус],"Проведён",Docs[Вид],"Операционные",Docs[Дата],">="&E$6,Docs[Дата],"<"&EDATE(E$6,1)) -> 245000 | F10: =SUMIFS(Docs[Сумма],Docs[Дата],"<="&ДатаОтчета,Docs[Статус],"Проведён",Docs[Вид],"Операционные",Docs[Дата],">="&F$6,Docs[Дата],"<"&EDATE(F$6,1)) -> 245000 | G10: =SUMIFS(Docs[Сумма],Docs[Дата],"<="&ДатаОтчета,Docs[Статус],"Проведён",Docs[Вид],"Операционные",Docs[Дата],">="&G$6,Docs[Дата],"<"&EDATE(G$6,1)) -> 245000 | H10: =SUMIFS(Docs[Сумма],Docs[Дата],"<="&ДатаОтчета,Docs[Статус],"Проведён",Docs[Вид],"Операционные",Docs[Дата],">="&H$6,Docs[Дата],"<"&EDATE(H$6,1)) -> 245000 | I10: =SUMIFS(Docs[Сумма],Docs[Дата],"<="&ДатаОтчета,Docs[Статус],"Проведён",Docs[Вид],"Операционные",Docs[Дата],">="&I$6,Docs[Дата],"<"&EDATE(I$6,1)) -> 310000 | ... M10: =SUMIFS(Docs[Сумма],Docs[Дата],"<="&ДатаОтчета,Docs[Статус],"Проведён",Docs[Вид],"Операционные",Docs[Дата],">="&M$6,Docs[Дата],"<"&EDATE(M$6,1)) -> 245000 | N10: =SUM(B10:M10) -> 3005000
A11: Амортизация | B11: =SUM(АКТИВЫ!K7:K56) -> 0 | C11: =SUM(АКТИВЫ!L7:L56) -> 5000 | D11: =SUM(АКТИВЫ!M7:M56) -> 5000 | E11: =SUM(АКТИВЫ!N7:N56) -> 5000 | F11: =SUM(АКТИВЫ!O7:O56) -> 5000 | G11: =SUM(АКТИВЫ!P7:P56) -> 5000 | H11: =SUM(АКТИВЫ!Q7:Q56) -> 5000 | I11: =SUM(АКТИВЫ!R7:R56) -> 5000 | ... M11: =SUM(АКТИВЫ!V7:V56) -> 5000 | N11: =SUM(B11:M11) -> 55000
A12: Операционная прибыль | B12: =B9-B10-B11 -> 40600 | C12: =C9-C10-C11 -> -127600 | D12: =D9-D10-D11 -> 93800 | E12: =E9-E10-E11 -> 124000 | F12: =F9-F10-F11 -> 144400 | G12: =G9-G10-G11 -> 171600 | H12: =H9-H10-H11 -> 151200 | I12: =I9-I10-I11 -> -172200 | ... M12: =M9-M10-M11 -> 307600 | N12: =SUM(B12:M12) -> 1425000
A13: Проценты | B13: =SUMIFS(Docs[Сумма],Docs[Дата],"<="&ДатаОтчета,Docs[Статус],"Проведён",Docs[Вид],"Проценты",Docs[Дата],">="&B$6,Docs[Дата],"<"&EDATE(B$6,1)) -> 4500 | C13: =SUMIFS(Docs[Сумма],Docs[Дата],"<="&ДатаОтчета,Docs[Статус],"Проведён",Docs[Вид],"Проценты",Docs[Дата],">="&C$6,Docs[Дата],"<"&EDATE(C$6,1)) -> 4342.84 | D13: =SUMIFS(Docs[Сумма],Docs[Дата],"<="&ДатаОтчета,Docs[Статус],"Проведён",Docs[Вид],"Проценты",Docs[Дата],">="&D$6,Docs[Дата],"<"&EDATE(D$6,1)) -> 4183.33 | E13: =SUMIFS(Docs[Сумма],Docs[Дата],"<="&ДатаОтчета,Docs[Статус],"Проведён",Docs[Вид],"Проценты",Docs[Дата],">="&E$6,Docs[Дата],"<"&EDATE(E$6,1)) -> 4021.42 | F13: =SUMIFS(Docs[Сумма],Docs[Дата],"<="&ДатаОтчета,Docs[Статус],"Проведён",Docs[Вид],"Проценты",Docs[Дата],">="&F$6,Docs[Дата],"<"&EDATE(F$6,1)) -> 3857.08 | G13: =SUMIFS(Docs[Сумма],Docs[Дата],"<="&ДатаОтчета,Docs[Статус],"Проведён",Docs[Вид],"Проценты",Docs[Дата],">="&G$6,Docs[Дата],"<"&EDATE(G$6,1)) -> 3690.28 | H13: =SUMIFS(Docs[Сумма],Docs[Дата],"<="&ДатаОтчета,Docs[Статус],"Проведён",Docs[Вид],"Проценты",Docs[Дата],">="&H$6,Docs[Дата],"<"&EDATE(H$6,1)) -> 3145.97 | I13: =SUMIFS(Docs[Сумма],Docs[Дата],"<="&ДатаОтчета,Docs[Статус],"Проведён",Docs[Вид],"Проценты",Docs[Дата],">="&I$6,Docs[Дата],"<"&EDATE(I$6,1)) -> 2968.5 | ... M13: =SUMIFS(Docs[Сумма],Docs[Дата],"<="&ДатаОтчета,Docs[Статус],"Проведён",Docs[Вид],"Проценты",Docs[Дата],">="&M$6,Docs[Дата],"<"&EDATE(M$6,1)) -> 2231.61 | N13: =SUM(B13:M13) -> 40754.91
A14: Налог на результат | B14: =НАЛОГИ!H7 -> 25200 | C14: =НАЛОГИ!H8 -> 10800 | D14: =НАЛОГИ!H9 -> 30420 | E14: =НАЛОГИ!H10 -> 33000 | F14: =НАЛОГИ!H11 -> 34800 | G14: =НАЛОГИ!H12 -> 37200 | H14: =НАЛОГИ!H13 -> 35400 | I14: =НАЛОГИ!H14 -> 12600 | J14: =НАЛОГИ!H15 -> 39000 | K14: =НАЛОГИ!H16 -> 42600 | L14: =НАЛОГИ!H17 -> 45600 | M14: =НАЛОГИ!H18 -> 45657.6 | N14: =SUM(B14:M14) -> 392277.6
A15: Взносы ИП за себя | B15: =НАЛОГИ!L7 -> 5982.5 | C15: =НАЛОГИ!L8 -> 6582.5 | D15: =НАЛОГИ!L9 -> 9852.5 | E15: =НАЛОГИ!L10 -> 10282.5 | F15: =НАЛОГИ!L11 -> 10582.5 | G15: =НАЛОГИ!L12 -> 10982.5 | H15: =НАЛОГИ!L13 -> 10682.5 | I15: =НАЛОГИ!L14 -> 6882.5 | J15: =НАЛОГИ!L15 -> 11282.5 | K15: =НАЛОГИ!L16 -> 11882.5 | L15: =НАЛОГИ!L17 -> 12382.5 | M15: =НАЛОГИ!L18 -> 12392.1 | N15: =SUM(B15:M15) -> 119769.6
A16: Итоговый результат | B16: =B12-SUM(B13:B15) -> 4917.5 | C16: =C12-SUM(C13:C15) -> -149325.34 | D16: =D12-SUM(D13:D15) -> 49344.17 | E16: =E12-SUM(E13:E15) -> 76696.08 | F16: =F12-SUM(F13:F15) -> 95160.42 | G16: =G12-SUM(G13:G15) -> 119727.22 | H16: =H12-SUM(H13:H15) -> 101971.53 | I16: =I12-SUM(I13:I15) -> -194651 | ... M16: =M12-SUM(M13:M15) -> 247318.69 | N16: =SUM(B16:M16) -> 872197.89
A17: Итоговая рентабельность | B17: =IF(B7=0,"н/д",B16/B7) -> 0.011708333 | C17: =IF(C7=0,"н/д",C16/C7) -> -0.82958522 | D17: =IF(D7=0,"н/д",D16/D7) -> 0.097325779 | E17: =IF(E7=0,"н/д",E16/E7) -> 0.13944742 | F17: =IF(F7=0,"н/д",F16/F7) -> 0.16406969 | G17: =IF(G7=0,"н/д",G16/G7) -> 0.19310842 | H17: =IF(H7=0,"н/д",H16/H7) -> 0.1728331 | I17: =IF(I7=0,"н/д",I16/I7) -> -0.92690952 | ... N17: =IF(N7=0,"н/д",N16/N7) -> 0.13221129
A18: Убыточный месяц | B18: =IF(B16<0,"Убыток","Прибыль / ноль") -> Прибыль / ноль | C18: =IF(C16<0,"Убыток","Прибыль / ноль") -> Убыток | D18: =IF(D16<0,"Убыток","Прибыль / ноль") -> Прибыль / ноль | E18: =IF(E16<0,"Убыток","Прибыль / ноль") -> Прибыль / ноль | F18: =IF(F16<0,"Убыток","Прибыль / ноль") -> Прибыль / ноль | G18: =IF(G16<0,"Убыток","Прибыль / ноль") -> Прибыль / ноль | H18: =IF(H16<0,"Убыток","Прибыль / ноль") -> Прибыль / ноль | I18: =IF(I16<0,"Убыток","Прибыль / ноль") -> Убыток | ... M18: =IF(M16<0,"Убыток","Прибыль / ноль") -> Прибыль / ноль | N18: =COUNTIF(B16:M16,"<0") -> 2

Sheet БАЛАНС
A1: Главная панель | D1: Настройки | F1: Контроль
A2: БАЛАНС
A3: LEO STUDIO • Управленческий учёт • RUB
A6: Статья | B6: Сумма | C6: Методика
A7: Денежные средства | B7: =СЧЕТА!B19 -> 1675043.2 | C7: Все счета, включая резерв
A8: Дебиторская задолженность | B8: =НАСТРОЙКИ!B36+SUMIFS(Docs[Остаток],Docs[Дата],"<="&ДатаОтчета,Docs[Статус],"Проведён",Docs[Тип долга],"ДЗ") -> 59040 | C8: Сумма непогашенных начислений
A9: Основные средства нетто | B9: =АКТИВЫ!B59 -> 125000 | C9: Стоимость минус амортизация
A10: Прочие активы | B10: =НАСТРОЙКИ!B38+MAX(0,-НАЛОГИ!J18)+MAX(0,НАЛОГИ!B26-НАЛОГИ!B25)+MAX(0,-НАЛОГИ!B30) -> 0 | C10: Начальные активы и налоговые переплаты
A11: АКТИВЫ | B11: =SUM(B7:B10) -> 1859083.2
A14: Кредиторская задолженность | B14: =НАСТРОЙКИ!B37+SUMIFS(Docs[Остаток],Docs[Дата],"<="&ДатаОтчета,Docs[Статус],"Проведён",Docs[Тип долга],"КЗ") -> 131200 | C14: Включает начисленные дивиденды
A15: Кредиты и займы | B15: =НАСТРОЙКИ!B33+SUMIFS(Cash[Поток],Cash[Дата],"<="&ДатаОтчета,Cash[Статус],"Проведён",Cash[Тип],"Получение кредита")+SUMIFS(Cash[Поток],Cash[Дата],"<="&ДатаОтчета,Cash[Статус],"Проведён",Cash[Тип],"Тело кредита")+SUMIFS(Cash[Поток],Cash[Дата],"<="&ДатаОтчета,Cash[Статус],"Проведён",Cash[Тип],"Займ участника")+SUMIFS(Cash[Поток],Cash[Дата],"<="&ДатаОтчета,Cash[Статус],"Проведён",Cash[Тип],"Возврат займа") -> 136028.15 | C15: Тело отдельно от процентов
A16: Налоги и взносы | B16: =MAX(0,НАЛОГИ!J18)+НАЛОГИ!B27+MAX(0,НАЛОГИ!B30) -> 319657.2 | C16: НДФЛ сотрудников уже в КЗ
A17: Прочие обязательства | B17: =НАСТРОЙКИ!B39 -> 0 | C17: Начальное сальдо
A18: ОБЯЗАТЕЛЬСТВА | B18: =SUM(B14:B17) -> 586885.35
A21: Начальный капитал | B21: =НАСТРОЙКИ!B32 -> 0 | C21: Явный ввод, не подгонка баланса
A22: Взносы собственников | B22: =SUMIFS(Cash[Поток],Cash[Дата],"<="&ДатаОтчета,Cash[Статус],"Проведён",Cash[Тип],"Взнос собственника") -> 500000 | C22: Для ООО: уставный капитал / вклад с документом
A23: Накопленный результат | B23: =НАСТРОЙКИ!B35+ОПиУ!N16 -> 872197.89 | C23: Начальная прибыль плюс результат года
A24: Изъятия / дивиденды | B24: =-SUMIFS(Cash[Поток],Cash[Дата],"<="&ДатаОтчета,Cash[Статус],"Проведён",Cash[Тип],"Вывод ИП")+SUMIFS(Docs[Сумма],Docs[Дата],"<="&ДатаОтчета,Docs[Статус],"Проведён",Docs[Вид],"Дивиденды") -> 100000 | C24: Уменьшение капитала, не расход
A25: КАПИТАЛ | B25: =B21+B22+B23-B24 -> 1272197.9
A27: Обязательства + капитал | B27: =B18+B25 -> 1859083.2
A28: Расхождение | B28: =B11-B27 -> 0 | C28: Если не ноль: проверьте начальные остатки, связи, активы
A29: Состояние | B29: =IF(ABS(B28)<0.02,"Баланс сходится","ОШИБКА: баланс не сходится") -> Баланс сходится

Sheet НАЛОГИ
A1: Главная панель | D1: Настройки | F1: Контроль
A2: НАЛОГИ
A3: LEO STUDIO • Управленческий учёт • RUB
A4: Область расчёта | B4: =IF(OR(AND(Форма<>"ИП",Форма<>"ООО"),AND(Режим<>"УСН Доходы",Режим<>"УСН Д-Р",Режим<>"НПД",Режим<>"Ручной")),"РУЧНОЙ: неизвестная форма или режим",IF(Год<>2026,"РУЧНОЙ: обновите правила года",IF(AND(Форма="ООО",Режим="НПД"),"ОШИБКА: ООО не вправе НПД",IF(Режим="Ручной","РУЧНОЙ РЕЖИМ",IF(AND(Режим="НПД",OR(Сотрудники="Да",НАСТРОЙКИ!B27<>"Да",SUM(Cash[Налоговый доход])>ЛимитНПД)),"РУЧНОЙ: условия НПД",IF(AND(Режим<>"НПД",OR(ДоходПрошлыйГод>ПорогНДС,SUM(Cash[Налоговый доход])>ПорогНДС)),"РУЧНОЙ: возникновение НДС",IF(НАСТРОЙКИ!B28<>"Да","РУЧНОЙ: запрет автоналога","ПРЕДВАРИТЕЛЬНЫЙ РАСЧЁТ"))))))) -> ПРЕДВАРИТЕЛЬНЫЙ РАСЧЁТ
A6: Месяц | B6: Доход ФЛ НИ | C6: Доход ЮЛ НИ | D6: Расход УСН НИ | E6: База Д-Р НИ | F6: Вычет взносов ввод | G6: Налог НИ | H6: Начислено месяц | I6: Уплачено месяц | J6: Налог сальдо | K6: Взносы ИП НИ | L6: Взносы ИП месяц | M6: НДС ввод | N6: Налог вручную
A7: =DATE(Год,1,1) -> 46023 | B7: =SUMIFS(Cash[Налоговый доход],Cash[Дата],">="&DATE(Год,1,1),Cash[Дата],"<="&MIN(EOMONTH(A7,0),ДатаОтчета),Cash[Тип лица],"ФЛ") -> 42000 | C7: =SUMIFS(Cash[Налоговый доход],Cash[Дата],">="&DATE(Год,1,1),Cash[Дата],"<="&MIN(EOMONTH(A7,0),ДатаОтчета),Cash[Тип лица],"<>ФЛ") -> 378000 | D7: =SUMIFS(Cash[Налоговый расход],Cash[Дата],">="&DATE(Год,1,1),Cash[Дата],"<="&MIN(EOMONTH(A7,0),ДатаОтчета),Cash[Статус],"Проведён",Cash[Тип],"<>Возврат поставщика")-SUMIFS(Cash[Налоговый расход],Cash[Дата],">="&DATE(Год,1,1),Cash[Дата],"<="&MIN(EOMONTH(A7,0),ДатаОтчета),Cash[Статус],"Проведён",Cash[Тип],"Возврат поставщика") -> 383900 | E7: =MAX(0,B7+C7-D7) -> 36100 | F7: 0 | G7: =IF(A7>ДатаОтчета,0,IF($B$4="ПРЕДВАРИТЕЛЬНЫЙ РАСЧЁТ",ROUND(IF(Режим="УСН Доходы",MAX(0,(B7+C7)*СтавкаДоход-IF(OR(Форма="ООО",Сотрудники="Да"),MIN((B7+C7)*СтавкаДоход*0.5,SUM($F$7:F7)+IF(MONTH(A7)=12,ВычетУСН,0)),MIN((B7+C7)*СтавкаДоход,SUM($F$7:F7)+IF(MONTH(A7)=12,ВычетУСН,0)))),IF(Режим="УСН Д-Р",MAX(E7*СтавкаДР,IF(MONTH(A7)=12,(B7+C7)*0.01,0)),MAX(0,B7*СтавкаНПДФЛ+C7*СтавкаНПДЮЛ-MIN(БонусНПД,B7*0.01+C7*0.02)))),2),SUM($N$7:N7))) -> 25200 | H7: =G7 -> 25200 | I7: =SUMIFS(Cash[Сумма],Cash[Дата],"<="&ДатаОтчета,Cash[Статус],"Проведён",Cash[Тип],"Налог",Cash[Дата],">="&A7,Cash[Дата],"<"&EDATE(A7,1),Cash[Категория],"<>НДС") -> 0 | J7: =НАСТРОЙКИ!$B$34+G7-SUM($I$7:I7) -> 25200 | K7: =IF(A7>ДатаОтчета,0,IF(AND(Форма="ИП",Режим<>"НПД",НАСТРОЙКИ!B28="Да"),IF(A7>ДатаОтчета,0,ФиксВзносы*MONTH(A7)/12+MIN(МаксВзносы,MAX(0,IF(Режим="УСН Д-Р",E7,B7+C7)-300000)*0.01)),0)) -> 5982.5 | L7: =K7 -> 5982.5 | M7: 0 | N7: 0
A8: =DATE(Год,2,1) -> 46054 | B8: =SUMIFS(Cash[Налоговый доход],Cash[Дата],">="&DATE(Год,1,1),Cash[Дата],"<="&MIN(EOMONTH(A8,0),ДатаОтчета),Cash[Тип лица],"ФЛ") -> 60000 | C8: =SUMIFS(Cash[Налоговый доход],Cash[Дата],">="&DATE(Год,1,1),Cash[Дата],"<="&MIN(EOMONTH(A8,0),ДатаОтчета),Cash[Тип лица],"<>ФЛ") -> 540000 | D8: =SUMIFS(Cash[Налоговый расход],Cash[Дата],">="&DATE(Год,1,1),Cash[Дата],"<="&MIN(EOMONTH(A8,0),ДатаОтчета),Cash[Статус],"Проведён",Cash[Тип],"<>Возврат поставщика")-SUMIFS(Cash[Налоговый расход],Cash[Дата],">="&DATE(Год,1,1),Cash[Дата],"<="&MIN(EOMONTH(A8,0),ДатаОтчета),Cash[Статус],"Проведён",Cash[Тип],"Возврат поставщика") -> 690842.84 | E8: =MAX(0,B8+C8-D8) -> 0 | F8: 0 | G8: =IF(A8>ДатаОтчета,G7,IF($B$4="ПРЕДВАРИТЕЛЬНЫЙ РАСЧЁТ",ROUND(IF(Режим="УСН Доходы",MAX(0,(B8+C8)*СтавкаДоход-IF(OR(Форма="ООО",Сотрудники="Да"),MIN((B8+C8)*СтавкаДоход*0.5,SUM($F$7:F8)+IF(MONTH(A8)=12,ВычетУСН,0)),MIN((B8+C8)*СтавкаДоход,SUM($F$7:F8)+IF(MONTH(A8)=12,ВычетУСН,0)))),IF(Режим="УСН Д-Р",MAX(E8*СтавкаДР,IF(MONTH(A8)=12,(B8+C8)*0.01,0)),MAX(0,B8*СтавкаНПДФЛ+C8*СтавкаНПДЮЛ-MIN(БонусНПД,B8*0.01+C8*0.02)))),2),SUM($N$7:N8))) -> 36000 | H8: =G8-G7 -> 10800 | I8: =SUMIFS(Cash[Сумма],Cash[Дата],"<="&ДатаОтчета,Cash[Статус],"Проведён",Cash[Тип],"Налог",Cash[Дата],">="&A8,Cash[Дата],"<"&EDATE(A8,1),Cash[Категория],"<>НДС") -> 0 | J8: =НАСТРОЙКИ!$B$34+G8-SUM($I$7:I8) -> 36000 | K8: =IF(A8>ДатаОтчета,K7,IF(AND(Форма="ИП",Режим<>"НПД",НАСТРОЙКИ!B28="Да"),IF(A8>ДатаОтчета,0,ФиксВзносы*MONTH(A8)/12+MIN(МаксВзносы,MAX(0,IF(Режим="УСН Д-Р",E8,B8+C8)-300000)*0.01)),0)) -> 12565 | L8: =K8-K7 -> 6582.5 | M8: 0 | N8: 0
A9: =DATE(Год,3,1) -> 46082 | B9: =SUMIFS(Cash[Налоговый доход],Cash[Дата],">="&DATE(Год,1,1),Cash[Дата],"<="&MIN(EOMONTH(A9,0),ДатаОтчета),Cash[Тип лица],"ФЛ") -> 111000 | C9: =SUMIFS(Cash[Налоговый доход],Cash[Дата],">="&DATE(Год,1,1),Cash[Дата],"<="&MIN(EOMONTH(A9,0),ДатаОтчета),Cash[Тип лица],"<>ФЛ") -> 996000 | D9: =SUMIFS(Cash[Налоговый расход],Cash[Дата],">="&DATE(Год,1,1),Cash[Дата],"<="&MIN(EOMONTH(A9,0),ДатаОтчета),Cash[Статус],"Проведён",Cash[Тип],"<>Возврат поставщика")-SUMIFS(Cash[Налоговый расход],Cash[Дата],">="&DATE(Год,1,1),Cash[Дата],"<="&MIN(EOMONTH(A9,0),ДатаОтчета),Cash[Статус],"Проведён",Cash[Тип],"Возврат поставщика") -> 1103226.2 | E9: =MAX(0,B9+C9-D9) -> 3773.83 | F9: 0 | G9: =IF(A9>ДатаОтчета,G8,IF($B$4="ПРЕДВАРИТЕЛЬНЫЙ РАСЧЁТ",ROUND(IF(Режим="УСН Доходы",MAX(0,(B9+C9)*СтавкаДоход-IF(OR(Форма="ООО",Сотрудники="Да"),MIN((B9+C9)*СтавкаДоход*0.5,SUM($F$7:F9)+IF(MONTH(A9)=12,ВычетУСН,0)),MIN((B9+C9)*СтавкаДоход,SUM($F$7:F9)+IF(MONTH(A9)=12,ВычетУСН,0)))),IF(Режим="УСН Д-Р",MAX(E9*СтавкаДР,IF(MONTH(A9)=12,(B9+C9)*0.01,0)),MAX(0,B9*СтавкаНПДФЛ+C9*СтавкаНПДЮЛ-MIN(БонусНПД,B9*0.01+C9*0.02)))),2),SUM($N$7:N9))) -> 66420 | H9: =G9-G8 -> 30420 | I9: =SUMIFS(Cash[Сумма],Cash[Дата],"<="&ДатаОтчета,Cash[Статус],"Проведён",Cash[Тип],"Налог",Cash[Дата],">="&A9,Cash[Дата],"<"&EDATE(A9,1),Cash[Категория],"<>НДС") -> 0 | J9: =НАСТРОЙКИ!$B$34+G9-SUM($I$7:I9) -> 66420 | K9: =IF(A9>ДатаОтчета,K8,IF(AND(Форма="ИП",Режим<>"НПД",НАСТРОЙКИ!B28="Да"),IF(A9>ДатаОтчета,0,ФиксВзносы*MONTH(A9)/12+MIN(МаксВзносы,MAX(0,IF(Режим="УСН Д-Р",E9,B9+C9)-300000)*0.01)),0)) -> 22417.5 | L9: =K9-K8 -> 9852.5 | M9: 0 | N9: 0
A10: =DATE(Год,4,1) -> 46113 | B10: =SUMIFS(Cash[Налоговый доход],Cash[Дата],">="&DATE(Год,1,1),Cash[Дата],"<="&MIN(EOMONTH(A10,0),ДатаОтчета),Cash[Тип лица],"ФЛ") -> 166000 | C10: =SUMIFS(Cash[Налоговый доход],Cash[Дата],">="&DATE(Год,1,1),Cash[Дата],"<="&MIN(EOMONTH(A10,0),ДатаОтчета),Cash[Тип лица],"<>ФЛ") -> 1491000 | D10: =SUMIFS(Cash[Налоговый расход],Cash[Дата],">="&DATE(Год,1,1),Cash[Дата],"<="&MIN(EOMONTH(A10,0),ДатаОтчета),Cash[Статус],"Проведён",Cash[Тип],"<>Возврат поставщика")-SUMIFS(Cash[Налоговый расход],Cash[Дата],">="&DATE(Год,1,1),Cash[Дата],"<="&MIN(EOMONTH(A10,0),ДатаОтчета),Cash[Статус],"Проведён",Cash[Тип],"Возврат поставщика") -> 1528247.6 | E10: =MAX(0,B10+C10-D10) -> 128752.41 | F10: 0 | G10: =IF(A10>ДатаОтчета,G9,IF($B$4="ПРЕДВАРИТЕЛЬНЫЙ РАСЧЁТ",ROUND(IF(Режим="УСН Доходы",MAX(0,(B10+C10)*СтавкаДоход-IF(OR(Форма="ООО",Сотрудники="Да"),MIN((B10+C10)*СтавкаДоход*0.5,SUM($F$7:F10)+IF(MONTH(A10)=12,ВычетУСН,0)),MIN((B10+C10)*СтавкаДоход,SUM($F$7:F10)+IF(MONTH(A10)=12,ВычетУСН,0)))),IF(Режим="УСН Д-Р",MAX(E10*СтавкаДР,IF(MONTH(A10)=12,(B10+C10)*0.01,0)),MAX(0,B10*СтавкаНПДФЛ+C10*СтавкаНПДЮЛ-MIN(БонусНПД,B10*0.01+C10*0.02)))),2),SUM($N$7:N10))) -> 99420 | H10: =G10-G9 -> 33000 | I10: =SUMIFS(Cash[Сумма],Cash[Дата],"<="&ДатаОтчета,Cash[Статус],"Проведён",Cash[Тип],"Налог",Cash[Дата],">="&A10,Cash[Дата],"<"&EDATE(A10,1),Cash[Категория],"<>НДС") -> 45000 | J10: =НАСТРОЙКИ!$B$34+G10-SUM($I$7:I10) -> 54420 | K10: =IF(A10>ДатаОтчета,K9,IF(AND(Форма="ИП",Режим<>"НПД",НАСТРОЙКИ!B28="Да"),IF(A10>ДатаОтчета,0,ФиксВзносы*MONTH(A10)/12+MIN(МаксВзносы,MAX(0,IF(Режим="УСН Д-Р",E10,B10+C10)-300000)*0.01)),0)) -> 32700 | L10: =K10-K9 -> 10282.5 | M10: 0 | N10: 0
A11: =DATE(Год,5,1) -> 46143 | B11: =SUMIFS(Cash[Налоговый доход],Cash[Дата],">="&DATE(Год,1,1),Cash[Дата],"<="&MIN(EOMONTH(A11,0),ДатаОтчета),Cash[Тип лица],"ФЛ") -> 224000 | C11: =SUMIFS(Cash[Налоговый доход],Cash[Дата],">="&DATE(Год,1,1),Cash[Дата],"<="&MIN(EOMONTH(A11,0),ДатаОтчета),Cash[Тип лица],"<>ФЛ") -> 2013000 | D11: =SUMIFS(Cash[Налоговый расход],Cash[Дата],">="&DATE(Год,1,1),Cash[Дата],"<="&MIN(EOMONTH(A11,0),ДатаОтчета),Cash[Статус],"Проведён",Cash[Тип],"<>Возврат поставщика")-SUMIFS(Cash[Налоговый расход],Cash[Дата],">="&DATE(Год,1,1),Cash[Дата],"<="&MIN(EOMONTH(A11,0),ДатаОтчета),Cash[Статус],"Проведён",Cash[Тип],"Возврат поставщика") -> 1962704.7 | E11: =MAX(0,B11+C11-D11) -> 274295.33 | F11: 0 | G11: =IF(A11>ДатаОтчета,G10,IF($B$4="ПРЕДВАРИТЕЛЬНЫЙ РАСЧЁТ",ROUND(IF(Режим="УСН Доходы",MAX(0,(B11+C11)*СтавкаДоход-IF(OR(Форма="ООО",Сотрудники="Да"),MIN((B11+C11)*СтавкаДоход*0.5,SUM($F$7:F11)+IF(MONTH(A11)=12,ВычетУСН,0)),MIN((B11+C11)*СтавкаДоход,SUM($F$7:F11)+IF(MONTH(A11)=12,ВычетУСН,0)))),IF(Режим="УСН Д-Р",MAX(E11*СтавкаДР,IF(MONTH(A11)=12,(B11+C11)*0.01,0)),MAX(0,B11*СтавкаНПДФЛ+C11*СтавкаНПДЮЛ-MIN(БонусНПД,B11*0.01+C11*0.02)))),2),SUM($N$7:N11))) -> 134220 | H11: =G11-G10 -> 34800 | I11: =SUMIFS(Cash[Сумма],Cash[Дата],"<="&ДатаОтчета,Cash[Статус],"Проведён",Cash[Тип],"Налог",Cash[Дата],">="&A11,Cash[Дата],"<"&EDATE(A11,1),Cash[Категория],"<>НДС") -> 0 | J11: =НАСТРОЙКИ!$B$34+G11-SUM($I$7:I11) -> 89220 | K11: =IF(A11>ДатаОтчета,K10,IF(AND(Форма="ИП",Режим<>"НПД",НАСТРОЙКИ!B28="Да"),IF(A11>ДатаОтчета,0,ФиксВзносы*MONTH(A11)/12+MIN(МаксВзносы,MAX(0,IF(Режим="УСН Д-Р",E11,B11+C11)-300000)*0.01)),0)) -> 43282.5 | L11: =K11-K10 -> 10582.5 | M11: 0 | N11: 0
A12: =DATE(Год,6,1) -> 46174 | B12: =SUMIFS(Cash[Налоговый доход],Cash[Дата],">="&DATE(Год,1,1),Cash[Дата],"<="&MIN(EOMONTH(A12,0),ДатаОтчета),Cash[Тип лица],"ФЛ") -> 286000 | C12: =SUMIFS(Cash[Налоговый доход],Cash[Дата],">="&DATE(Год,1,1),Cash[Дата],"<="&MIN(EOMONTH(A12,0),ДатаОтчета),Cash[Тип лица],"<>ФЛ") -> 2571000 | D12: =SUMIFS(Cash[Налоговый расход],Cash[Дата],">="&DATE(Год,1,1),Cash[Дата],"<="&MIN(EOMONTH(A12,0),ДатаОтчета),Cash[Статус],"Проведён",Cash[Тип],"<>Возврат поставщика")-SUMIFS(Cash[Налоговый расход],Cash[Дата],">="&DATE(Год,1,1),Cash[Дата],"<="&MIN(EOMONTH(A12,0),ДатаОтчета),Cash[Статус],"Проведён",Cash[Тип],"Возврат поставщика") -> 2409794.9 | E12: =MAX(0,B12+C12-D12) -> 447205.05 | F12: 0 | G12: =IF(A12>ДатаОтчета,G11,IF($B$4="ПРЕДВАРИТЕЛЬНЫЙ РАСЧЁТ",ROUND(IF(Режим="УСН Доходы",MAX(0,(B12+C12)*СтавкаДоход-IF(OR(Форма="ООО",Сотрудники="Да"),MIN((B12+C12)*СтавкаДоход*0.5,SUM($F$7:F12)+IF(MONTH(A12)=12,ВычетУСН,0)),MIN((B12+C12)*СтавкаДоход,SUM($F$7:F12)+IF(MONTH(A12)=12,ВычетУСН,0)))),IF(Режим="УСН Д-Р",MAX(E12*СтавкаДР,IF(MONTH(A12)=12,(B12+C12)*0.01,0)),MAX(0,B12*СтавкаНПДФЛ+C12*СтавкаНПДЮЛ-MIN(БонусНПД,B12*0.01+C12*0.02)))),2),SUM($N$7:N12))) -> 171420 | H12: =G12-G11 -> 37200 | I12: =SUMIFS(Cash[Сумма],Cash[Дата],"<="&ДатаОтчета,Cash[Статус],"Проведён",Cash[Тип],"Налог",Cash[Дата],">="&A12,Cash[Дата],"<"&EDATE(A12,1),Cash[Категория],"<>НДС") -> 0 | J12: =НАСТРОЙКИ!$B$34+G12-SUM($I$7:I12) -> 126420 | K12: =IF(A12>ДатаОтчета,K11,IF(AND(Форма="ИП",Режим<>"НПД",НАСТРОЙКИ!B28="Да"),IF(A12>ДатаОтчета,0,ФиксВзносы*MONTH(A12)/12+MIN(МаксВзносы,MAX(0,IF(Режим="УСН Д-Р",E12,B12+C12)-300000)*0.01)),0)) -> 54265 | L12: =K12-K11 -> 10982.5 | M12: 0 | N12: 0
A13: =DATE(Год,7,1) -> 46204 | B13: =SUMIFS(Cash[Налоговый доход],Cash[Дата],">="&DATE(Год,1,1),Cash[Дата],"<="&MIN(EOMONTH(A13,0),ДатаОтчета),Cash[Тип лица],"ФЛ") -> 345000 | C13: =SUMIFS(Cash[Налоговый доход],Cash[Дата],">="&DATE(Год,1,1),Cash[Дата],"<="&MIN(EOMONTH(A13,0),ДатаОтчета),Cash[Тип лица],"<>ФЛ") -> 3102000 | D13: =SUMIFS(Cash[Налоговый расход],Cash[Дата],">="&DATE(Год,1,1),Cash[Дата],"<="&MIN(EOMONTH(A13,0),ДатаОтчета),Cash[Статус],"Проведён",Cash[Тип],"<>Возврат поставщика")-SUMIFS(Cash[Налоговый расход],Cash[Дата],">="&DATE(Год,1,1),Cash[Дата],"<="&MIN(EOMONTH(A13,0),ДатаОтчета),Cash[Статус],"Проведён",Cash[Тип],"Возврат поставщика") -> 2846740.9 | E13: =MAX(0,B13+C13-D13) -> 600259.08 | F13: 0 | G13: =IF(A13>ДатаОтчета,G12,IF($B$4="ПРЕДВАРИТЕЛЬНЫЙ РАСЧЁТ",ROUND(IF(Режим="УСН Доходы",MAX(0,(B13+C13)*СтавкаДоход-IF(OR(Форма="ООО",Сотрудники="Да"),MIN((B13+C13)*СтавкаДоход*0.5,SUM($F$7:F13)+IF(MONTH(A13)=12,ВычетУСН,0)),MIN((B13+C13)*СтавкаДоход,SUM($F$7:F13)+IF(MONTH(A13)=12,ВычетУСН,0)))),IF(Режим="УСН Д-Р",MAX(E13*СтавкаДР,IF(MONTH(A13)=12,(B13+C13)*0.01,0)),MAX(0,B13*СтавкаНПДФЛ+C13*СтавкаНПДЮЛ-MIN(БонусНПД,B13*0.01+C13*0.02)))),2),SUM($N$7:N13))) -> 206820 | H13: =G13-G12 -> 35400 | I13: =SUMIFS(Cash[Сумма],Cash[Дата],"<="&ДатаОтчета,Cash[Статус],"Проведён",Cash[Тип],"Налог",Cash[Дата],">="&A13,Cash[Дата],"<"&EDATE(A13,1),Cash[Категория],"<>НДС") -> 45000 | J13: =НАСТРОЙКИ!$B$34+G13-SUM($I$7:I13) -> 116820 | K13: =IF(A13>ДатаОтчета,K12,IF(AND(Форма="ИП",Режим<>"НПД",НАСТРОЙКИ!B28="Да"),IF(A13>ДатаОтчета,0,ФиксВзносы*MONTH(A13)/12+MIN(МаксВзносы,MAX(0,IF(Режим="УСН Д-Р",E13,B13+C13)-300000)*0.01)),0)) -> 64947.5 | L13: =K13-K12 -> 10682.5 | M13: 0 | N13: 0
A14: =DATE(Год,8,1) -> 46235 | B14: =SUMIFS(Cash[Налоговый доход],Cash[Дата],">="&DATE(Год,1,1),Cash[Дата],"<="&MIN(EOMONTH(A14,0),ДатаОтчета),Cash[Тип лица],"ФЛ") -> 366000 | C14: =SUMIFS(Cash[Налоговый доход],Cash[Дата],">="&DATE(Год,1,1),Cash[Дата],"<="&MIN(EOMONTH(A14,0),ДатаОтчета),Cash[Тип лица],"<>ФЛ") -> 3291000 | D14: =SUMIFS(Cash[Налоговый расход],Cash[Дата],">="&DATE(Год,1,1),Cash[Дата],"<="&MIN(EOMONTH(A14,0),ДатаОтчета),Cash[Статус],"Проведён",Cash[Тип],"<>Возврат поставщика")-SUMIFS(Cash[Налоговый расход],Cash[Дата],">="&DATE(Год,1,1),Cash[Дата],"<="&MIN(EOMONTH(A14,0),ДатаОтчета),Cash[Статус],"Проведён",Cash[Тип],"Возврат поставщика") -> 3226909.4 | E14: =MAX(0,B14+C14-D14) -> 430090.58 | F14: 0 | G14: =IF(A14>ДатаОтчета,G13,IF($B$4="ПРЕДВАРИТЕЛЬНЫЙ РАСЧЁТ",ROUND(IF(Режим="УСН Доходы",MAX(0,(B14+C14)*СтавкаДоход-IF(OR(Форма="ООО",Сотрудники="Да"),MIN((B14+C14)*СтавкаДоход*0.5,SUM($F$7:F14)+IF(MONTH(A14)=12,ВычетУСН,0)),MIN((B14+C14)*СтавкаДоход,SUM($F$7:F14)+IF(MONTH(A14)=12,ВычетУСН,0)))),IF(Режим="УСН Д-Р",MAX(E14*СтавкаДР,IF(MONTH(A14)=12,(B14+C14)*0.01,0)),MAX(0,B14*СтавкаНПДФЛ+C14*СтавкаНПДЮЛ-MIN(БонусНПД,B14*0.01+C14*0.02)))),2),SUM($N$7:N14))) -> 219420 | H14: =G14-G13 -> 12600 | I14: =SUMIFS(Cash[Сумма],Cash[Дата],"<="&ДатаОтчета,Cash[Статус],"Проведён",Cash[Тип],"Налог",Cash[Дата],">="&A14,Cash[Дата],"<"&EDATE(A14,1),Cash[Категория],"<>НДС") -> 0 | J14: =НАСТРОЙКИ!$B$34+G14-SUM($I$7:I14) -> 129420 | K14: =IF(A14>ДатаОтчета,K13,IF(AND(Форма="ИП",Режим<>"НПД",НАСТРОЙКИ!B28="Да"),IF(A14>ДатаОтчета,0,ФиксВзносы*MONTH(A14)/12+MIN(МаксВзносы,MAX(0,IF(Режим="УСН Д-Р",E14,B14+C14)-300000)*0.01)),0)) -> 71830 | L14: =K14-K13 -> 6882.5 | M14: 0 | N14: 0
A15: =DATE(Год,9,1) -> 46266 | B15: =SUMIFS(Cash[Налоговый доход],Cash[Дата],">="&DATE(Год,1,1),Cash[Дата],"<="&MIN(EOMONTH(A15,0),ДатаОтчета),Cash[Тип лица],"ФЛ") -> 431000 | C15: =SUMIFS(Cash[Налоговый доход],Cash[Дата],">="&DATE(Год,1,1),Cash[Дата],"<="&MIN(EOMONTH(A15,0),ДатаОтчета),Cash[Тип лица],"<>ФЛ") -> 3876000 | D15: =SUMIFS(Cash[Налоговый расход],Cash[Дата],">="&DATE(Год,1,1),Cash[Дата],"<="&MIN(EOMONTH(A15,0),ДатаОтчета),Cash[Статус],"Проведён",Cash[Тип],"<>Возврат поставщика")-SUMIFS(Cash[Налоговый расход],Cash[Дата],">="&DATE(Год,1,1),Cash[Дата],"<="&MIN(EOMONTH(A15,0),ДатаОтчета),Cash[Статус],"Проведён",Cash[Тип],"Возврат поставщика") -> 3682697.8 | E15: =MAX(0,B15+C15-D15) -> 624302.21 | F15: 0 | G15: =IF(A15>ДатаОтчета,G14,IF($B$4="ПРЕДВАРИТЕЛЬНЫЙ РАСЧЁТ",ROUND(IF(Режим="УСН Доходы",MAX(0,(B15+C15)*СтавкаДоход-IF(OR(Форма="ООО",Сотрудники="Да"),MIN((B15+C15)*СтавкаДоход*0.5,SUM($F$7:F15)+IF(MONTH(A15)=12,ВычетУСН,0)),MIN((B15+C15)*СтавкаДоход,SUM($F$7:F15)+IF(MONTH(A15)=12,ВычетУСН,0)))),IF(Режим="УСН Д-Р",MAX(E15*СтавкаДР,IF(MONTH(A15)=12,(B15+C15)*0.01,0)),MAX(0,B15*СтавкаНПДФЛ+C15*СтавкаНПДЮЛ-MIN(БонусНПД,B15*0.01+C15*0.02)))),2),SUM($N$7:N15))) -> 258420 | H15: =G15-G14 -> 39000 | I15: =SUMIFS(Cash[Сумма],Cash[Дата],"<="&ДатаОтчета,Cash[Статус],"Проведён",Cash[Тип],"Налог",Cash[Дата],">="&A15,Cash[Дата],"<"&EDATE(A15,1),Cash[Категория],"<>НДС") -> 0 | J15: =НАСТРОЙКИ!$B$34+G15-SUM($I$7:I15) -> 168420 | K15: =IF(A15>ДатаОтчета,K14,IF(AND(Форма="ИП",Режим<>"НПД",НАСТРОЙКИ!B28="Да"),IF(A15>ДатаОтчета,0,ФиксВзносы*MONTH(A15)/12+MIN(МаксВзносы,MAX(0,IF(Режим="УСН Д-Р",E15,B15+C15)-300000)*0.01)),0)) -> 83112.5 | L15: =K15-K14 -> 11282.5 | M15: 0 | N15: 0
A16: =DATE(Год,10,1) -> 46296 | B16: =SUMIFS(Cash[Налоговый доход],Cash[Дата],">="&DATE(Год,1,1),Cash[Дата],"<="&MIN(EOMONTH(A16,0),ДатаОтчета),Cash[Тип лица],"ФЛ") -> 502000 | C16: =SUMIFS(Cash[Налоговый доход],Cash[Дата],">="&DATE(Год,1,1),Cash[Дата],"<="&MIN(EOMONTH(A16,0),ДатаОтчета),Cash[Тип лица],"<>ФЛ") -> 4515000 | D16: =SUMIFS(Cash[Налоговый расход],Cash[Дата],">="&DATE(Год,1,1),Cash[Дата],"<="&MIN(EOMONTH(A16,0),ДатаОтчета),Cash[Статус],"Проведён",Cash[Тип],"<>Возврат поставщика")-SUMIFS(Cash[Налоговый расход],Cash[Дата],">="&DATE(Год,1,1),Cash[Дата],"<="&MIN(EOMONTH(A16,0),ДатаОтчета),Cash[Статус],"Проведён",Cash[Тип],"Возврат поставщика") -> 4157503.3 | E16: =MAX(0,B16+C16-D16) -> 859496.67 | F16: 0 | G16: =IF(A16>ДатаОтчета,G15,IF($B$4="ПРЕДВАРИТЕЛЬНЫЙ РАСЧЁТ",ROUND(IF(Режим="УСН Доходы",MAX(0,(B16+C16)*СтавкаДоход-IF(OR(Форма="ООО",Сотрудники="Да"),MIN((B16+C16)*СтавкаДоход*0.5,SUM($F$7:F16)+IF(MONTH(A16)=12,ВычетУСН,0)),MIN((B16+C16)*СтавкаДоход,SUM($F$7:F16)+IF(MONTH(A16)=12,ВычетУСН,0)))),IF(Режим="УСН Д-Р",MAX(E16*СтавкаДР,IF(MONTH(A16)=12,(B16+C16)*0.01,0)),MAX(0,B16*СтавкаНПДФЛ+C16*СтавкаНПДЮЛ-MIN(БонусНПД,B16*0.01+C16*0.02)))),2),SUM($N$7:N16))) -> 301020 | H16: =G16-G15 -> 42600 | I16: =SUMIFS(Cash[Сумма],Cash[Дата],"<="&ДатаОтчета,Cash[Статус],"Проведён",Cash[Тип],"Налог",Cash[Дата],">="&A16,Cash[Дата],"<"&EDATE(A16,1),Cash[Категория],"<>НДС") -> 45000 | J16: =НАСТРОЙКИ!$B$34+G16-SUM($I$7:I16) -> 166020 | K16: =IF(A16>ДатаОтчета,K15,IF(AND(Форма="ИП",Режим<>"НПД",НАСТРОЙКИ!B28="Да"),IF(A16>ДатаОтчета,0,ФиксВзносы*MONTH(A16)/12+MIN(МаксВзносы,MAX(0,IF(Режим="УСН Д-Р",E16,B16+C16)-300000)*0.01)),0)) -> 94995 | L16: =K16-K15 -> 11882.5 | M16: 0 | N16: 0
A17: =DATE(Год,11,1) -> 46327 | B17: =SUMIFS(Cash[Налоговый доход],Cash[Дата],">="&DATE(Год,1,1),Cash[Дата],"<="&MIN(EOMONTH(A17,0),ДатаОтчета),Cash[Тип лица],"ФЛ") -> 578000 | C17: =SUMIFS(Cash[Налоговый доход],Cash[Дата],">="&DATE(Год,1,1),Cash[Дата],"<="&MIN(EOMONTH(A17,0),ДатаОтчета),Cash[Тип лица],"<>ФЛ") -> 5199000 | D17: =SUMIFS(Cash[Налоговый расход],Cash[Дата],">="&DATE(Год,1,1),Cash[Дата],"<="&MIN(EOMONTH(A17,0),ДатаОтчета),Cash[Статус],"Проведён",Cash[Тип],"<>Возврат поставщика")-SUMIFS(Cash[Налоговый расход],Cash[Дата],">="&DATE(Год,1,1),Cash[Дата],"<="&MIN(EOMONTH(A17,0),ДатаОтчета),Cash[Статус],"Проведён",Cash[Тип],"Возврат поставщика") -> 4648123.3 | E17: =MAX(0,B17+C17-D17) -> 1128876.7 | F17: 0 | G17: =IF(A17>ДатаОтчета,G16,IF($B$4="ПРЕДВАРИТЕЛЬНЫЙ РАСЧЁТ",ROUND(IF(Режим="УСН Доходы",MAX(0,(B17+C17)*СтавкаДоход-IF(OR(Форма="ООО",Сотрудники="Да"),MIN((B17+C17)*СтавкаДоход*0.5,SUM($F$7:F17)+IF(MONTH(A17)=12,ВычетУСН,0)),MIN((B17+C17)*СтавкаДоход,SUM($F$7:F17)+IF(MONTH(A17)=12,ВычетУСН,0)))),IF(Режим="УСН Д-Р",MAX(E17*СтавкаДР,IF(MONTH(A17)=12,(B17+C17)*0.01,0)),MAX(0,B17*СтавкаНПДФЛ+C17*СтавкаНПДЮЛ-MIN(БонусНПД,B17*0.01+C17*0.02)))),2),SUM($N$7:N17))) -> 346620 | H17: =G17-G16 -> 45600 | I17: =SUMIFS(Cash[Сумма],Cash[Дата],"<="&ДатаОтчета,Cash[Статус],"Проведён",Cash[Тип],"Налог",Cash[Дата],">="&A17,Cash[Дата],"<"&EDATE(A17,1),Cash[Категория],"<>НДС") -> 0 | J17: =НАСТРОЙКИ!$B$34+G17-SUM($I$7:I17) -> 211620 | K17: =IF(A17>ДатаОтчета,K16,IF(AND(Форма="ИП",Режим<>"НПД",НАСТРОЙКИ!B28="Да"),IF(A17>ДатаОтчета,0,ФиксВзносы*MONTH(A17)/12+MIN(МаксВзносы,MAX(0,IF(Режим="УСН Д-Р",E17,B17+C17)-300000)*0.01)),0)) -> 107377.5 | L17: =K17-K16 -> 12382.5 | M17: 0 | N17: 0
A18: =DATE(Год,12,1) -> 46357 | B18: =SUMIFS(Cash[Налоговый доход],Cash[Дата],">="&DATE(Год,1,1),Cash[Дата],"<="&MIN(EOMONTH(A18,0),ДатаОтчета),Cash[Тип лица],"ФЛ") -> 627200 | C18: =SUMIFS(Cash[Налоговый доход],Cash[Дата],">="&DATE(Год,1,1),Cash[Дата],"<="&MIN(EOMONTH(A18,0),ДатаОтчета),Cash[Тип лица],"<>ФЛ") -> 5910760 | D18: =SUMIFS(Cash[Налоговый расход],Cash[Дата],">="&DATE(Год,1,1),Cash[Дата],"<="&MIN(EOMONTH(A18,0),ДатаОтчета),Cash[Статус],"Проведён",Cash[Тип],"<>Возврат поставщика")-SUMIFS(Cash[Налоговый расход],Cash[Дата],">="&DATE(Год,1,1),Cash[Дата],"<="&MIN(EOMONTH(A18,0),ДатаОтчета),Cash[Статус],"Проведён",Cash[Тип],"Возврат поставщика") -> 5026554.9 | E18: =MAX(0,B18+C18-D18) -> 1511405.1 | F18: 0 | G18: =IF(A18>ДатаОтчета,G17,IF($B$4="ПРЕДВАРИТЕЛЬНЫЙ РАСЧЁТ",ROUND(IF(Режим="УСН Доходы",MAX(0,(B18+C18)*СтавкаДоход-IF(OR(Форма="ООО",Сотрудники="Да"),MIN((B18+C18)*СтавкаДоход*0.5,SUM($F$7:F18)+IF(MONTH(A18)=12,ВычетУСН,0)),MIN((B18+C18)*СтавкаДоход,SUM($F$7:F18)+IF(MONTH(A18)=12,ВычетУСН,0)))),IF(Режим="УСН Д-Р",MAX(E18*СтавкаДР,IF(MONTH(A18)=12,(B18+C18)*0.01,0)),MAX(0,B18*СтавкаНПДФЛ+C18*СтавкаНПДЮЛ-MIN(БонусНПД,B18*0.01+C18*0.02)))),2),SUM($N$7:N18))) -> 392277.6 | H18: =G18-G17 -> 45657.6 | I18: =SUMIFS(Cash[Сумма],Cash[Дата],"<="&ДатаОтчета,Cash[Статус],"Проведён",Cash[Тип],"Налог",Cash[Дата],">="&A18,Cash[Дата],"<"&EDATE(A18,1),Cash[Категория],"<>НДС") -> 0 | J18: =НАСТРОЙКИ!$B$34+G18-SUM($I$7:I18) -> 257277.6 | K18: =IF(A18>ДатаОтчета,K17,IF(AND(Форма="ИП",Режим<>"НПД",НАСТРОЙКИ!B28="Да"),IF(A18>ДатаОтчета,0,ФиксВзносы*MONTH(A18)/12+MIN(МаксВзносы,MAX(0,IF(Режим="УСН Д-Р",E18,B18+C18)-300000)*0.01)),0)) -> 119769.6 | L18: =K18-K17 -> 12392.1 | M18: 0 | N18: 0
A21: Предварительный налог | B21: =G18 -> 392277.6
A22: Уплачено налогов | B22: =SUM(I7:I18) -> 135000
A23: Налог к уплате | B23: =MAX(0,J18) -> 257277.6
A24: Переплата налога | B24: =MAX(0,-J18) -> 0
A25: Взносы ИП начислено | B25: =K18 -> 119769.6
A26: Взносы ИП уплачено | B26: =SUMIFS(Cash[Сумма],Cash[Дата],"<="&ДатаОтчета,Cash[Статус],"Проведён",Cash[Тип],"Взносы ИП") -> 57390
A27: Взносы ИП к уплате | B27: =MAX(0,B25-B26) -> 62379.6
A28: НДС начислено вручную | B28: =SUM(M7:M18) -> 0
A29: НДС уплачено | B29: =SUMIFS(Cash[Сумма],Cash[Дата],"<="&ДатаОтчета,Cash[Статус],"Проведён",Cash[Тип],"Налог",Cash[Категория],"НДС") -> 0
A30: НДС сальдо | B30: =B28-B29 -> 0
A31: Налоговая нагрузка | B31: =IF(SUM(B18:C18)=0,"н/д",(B21+B25+B28)/SUM(B18:C18)) -> 0.078319109
A34: Параметр | B34: Значение | C34: Год | D34: Проверено | E34: Условия | F34: Источник
A35: УСН доходы | B35: =НАСТРОЙКИ!B14 -> 0.06 | C35: 2026 | D35: 46310 | E35: Базовая / региональная ставка | F35: https://www.nalog.gov.ru/rn77/taxation/taxes/usn/
A36: УСН Д-Р | B36: =НАСТРОЙКИ!B15 -> 0.15 | C36: 2026 | D36: 46310 | E36: Минимальный 1% только по итогам года | F36: https://www.nalog.gov.ru/rn77/taxation/taxes/usn/
A37: НПД ФЛ | B37: =НАСТРОЙКИ!B16 -> 0.04 | C37: 2026 | D37: 46310 | E37: ФЛ, без запрещённых операций | F37: https://npd.nalog.ru/
A38: НПД ЮЛ | B38: =НАСТРОЙКИ!B17 -> 0.06 | C38: 2026 | D38: 46310 | E38: ЮЛ и ИП | F38: https://npd.nalog.ru/
A39: Лимит НПД | B39: 2400000 | C39: 2026 | D39: 46310 | E39: Годовой доход | F39: https://npd.nalog.ru/
A40: Порог НДС УСН | B40: 20000000 | C40: 2026 | D40: 46310 | E40: За прошлый или текущий год | F40: https://www.nalog.gov.ru/new2026/
A41: Лимит УСН 2026 | B41: 490500000 | C41: 2026 | D41: 46310 | E41: Дополнительно проверьте иные условия | F41: https://www.nalog.gov.ru/new2026/
A42: Взносы ИП | B42: =ФиксВзносы -> 57390 | C42: 2026 | D42: 46310 | E42: Полный год; отдельные категории исключены | F42: https://nalog.garant.ru/fns/nk/25251f9c341b4b29fabf5cb7957c5992/
A43: Доп. взносы максимум | B43: =МаксВзносы -> 321818 | C43: 2026 | D43: 46310 | E43: Совокупно 379208 с фиксированной частью | F43: https://nalog.garant.ru/fns/nk/25251f9c341b4b29fabf5cb7957c5992/
A46: Платёж | B46: Базовый срок | C46: Сумма план | D46: Примечание
A47: УСН 3 мес. | B47: =DATE(Год,4,28) -> 46140 | C47: =MAX(0,G9-SUM($I$7:I9)) -> 66420 | D47: Срок без переноса выходных; платёж сверить с ЕНС
A48: УСН 6 мес. | B48: =DATE(Год,7,28) -> 46231 | C48: =MAX(0,G12-SUM($I$7:I12)) -> 126420 | D48: Срок без переноса выходных; платёж сверить с ЕНС
A49: УСН 9 мес. | B49: =DATE(Год,10,28) -> 46323 | C49: =MAX(0,G15-SUM($I$7:I15)) -> 168420 | D49: Срок без переноса выходных; платёж сверить с ЕНС
A50: УСН 12 мес. | B50: =DATE(Год+1,IF(Форма="ООО",3,4),28) -> 46505 | C50: =MAX(0,G18-SUM($I$7:I18)) -> 257277.6 | D50: Срок без переноса выходных; платёж сверить с ЕНС
A52: Взносы фиксированные | B52: =DATE(Год,12,28) -> 46384 | C52: =IF(AND(Форма="ИП",Режим<>"НПД",НАСТРОЙКИ!B28="Да"),MAX(0,ФиксВзносы-B26),0) -> 0
A53: Дополнительный 1% | B53: =DATE(Год+1,7,1) -> 46569 | C53: =IF(AND(Форма="ИП",Режим<>"НПД",НАСТРОЙКИ!B28="Да"),MAX(0,K18-ФиксВзносы-MAX(0,B26-ФиксВзносы)),0) -> 62379.6
A55: НДФЛ и взносы сотрудников вводятся отдельными начислениями, не в налог на результат.
A56: НДС: ручной ввод обязательства и отдельный платёж. Для возмещения/входного НДС нужна адаптация.

Sheet БЮДЖЕТ
A1: Главная панель | D1: Настройки | F1: Контроль
A2: БЮДЖЕТ
A3: LEO STUDIO • Управленческий учёт • RUB
A6: Показатель | B6: =DATE(Год,1,1) -> 46023 | C6: =DATE(Год,2,1) -> 46054 | D6: =DATE(Год,3,1) -> 46082 | E6: =DATE(Год,4,1) -> 46113 | F6: =DATE(Год,5,1) -> 46143 | G6: =DATE(Год,6,1) -> 46174 | H6: =DATE(Год,7,1) -> 46204 | I6: =DATE(Год,8,1) -> 46235 | J6: =DATE(Год,9,1) -> 46266 | K6: =DATE(Год,10,1) -> 46296 | L6: =DATE(Год,11,1) -> 46327 | M6: =DATE(Год,12,1) -> 46357 | N6: Год / итог
A7: Выручка план | B7: 540000 | C7: 540000 | D7: 540000 | E7: 540000 | F7: 540000 | G7: 540000 | H7: 540000 | I7: 540000 | J7: 540000 | K7: 540000 | L7: 540000 | M7: 540000 | N7: =SUM(B7:M7) -> 6480000
A8: Себестоимость план | B8: 175000 | C8: 175000 | D8: 175000 | E8: 175000 | F8: 175000 | G8: 175000 | H8: 175000 | I8: 175000 | J8: 175000 | K8: 175000 | L8: 175000 | M8: 175000 | N8: =SUM(B8:M8) -> 2100000
A9: Операционные план | B9: 260000 | C9: 260000 | D9: 260000 | E9: 260000 | F9: 260000 | G9: 260000 | H9: 260000 | I9: 260000 | J9: 260000 | K9: 260000 | L9: 260000 | M9: 260000 | N9: =SUM(B9:M9) -> 3120000
A10: Налог + взносы ИП план | B10: 30000 | C10: 30000 | D10: 30000 | E10: 30000 | F10: 30000 | G10: 30000 | H10: 30000 | I10: 30000 | J10: 30000 | K10: 30000 | L10: 30000 | M10: 30000 | N10: =SUM(B10:M10) -> 360000
A11: Капитальные затраты план | B11: 180000 | C11: 0 | D11: 0 | E11: 0 | F11: 0 | G11: 0 | H11: 0 | I11: 0 | J11: 0 | K11: 0 | L11: 0 | M11: 0 | N11: =SUM(B11:M11) -> 180000
A12: Кредит: тело + проценты план | B12: 15000 | C12: 15000 | D12: 15000 | E12: 15000 | F12: 15000 | G12: 15000 | H12: 15000 | I12: 15000 | J12: 15000 | K12: 15000 | L12: 15000 | M12: 15000 | N12: =SUM(B12:M12) -> 180000
A13: Денежные поступления план | B13: 530000 | C13: 530000 | D13: 530000 | E13: 530000 | F13: 530000 | G13: 530000 | H13: 530000 | I13: 530000 | J13: 530000 | K13: 530000 | L13: 530000 | M13: 530000 | N13: =SUM(B13:M13) -> 6360000
A14: Денежные выплаты план | B14: 470000 | C14: 470000 | D14: 470000 | E14: 470000 | F14: 470000 | G14: 470000 | H14: 470000 | I14: 470000 | J14: 470000 | K14: 470000 | L14: 470000 | M14: 470000 | N14: =SUM(B14:M14) -> 5640000
A15: Денежный остаток план | B15: =SUM(Accounts[Начальный])+B13-B14 -> 60000 | C15: =B15+C13-C14 -> 120000 | D15: =C15+D13-D14 -> 180000 | E15: =D15+E13-E14 -> 240000 | F15: =E15+F13-F14 -> 300000 | G15: =F15+G13-G14 -> 360000 | H15: =G15+H13-H14 -> 420000 | I15: =H15+I13-I14 -> 480000 | J15: =I15+J13-J14 -> 540000 | ... M15: =L15+M13-M14 -> 720000 | N15: =M15 -> 720000
A18: Выручка факт | B18: =ОПиУ!B7 -> 420000 | C18: =ОПиУ!C7 -> 180000 | D18: =ОПиУ!D7 -> 507000 | E18: =ОПиУ!E7 -> 550000 | F18: =ОПиУ!F7 -> 580000 | G18: =ОПиУ!G7 -> 620000 | H18: =ОПиУ!H7 -> 590000 | I18: =ОПиУ!I7 -> 210000 | ... M18: =ОПиУ!M7 -> 820000 | N18: =SUM(B18:M18) -> 6597000
A19: Выручка отклонение, руб. | B19: =B18-B7 -> -120000 | C19: =C18-C7 -> -360000 | D19: =D18-D7 -> -33000 | E19: =E18-E7 -> 10000 | F19: =F18-F7 -> 40000 | G19: =G18-G7 -> 80000 | H19: =H18-H7 -> 50000 | I19: =I18-I7 -> -330000 | ... M19: =M18-M7 -> 280000 | N19: =SUM(B19:M19) -> 117000
A20: Выручка отклонение, % | B20: =IF(B7=0,"н/д",B19/B7) -> -0.22222222 | C20: =IF(C7=0,"н/д",C19/C7) -> -0.66666667 | D20: =IF(D7=0,"н/д",D19/D7) -> -0.061111111 | E20: =IF(E7=0,"н/д",E19/E7) -> 0.018518519 | F20: =IF(F7=0,"н/д",F19/F7) -> 0.074074074 | G20: =IF(G7=0,"н/д",G19/G7) -> 0.14814815 | H20: =IF(H7=0,"н/д",H19/H7) -> 0.092592593 | I20: =IF(I7=0,"н/д",I19/I7) -> -0.61111111 | ... N20: =IF(N7=0,"н/д",N19/N7) -> 0.018055556
A22: Себестоимость факт | B22: =ОПиУ!B8 -> 134400 | C22: =ОПиУ!C8 -> 57600 | D22: =ОПиУ!D8 -> 163200 | E22: =ОПиУ!E8 -> 176000 | F22: =ОПиУ!F8 -> 185600 | G22: =ОПиУ!G8 -> 198400 | H22: =ОПиУ!H8 -> 188800 | I22: =ОПиУ!I8 -> 67200 | ... M22: =ОПиУ!M8 -> 262400 | N22: =SUM(B22:M22) -> 2112000
A23: Себестоимость отклонение | B23: =B22-B8 -> -40600 | C23: =C22-C8 -> -117400 | D23: =D22-D8 -> -11800 | E23: =E22-E8 -> 1000 | F23: =F22-F8 -> 10600 | G23: =G22-G8 -> 23400 | H23: =H22-H8 -> 13800 | I23: =I22-I8 -> -107800 | ... M23: =M22-M8 -> 87400 | N23: =SUM(B23:M23) -> 12000
A24: Операционные факт | B24: =ОПиУ!B10 -> 245000 | C24: =ОПиУ!C10 -> 245000 | D24: =ОПиУ!D10 -> 245000 | E24: =ОПиУ!E10 -> 245000 | F24: =ОПиУ!F10 -> 245000 | G24: =ОПиУ!G10 -> 245000 | H24: =ОПиУ!H10 -> 245000 | I24: =ОПиУ!I10 -> 310000 | ... M24: =ОПиУ!M10 -> 245000 | N24: =SUM(B24:M24) -> 3005000
A25: Операционные отклонение | B25: =B24-B9 -> -15000 | C25: =C24-C9 -> -15000 | D25: =D24-D9 -> -15000 | E25: =E24-E9 -> -15000 | F25: =F24-F9 -> -15000 | G25: =G24-G9 -> -15000 | H25: =H24-H9 -> -15000 | I25: =I24-I9 -> 50000 | ... M25: =M24-M9 -> -15000 | N25: =SUM(B25:M25) -> -115000
A26: Налоги факт | B26: =ОПиУ!B14+ОПиУ!B15 -> 31182.5 | C26: =ОПиУ!C14+ОПиУ!C15 -> 17382.5 | D26: =ОПиУ!D14+ОПиУ!D15 -> 40272.5 | E26: =ОПиУ!E14+ОПиУ!E15 -> 43282.5 | F26: =ОПиУ!F14+ОПиУ!F15 -> 45382.5 | G26: =ОПиУ!G14+ОПиУ!G15 -> 48182.5 | H26: =ОПиУ!H14+ОПиУ!H15 -> 46082.5 | I26: =ОПиУ!I14+ОПиУ!I15 -> 19482.5 | ... M26: =ОПиУ!M14+ОПиУ!M15 -> 58049.7 | N26: =SUM(B26:M26) -> 512047.2
A27: Налоги отклонение | B27: =B26-B10 -> 1182.5 | C27: =C26-C10 -> -12617.5 | D27: =D26-D10 -> 10272.5 | E27: =E26-E10 -> 13282.5 | F27: =F26-F10 -> 15382.5 | G27: =G26-G10 -> 18182.5 | H27: =H26-H10 -> 16082.5 | I27: =I26-I10 -> -10517.5 | ... M27: =M26-M10 -> 28049.7 | N27: =SUM(B27:M27) -> 152047.2
A28: Капитальные затраты факт | B28: =-SUMIFS(Cash[Поток],Cash[Дата],"<="&ДатаОтчета,Cash[Статус],"Проведён",Cash[Тип],"Покупка ОС",Cash[Дата],">="&B$6,Cash[Дата],"<"&EDATE(B$6,1)) -> 180000 | C28: =-SUMIFS(Cash[Поток],Cash[Дата],"<="&ДатаОтчета,Cash[Статус],"Проведён",Cash[Тип],"Покупка ОС",Cash[Дата],">="&C$6,Cash[Дата],"<"&EDATE(C$6,1)) -> 0 | D28: =-SUMIFS(Cash[Поток],Cash[Дата],"<="&ДатаОтчета,Cash[Статус],"Проведён",Cash[Тип],"Покупка ОС",Cash[Дата],">="&D$6,Cash[Дата],"<"&EDATE(D$6,1)) -> 0 | E28: =-SUMIFS(Cash[Поток],Cash[Дата],"<="&ДатаОтчета,Cash[Статус],"Проведён",Cash[Тип],"Покупка ОС",Cash[Дата],">="&E$6,Cash[Дата],"<"&EDATE(E$6,1)) -> 0 | F28: =-SUMIFS(Cash[Поток],Cash[Дата],"<="&ДатаОтчета,Cash[Статус],"Проведён",Cash[Тип],"Покупка ОС",Cash[Дата],">="&F$6,Cash[Дата],"<"&EDATE(F$6,1)) -> 0 | G28: =-SUMIFS(Cash[Поток],Cash[Дата],"<="&ДатаОтчета,Cash[Статус],"Проведён",Cash[Тип],"Покупка ОС",Cash[Дата],">="&G$6,Cash[Дата],"<"&EDATE(G$6,1)) -> 0 | H28: =-SUMIFS(Cash[Поток],Cash[Дата],"<="&ДатаОтчета,Cash[Статус],"Проведён",Cash[Тип],"Покупка ОС",Cash[Дата],">="&H$6,Cash[Дата],"<"&EDATE(H$6,1)) -> 0 | I28: =-SUMIFS(Cash[Поток],Cash[Дата],"<="&ДатаОтчета,Cash[Статус],"Проведён",Cash[Тип],"Покупка ОС",Cash[Дата],">="&I$6,Cash[Дата],"<"&EDATE(I$6,1)) -> 0 | ... M28: =-SUMIFS(Cash[Поток],Cash[Дата],"<="&ДатаОтчета,Cash[Статус],"Проведён",Cash[Тип],"Покупка ОС",Cash[Дата],">="&M$6,Cash[Дата],"<"&EDATE(M$6,1)) -> 0 | N28: =SUM(B28:M28) -> 180000
A29: Капзатраты отклонение | B29: =B28-B11 -> 0 | C29: =C28-C11 -> 0 | D29: =D28-D11 -> 0 | E29: =E28-E11 -> 0 | F29: =F28-F11 -> 0 | G29: =G28-G11 -> 0 | H29: =H28-H11 -> 0 | I29: =I28-I11 -> 0 | ... M29: =M28-M11 -> 0 | N29: =SUM(B29:M29) -> 0
A30: Кредит факт | B30: =-SUMIFS(Cash[Поток],Cash[Дата],"<="&ДатаОтчета,Cash[Статус],"Проведён",Cash[Тип],"Тело кредита",Cash[Дата],">="&B$6,Cash[Дата],"<"&EDATE(B$6,1))-SUMIFS(Cash[Поток],Cash[Дата],"<="&ДатаОтчета,Cash[Статус],"Проведён",Cash[Тип],"Проценты",Cash[Дата],">="&B$6,Cash[Дата],"<"&EDATE(B$6,1)) -> 14977.23 | C30: =-SUMIFS(Cash[Поток],Cash[Дата],"<="&ДатаОтчета,Cash[Статус],"Проведён",Cash[Тип],"Тело кредита",Cash[Дата],">="&C$6,Cash[Дата],"<"&EDATE(C$6,1))-SUMIFS(Cash[Поток],Cash[Дата],"<="&ДатаОтчета,Cash[Статус],"Проведён",Cash[Тип],"Проценты",Cash[Дата],">="&C$6,Cash[Дата],"<"&EDATE(C$6,1)) -> 14977.23 | D30: =-SUMIFS(Cash[Поток],Cash[Дата],"<="&ДатаОтчета,Cash[Статус],"Проведён",Cash[Тип],"Тело кредита",Cash[Дата],">="&D$6,Cash[Дата],"<"&EDATE(D$6,1))-SUMIFS(Cash[Поток],Cash[Дата],"<="&ДатаОтчета,Cash[Статус],"Проведён",Cash[Тип],"Проценты",Cash[Дата],">="&D$6,Cash[Дата],"<"&EDATE(D$6,1)) -> 14977.23 | E30: =-SUMIFS(Cash[Поток],Cash[Дата],"<="&ДатаОтчета,Cash[Статус],"Проведён",Cash[Тип],"Тело кредита",Cash[Дата],">="&E$6,Cash[Дата],"<"&EDATE(E$6,1))-SUMIFS(Cash[Поток],Cash[Дата],"<="&ДатаОтчета,Cash[Статус],"Проведён",Cash[Тип],"Проценты",Cash[Дата],">="&E$6,Cash[Дата],"<"&EDATE(E$6,1)) -> 14977.23 | F30: =-SUMIFS(Cash[Поток],Cash[Дата],"<="&ДатаОтчета,Cash[Статус],"Проведён",Cash[Тип],"Тело кредита",Cash[Дата],">="&F$6,Cash[Дата],"<"&EDATE(F$6,1))-SUMIFS(Cash[Поток],Cash[Дата],"<="&ДатаОтчета,Cash[Статус],"Проведён",Cash[Тип],"Проценты",Cash[Дата],">="&F$6,Cash[Дата],"<"&EDATE(F$6,1)) -> 14977.23 | G30: =-SUMIFS(Cash[Поток],Cash[Дата],"<="&ДатаОтчета,Cash[Статус],"Проведён",Cash[Тип],"Тело кредита",Cash[Дата],">="&G$6,Cash[Дата],"<"&EDATE(G$6,1))-SUMIFS(Cash[Поток],Cash[Дата],"<="&ДатаОтчета,Cash[Статус],"Проведён",Cash[Тип],"Проценты",Cash[Дата],">="&G$6,Cash[Дата],"<"&EDATE(G$6,1)) -> 39977.23 | H30: =-SUMIFS(Cash[Поток],Cash[Дата],"<="&ДатаОтчета,Cash[Статус],"Проведён",Cash[Тип],"Тело кредита",Cash[Дата],">="&H$6,Cash[Дата],"<"&EDATE(H$6,1))-SUMIFS(Cash[Поток],Cash[Дата],"<="&ДатаОтчета,Cash[Статус],"Проведён",Cash[Тип],"Проценты",Cash[Дата],">="&H$6,Cash[Дата],"<"&EDATE(H$6,1)) -> 14977.23 | I30: =-SUMIFS(Cash[Поток],Cash[Дата],"<="&ДатаОтчета,Cash[Статус],"Проведён",Cash[Тип],"Тело кредита",Cash[Дата],">="&I$6,Cash[Дата],"<"&EDATE(I$6,1))-SUMIFS(Cash[Поток],Cash[Дата],"<="&ДатаОтчета,Cash[Статус],"Проведён",Cash[Тип],"Проценты",Cash[Дата],">="&I$6,Cash[Дата],"<"&EDATE(I$6,1)) -> 14977.23 | ... M30: =-SUMIFS(Cash[Поток],Cash[Дата],"<="&ДатаОтчета,Cash[Статус],"Проведён",Cash[Тип],"Тело кредита",Cash[Дата],">="&M$6,Cash[Дата],"<"&EDATE(M$6,1))-SUMIFS(Cash[Поток],Cash[Дата],"<="&ДатаОтчета,Cash[Статус],"Проведён",Cash[Тип],"Проценты",Cash[Дата],">="&M$6,Cash[Дата],"<"&EDATE(M$6,1)) -> 14977.23 | N30: =SUM(B30:M30) -> 204726.76
A31: Кредит отклонение | B31: =B30-B12 -> -22.77 | C31: =C30-C12 -> -22.77 | D31: =D30-D12 -> -22.77 | E31: =E30-E12 -> -22.77 | F31: =F30-F12 -> -22.77 | G31: =G30-G12 -> 24977.23 | H31: =H30-H12 -> -22.77 | I31: =I30-I12 -> -22.77 | ... M31: =M30-M12 -> -22.77 | N31: =SUM(B31:M31) -> 24726.76
A32: Денежный остаток факт | B32: =ДДС!B14 -> 645622.77 | C32: =ДДС!C14 -> 508045.54 | D32: =ДДС!D14 -> 566868.31 | E32: =ДДС!E14 -> 635891.08 | F32: =ДДС!F14 -> 770313.85 | G32: =ДДС!G14 -> 881936.62 | H32: =ДДС!H14 -> 978159.39 | I32: =ДДС!I14 -> 795982.16 | ... M32: =ДДС!M14 -> 1675043.2 | N32: =M32 -> 1675043.2
A33: Остаток отклонение | B33: =B32-B15 -> 585622.77 | C33: =C32-C15 -> 388045.54 | D33: =D32-D15 -> 386868.31 | E33: =E32-E15 -> 395891.08 | F33: =F32-F15 -> 470313.85 | G33: =G32-G15 -> 521936.62 | H33: =H32-H15 -> 558159.39 | I33: =I32-I15 -> 315982.16 | ... M33: =M32-M15 -> 955043.24 | N33: =M33 -> 955043.24
A35: Себестоимость отклонение, % | B35: =IF(B8=0,"н/д",(B22-B8)/B8) -> -0.232 | C35: =IF(C8=0,"н/д",(C22-C8)/C8) -> -0.67085714 | D35: =IF(D8=0,"н/д",(D22-D8)/D8) -> -0.067428571 | E35: =IF(E8=0,"н/д",(E22-E8)/E8) -> 0.0057142857 | F35: =IF(F8=0,"н/д",(F22-F8)/F8) -> 0.060571429 | G35: =IF(G8=0,"н/д",(G22-G8)/G8) -> 0.13371429 | H35: =IF(H8=0,"н/д",(H22-H8)/H8) -> 0.078857143 | I35: =IF(I8=0,"н/д",(I22-I8)/I8) -> -0.616 | ... N35: =IF(N8=0,"н/д",(N22-N8)/N8) -> 0.0057142857
A36: Операционные отклонение, % | B36: =IF(B9=0,"н/д",(B24-B9)/B9) -> -0.057692308 | C36: =IF(C9=0,"н/д",(C24-C9)/C9) -> -0.057692308 | D36: =IF(D9=0,"н/д",(D24-D9)/D9) -> -0.057692308 | E36: =IF(E9=0,"н/д",(E24-E9)/E9) -> -0.057692308 | F36: =IF(F9=0,"н/д",(F24-F9)/F9) -> -0.057692308 | G36: =IF(G9=0,"н/д",(G24-G9)/G9) -> -0.057692308 | H36: =IF(H9=0,"н/д",(H24-H9)/H9) -> -0.057692308 | I36: =IF(I9=0,"н/д",(I24-I9)/I9) -> 0.19230769 | ... N36: =IF(N9=0,"н/д",(N24-N9)/N9) -> -0.036858974
A37: Налоги отклонение, % | B37: =IF(B10=0,"н/д",(B26-B10)/B10) -> 0.039416667 | C37: =IF(C10=0,"н/д",(C26-C10)/C10) -> -0.42058333 | D37: =IF(D10=0,"н/д",(D26-D10)/D10) -> 0.34241667 | E37: =IF(E10=0,"н/д",(E26-E10)/E10) -> 0.44275 | F37: =IF(F10=0,"н/д",(F26-F10)/F10) -> 0.51275 | G37: =IF(G10=0,"н/д",(G26-G10)/G10) -> 0.60608333 | H37: =IF(H10=0,"н/д",(H26-H10)/H10) -> 0.53608333 | I37: =IF(I10=0,"н/д",(I26-I10)/I10) -> -0.35058333 | ... N37: =IF(N10=0,"н/д",(N26-N10)/N10) -> 0.42235333
A38: Капзатраты отклонение, % | B38: =IF(B11=0,"н/д",(B28-B11)/B11) -> 0 | C38: =IF(C11=0,"н/д",(C28-C11)/C11) -> н/д | D38: =IF(D11=0,"н/д",(D28-D11)/D11) -> н/д | E38: =IF(E11=0,"н/д",(E28-E11)/E11) -> н/д | F38: =IF(F11=0,"н/д",(F28-F11)/F11) -> н/д | G38: =IF(G11=0,"н/д",(G28-G11)/G11) -> н/д | H38: =IF(H11=0,"н/д",(H28-H11)/H11) -> н/д | I38: =IF(I11=0,"н/д",(I28-I11)/I11) -> н/д | ... N38: =IF(N11=0,"н/д",(N28-N11)/N11) -> 0
A39: Кредит отклонение, % | B39: =IF(B12=0,"н/д",(B30-B12)/B12) -> -0.001518 | C39: =IF(C12=0,"н/д",(C30-C12)/C12) -> -0.001518 | D39: =IF(D12=0,"н/д",(D30-D12)/D12) -> -0.001518 | E39: =IF(E12=0,"н/д",(E30-E12)/E12) -> -0.001518 | F39: =IF(F12=0,"н/д",(F30-F12)/F12) -> -0.001518 | G39: =IF(G12=0,"н/д",(G30-G12)/G12) -> 1.6651487 | H39: =IF(H12=0,"н/д",(H30-H12)/H12) -> -0.001518 | I39: =IF(I12=0,"н/д",(I30-I12)/I12) -> -0.001518 | ... N39: =IF(N12=0,"н/д",(N30-N12)/N12) -> 0.13737089
A40: Деньги отклонение, % | B40: =IF(B15=0,"н/д",(B32-B15)/B15) -> 9.7603795 | C40: =IF(C15=0,"н/д",(C32-C15)/C15) -> 3.2337128 | D40: =IF(D15=0,"н/д",(D32-D15)/D15) -> 2.1492684 | E40: =IF(E15=0,"н/д",(E32-E15)/E15) -> 1.6495462 | F40: =IF(F15=0,"н/д",(F32-F15)/F15) -> 1.5677128 | G40: =IF(G15=0,"н/д",(G32-G15)/G15) -> 1.4498239 | H40: =IF(H15=0,"н/д",(H32-H15)/H15) -> 1.3289509 | I40: =IF(I15=0,"н/д",(I32-I15)/I15) -> 0.65829617 | ... N40: =IF(N15=0,"н/д",(N32-N15)/N15) -> 1.3264489

Sheet РЕЗЕРВЫ
A1: Главная панель | D1: Настройки | F1: Контроль
A2: РЕЗЕРВЫ
A3: LEO STUDIO • Управленческий учёт • RUB
A6: Показатель | B6: Значение | C6: Пояснение
A7: Обязательные расходы / месяц | B7: =IF(НАСТРОЙКИ!B26>0,НАСТРОЙКИ!B26,SUM(ОПиУ!B10:M10)/MAX(1,MONTH(ДатаОтчета))) -> 250416.67 | C7: Операционные расходы без амортизации; уточните обязательную часть
A8: Цель покрытия, месяцев | B8: =МесяцыРезерва -> 3 | C8: Из настроек
A9: Целевой резерв | B9: =B7*B8 -> 751250 | C9: Расходы × месяцы
A10: Обособленный резерв | B10: =СЧЕТА!B21 -> 180000 | C10: Счёт Резерв, включён в общие деньги
A11: Недостаток | B11: =MAX(0,B9-B10) -> 571250 | C11: Не скрывается при избытке
A12: Достижение цели | B12: =IF(B9=0,"н/д",B10/B9) -> 0.23960067 | C12: При нулевой цели показатель не определён
A13: Месяцев покрытия | B13: =IF(B7=0,"н/д",B10/B7) -> 0.718802 | C13: Только обязательные расходы
A14: План пополнения | B14: =НАСТРОЙКИ!B25 -> 15000 | C14: Перевод на счёт Резерв
A15: Месяцев до цели | B15: =IF(B11=0,0,IF(B14<=0,"н/д",ROUNDUP(B11/B14,0))) -> 39 | C15: Без процентов и изменения расходов
A16: Статус | B16: =IF(B10>=B9,"Резерв достаточен","Резерв ниже цели") -> Резерв ниже цели

Sheet РЕИНВЕСТИЦИИ
A1: Главная панель | D1: Настройки | F1: Контроль
A2: РЕИНВЕСТИЦИИ
A3: LEO STUDIO • Управленческий учёт • RUB
A6: Показатель | B6: Сумма | C6: Методика
A7: Денежные средства | B7: =СЧЕТА!B19 -> 1675043.2 | C7: Все счета
A8: Налоги и взносы | B8: =БАЛАНС!B16 -> 319657.2 | C8: Зарезервировать полное обязательство
A9: Кредиторская задолженность | B9: =БАЛАНС!B14 -> 131200 | C9: Консервативно вся КЗ, включая дивиденды
A10: Защищённый резерв | B10: =MAX(РЕЗЕРВЫ!B9,РЕЗЕРВЫ!B10) -> 751250 | C10: Не вычитается повторно отдельным остатком
A11: Кредит: следующие 30 дней | B11: =SUMIFS(КРЕДИТ!D20:D79,КРЕДИТ!A20:A79,">"&ДатаОтчета,КРЕДИТ!A20:A79,"<="&ДатаОтчета+30) -> 14977.23 | C11: По графику
A12: План расходов 30 дней | B12: 0 | C12: Дополнительные плановые выплаты, не включённые выше
A13: Доступно к распределению | B13: =MAX(0,B7-SUM(B8:B12)) -> 457958.81 | C13: При недостатке денег: ноль
A16: Направление | B16: Доля ввод | C16: План, руб. | D16: Факт, руб. | E16: Отклонение
A17: Развитие бизнеса | B17: 0.2 | C17: =IF(ABS(SUM($B$17:$B$23)-1)>0.000001,0,$B$13*B17) -> 91591.762 | D17: =-SUMIFS(Cash[Поток],Cash[Дата],"<="&ДатаОтчета,Cash[Статус],"Проведён",Cash[Распределение],A17,Cash[Поток],"<0") -> 0 | E17: =D17-C17 -> -91591.762
A18: Маркетинг | B18: 0.2 | C18: =IF(ABS(SUM($B$17:$B$23)-1)>0.000001,0,$B$13*B18) -> 91591.762 | D18: =-SUMIFS(Cash[Поток],Cash[Дата],"<="&ДатаОтчета,Cash[Статус],"Проведён",Cash[Распределение],A18,Cash[Поток],"<0") -> 605000 | E18: =D18-C18 -> 513408.24
A19: Оборудование | B19: 0.15 | C19: =IF(ABS(SUM($B$17:$B$23)-1)>0.000001,0,$B$13*B19) -> 68693.821 | D19: =-SUMIFS(Cash[Поток],Cash[Дата],"<="&ДатаОтчета,Cash[Статус],"Проведён",Cash[Распределение],A19,Cash[Поток],"<0") -> 180000 | E19: =D19-C19 -> 111306.18
A20: Найм сотрудников | B20: 0.1 | C20: =IF(ABS(SUM($B$17:$B$23)-1)>0.000001,0,$B$13*B20) -> 45795.881 | D20: =-SUMIFS(Cash[Поток],Cash[Дата],"<="&ДатаОтчета,Cash[Статус],"Проведён",Cash[Распределение],A20,Cash[Поток],"<0") -> 0 | E20: =D20-C20 -> -45795.881
A21: Автоматизация | B21: 0.1 | C21: =IF(ABS(SUM($B$17:$B$23)-1)>0.000001,0,$B$13*B21) -> 45795.881 | D21: =-SUMIFS(Cash[Поток],Cash[Дата],"<="&ДатаОтчета,Cash[Статус],"Проведён",Cash[Распределение],A21,Cash[Поток],"<0") -> 0 | E21: =D21-C21 -> -45795.881
A22: Резерв | B22: 0.15 | C22: =IF(ABS(SUM($B$17:$B$23)-1)>0.000001,0,$B$13*B22) -> 68693.821 | D22: =SUMIFS(Cash[Сумма],Cash[Дата],"<="&ДатаОтчета,Cash[Статус],"Проведён",Cash[Тип],"Перевод",Cash[Счёт получателя],"Резерв") -> 180000 | E22: =D22-C22 -> 111306.18
A23: Выплаты собственнику | B23: 0.1 | C23: =IF(ABS(SUM($B$17:$B$23)-1)>0.000001,0,$B$13*B23) -> 45795.881 | D23: =-SUMIFS(Cash[Поток],Cash[Дата],"<="&ДатаОтчета,Cash[Статус],"Проведён",Cash[Распределение],A23,Cash[Поток],"<0") -> 100000 | E23: =D23-C23 -> 54204.119
A25: Сумма долей | B25: =SUM(B17:B23) -> 1
A26: Проверка долей | B26: =IF(ABS(B25-1)<0.000001,"ОК","ОШИБКА: доли должны дать 100%") -> ОК

Sheet ПРОГНОЗ
A1: Главная панель | D1: Настройки | F1: Контроль
A2: ПРОГНОЗ
A3: LEO STUDIO • Управленческий учёт • RUB
A4: Активный сценарий | B4: =Сценарий -> Базовый
A6: Показатель | B6: =EDATE(DATE(YEAR(ДатаОтчета),MONTH(ДатаОтчета),1),1) -> 46388 | C6: =EDATE(DATE(YEAR(ДатаОтчета),MONTH(ДатаОтчета),1),2) -> 46419 | D6: =EDATE(DATE(YEAR(ДатаОтчета),MONTH(ДатаОтчета),1),3) -> 46447 | E6: =EDATE(DATE(YEAR(ДатаОтчета),MONTH(ДатаОтчета),1),4) -> 46478 | F6: =EDATE(DATE(YEAR(ДатаОтчета),MONTH(ДатаОтчета),1),5) -> 46508 | G6: =EDATE(DATE(YEAR(ДатаОтчета),MONTH(ДатаОтчета),1),6) -> 46539 | H6: =EDATE(DATE(YEAR(ДатаОтчета),MONTH(ДатаОтчета),1),7) -> 46569 | I6: =EDATE(DATE(YEAR(ДатаОтчета),MONTH(ДатаОтчета),1),8) -> 46600 | J6: =EDATE(DATE(YEAR(ДатаОтчета),MONTH(ДатаОтчета),1),9) -> 46631 | K6: =EDATE(DATE(YEAR(ДатаОтчета),MONTH(ДатаОтчета),1),10) -> 46661 | L6: =EDATE(DATE(YEAR(ДатаОтчета),MONTH(ДатаОтчета),1),11) -> 46692 | M6: =EDATE(DATE(YEAR(ДатаОтчета),MONTH(ДатаОтчета),1),12) -> 46722 | N6: Год / итог
A7: Выручка | B7: =(SUMIFS(ОПиУ!$B$7:$M$7,ОПиУ!$B$6:$M$6,">="&EDATE(DATE(Год,MONTH(ДатаОтчета),1),-2),ОПиУ!$B$6:$M$6,"<="&ДатаОтчета)/MIN(3,MONTH(ДатаОтчета)))*(1-РИСКИ!$F$10)*(1+РИСКИ!$F$7) -> 778600 | C7: =B7*(1+РИСКИ!$F$7) -> 794172 | D7: =C7*(1+РИСКИ!$F$7) -> 810055.44 | E7: =D7*(1+РИСКИ!$F$7) -> 826256.55 | F7: =E7*(1+РИСКИ!$F$7) -> 842781.68 | G7: =F7*(1+РИСКИ!$F$7) -> 859637.31 | H7: =G7*(1+РИСКИ!$F$7) -> 876830.06 | I7: =H7*(1+РИСКИ!$F$7) -> 894366.66 | J7: =I7*(1+РИСКИ!$F$7) -> 912253.99 | ... M7: =L7*(1+РИСКИ!$F$7) -> 968091.24 | N7: =SUM(B7:M7) -> 10442653
A8: Переменные расходы | B8: =B7*IF(ОПиУ!$N$7=0,0,ОПиУ!$N$8/ОПиУ!$N$7) -> 249265.3 | C8: =C7*IF(ОПиУ!$N$7=0,0,ОПиУ!$N$8/ОПиУ!$N$7) -> 254250.61 | D8: =D7*IF(ОПиУ!$N$7=0,0,ОПиУ!$N$8/ОПиУ!$N$7) -> 259335.62 | E8: =E7*IF(ОПиУ!$N$7=0,0,ОПиУ!$N$8/ОПиУ!$N$7) -> 264522.33 | F8: =F7*IF(ОПиУ!$N$7=0,0,ОПиУ!$N$8/ОПиУ!$N$7) -> 269812.78 | G8: =G7*IF(ОПиУ!$N$7=0,0,ОПиУ!$N$8/ОПиУ!$N$7) -> 275209.04 | H8: =H7*IF(ОПиУ!$N$7=0,0,ОПиУ!$N$8/ОПиУ!$N$7) -> 280713.22 | I8: =I7*IF(ОПиУ!$N$7=0,0,ОПиУ!$N$8/ОПиУ!$N$7) -> 286327.48 | ... M8: =M7*IF(ОПиУ!$N$7=0,0,ОПиУ!$N$8/ОПиУ!$N$7) -> 309930.07 | N8: =SUM(B8:M8) -> 3343168.6
A9: Постоянные расходы | B9: =IF(НАСТРОЙКИ!$B$29=0,(SUMIFS(ОПиУ!$B$10:$M$10,ОПиУ!$B$6:$M$6,">="&EDATE(DATE(Год,MONTH(ДатаОтчета),1),-2),ОПиУ!$B$6:$M$6,"<="&ДатаОтчета)/MIN(3,MONTH(ДатаОтчета))),НАСТРОЙКИ!$B$29)*(1+РИСКИ!$F$8) -> 246225 | C9: =B9*(1+РИСКИ!$F$8) -> 247456.12 | D9: =C9*(1+РИСКИ!$F$8) -> 248693.41 | E9: =D9*(1+РИСКИ!$F$8) -> 249936.87 | F9: =E9*(1+РИСКИ!$F$8) -> 251186.56 | G9: =F9*(1+РИСКИ!$F$8) -> 252442.49 | H9: =G9*(1+РИСКИ!$F$8) -> 253704.7 | I9: =H9*(1+РИСКИ!$F$8) -> 254973.23 | J9: =I9*(1+РИСКИ!$F$8) -> 256248.09 | ... M9: =L9*(1+РИСКИ!$F$8) -> 260111.06 | N9: =SUM(B9:M9) -> 3037323.8
A10: Амортизация | B10: =(SUMIFS(ОПиУ!$B$11:$M$11,ОПиУ!$B$6:$M$6,">="&EDATE(DATE(Год,MONTH(ДатаОтчета),1),-2),ОПиУ!$B$6:$M$6,"<="&ДатаОтчета)/MIN(3,MONTH(ДатаОтчета))) -> 5000 | C10: =(SUMIFS(ОПиУ!$B$11:$M$11,ОПиУ!$B$6:$M$6,">="&EDATE(DATE(Год,MONTH(ДатаОтчета),1),-2),ОПиУ!$B$6:$M$6,"<="&ДатаОтчета)/MIN(3,MONTH(ДатаОтчета))) -> 5000 | D10: =(SUMIFS(ОПиУ!$B$11:$M$11,ОПиУ!$B$6:$M$6,">="&EDATE(DATE(Год,MONTH(ДатаОтчета),1),-2),ОПиУ!$B$6:$M$6,"<="&ДатаОтчета)/MIN(3,MONTH(ДатаОтчета))) -> 5000 | E10: =(SUMIFS(ОПиУ!$B$11:$M$11,ОПиУ!$B$6:$M$6,">="&EDATE(DATE(Год,MONTH(ДатаОтчета),1),-2),ОПиУ!$B$6:$M$6,"<="&ДатаОтчета)/MIN(3,MONTH(ДатаОтчета))) -> 5000 | F10: =(SUMIFS(ОПиУ!$B$11:$M$11,ОПиУ!$B$6:$M$6,">="&EDATE(DATE(Год,MONTH(ДатаОтчета),1),-2),ОПиУ!$B$6:$M$6,"<="&ДатаОтчета)/MIN(3,MONTH(ДатаОтчета))) -> 5000 | G10: =(SUMIFS(ОПиУ!$B$11:$M$11,ОПиУ!$B$6:$M$6,">="&EDATE(DATE(Год,MONTH(ДатаОтчета),1),-2),ОПиУ!$B$6:$M$6,"<="&ДатаОтчета)/MIN(3,MONTH(ДатаОтчета))) -> 5000 | H10: =(SUMIFS(ОПиУ!$B$11:$M$11,ОПиУ!$B$6:$M$6,">="&EDATE(DATE(Год,MONTH(ДатаОтчета),1),-2),ОПиУ!$B$6:$M$6,"<="&ДатаОтчета)/MIN(3,MONTH(ДатаОтчета))) -> 5000 | I10: =(SUMIFS(ОПиУ!$B$11:$M$11,ОПиУ!$B$6:$M$6,">="&EDATE(DATE(Год,MONTH(ДатаОтчета),1),-2),ОПиУ!$B$6:$M$6,"<="&ДатаОтчета)/MIN(3,MONTH(ДатаОтчета))) -> 5000 | ... M10: =(SUMIFS(ОПиУ!$B$11:$M$11,ОПиУ!$B$6:$M$6,">="&EDATE(DATE(Год,MONTH(ДатаОтчета),1),-2),ОПиУ!$B$6:$M$6,"<="&ДатаОтчета)/MIN(3,MONTH(ДатаОтчета))) -> 5000 | N10: =SUM(B10:M10) -> 60000
A11: Проценты | B11: =SUMIFS(КРЕДИТ!$C$20:$C$79,КРЕДИТ!$A$20:$A$79,">="&B$6,КРЕДИТ!$A$20:$A$79,"<"&EDATE(B$6,1))+БАЛАНС!$B$15*РИСКИ!$F$12/12 -> 2040.42 | C11: =SUMIFS(КРЕДИТ!$C$20:$C$79,КРЕДИТ!$A$20:$A$79,">="&C$6,КРЕДИТ!$A$20:$A$79,"<"&EDATE(C$6,1))+БАЛАНС!$B$15*РИСКИ!$F$12/12 -> 1846.37 | D11: =SUMIFS(КРЕДИТ!$C$20:$C$79,КРЕДИТ!$A$20:$A$79,">="&D$6,КРЕДИТ!$A$20:$A$79,"<"&EDATE(D$6,1))+БАЛАНС!$B$15*РИСКИ!$F$12/12 -> 1649.41 | E11: =SUMIFS(КРЕДИТ!$C$20:$C$79,КРЕДИТ!$A$20:$A$79,">="&E$6,КРЕДИТ!$A$20:$A$79,"<"&EDATE(E$6,1))+БАЛАНС!$B$15*РИСКИ!$F$12/12 -> 1449.49 | F11: =SUMIFS(КРЕДИТ!$C$20:$C$79,КРЕДИТ!$A$20:$A$79,">="&F$6,КРЕДИТ!$A$20:$A$79,"<"&EDATE(F$6,1))+БАЛАНС!$B$15*РИСКИ!$F$12/12 -> 1246.57 | G11: =SUMIFS(КРЕДИТ!$C$20:$C$79,КРЕДИТ!$A$20:$A$79,">="&G$6,КРЕДИТ!$A$20:$A$79,"<"&EDATE(G$6,1))+БАЛАНС!$B$15*РИСКИ!$F$12/12 -> 1040.61 | H11: =SUMIFS(КРЕДИТ!$C$20:$C$79,КРЕДИТ!$A$20:$A$79,">="&H$6,КРЕДИТ!$A$20:$A$79,"<"&EDATE(H$6,1))+БАЛАНС!$B$15*РИСКИ!$F$12/12 -> 831.56 | I11: =SUMIFS(КРЕДИТ!$C$20:$C$79,КРЕДИТ!$A$20:$A$79,">="&I$6,КРЕДИТ!$A$20:$A$79,"<"&EDATE(I$6,1))+БАЛАНС!$B$15*РИСКИ!$F$12/12 -> 619.38 | ... M11: =SUMIFS(КРЕДИТ!$C$20:$C$79,КРЕДИТ!$A$20:$A$79,">="&M$6,КРЕДИТ!$A$20:$A$79,"<"&EDATE(M$6,1))+БАЛАНС!$B$15*РИСКИ!$F$12/12 -> 0 | N11: =SUM(B11:M11) -> 11313.23
A12: Сценарные налоги | B12: =B7*(РИСКИ!$F$14+РИСКИ!$F$11) -> 46716 | C12: =C7*(РИСКИ!$F$14+РИСКИ!$F$11) -> 47650.32 | D12: =D7*(РИСКИ!$F$14+РИСКИ!$F$11) -> 48603.326 | E12: =E7*(РИСКИ!$F$14+РИСКИ!$F$11) -> 49575.393 | F12: =F7*(РИСКИ!$F$14+РИСКИ!$F$11) -> 50566.901 | G12: =G7*(РИСКИ!$F$14+РИСКИ!$F$11) -> 51578.239 | H12: =H7*(РИСКИ!$F$14+РИСКИ!$F$11) -> 52609.804 | I12: =I7*(РИСКИ!$F$14+РИСКИ!$F$11) -> 53662 | ... M12: =M7*(РИСКИ!$F$14+РИСКИ!$F$11) -> 58085.474 | N12: =SUM(B12:M12) -> 626559.18
A13: Внеплановые расходы | B13: =РИСКИ!$F$13 -> 0 | C13: =РИСКИ!$F$13 -> 0 | D13: =РИСКИ!$F$13 -> 0 | E13: =РИСКИ!$F$13 -> 0 | F13: =РИСКИ!$F$13 -> 0 | G13: =РИСКИ!$F$13 -> 0 | H13: =РИСКИ!$F$13 -> 0 | I13: =РИСКИ!$F$13 -> 0 | ... M13: =РИСКИ!$F$13 -> 0 | N13: =SUM(B13:M13) -> 0
A15: Прогнозная прибыль | B15: =B7-SUM(B8:B13) -> 229353.28 | C15: =C7-SUM(C8:C13) -> 237968.58 | D15: =D7-SUM(D8:D13) -> 246773.68 | E15: =E7-SUM(E8:E13) -> 255772.46 | F15: =F7-SUM(F8:F13) -> 264968.87 | G15: =G7-SUM(G8:G13) -> 274366.94 | H15: =H7-SUM(H8:H13) -> 283970.78 | I15: =I7-SUM(I8:I13) -> 293784.58 | ... M15: =M7-SUM(M8:M13) -> 334964.63 | N15: =SUM(B15:M15) -> 3364288.2
A16: Денежные поступления | B16: =B7*(1-РИСКИ!$F$9/30)+НАСТРОЙКИ!$B$30 -> 648833.33 | C16: =C7*(1-РИСКИ!$F$9/30)+B7*РИСКИ!$F$9/30 -> 791576.67 | D16: =D7*(1-РИСКИ!$F$9/30)+C7*РИСКИ!$F$9/30 -> 807408.2 | E16: =E7*(1-РИСКИ!$F$9/30)+D7*РИСКИ!$F$9/30 -> 823556.36 | F16: =F7*(1-РИСКИ!$F$9/30)+E7*РИСКИ!$F$9/30 -> 840027.49 | G16: =G7*(1-РИСКИ!$F$9/30)+F7*РИСКИ!$F$9/30 -> 856828.04 | H16: =H7*(1-РИСКИ!$F$9/30)+G7*РИСКИ!$F$9/30 -> 873964.6 | I16: =I7*(1-РИСКИ!$F$9/30)+H7*РИСКИ!$F$9/30 -> 891443.89 | J16: =J7*(1-РИСКИ!$F$9/30)+I7*РИСКИ!$F$9/30 -> 909272.77 | ... M16: =M7*(1-РИСКИ!$F$9/30)+L7*РИСКИ!$F$9/30 -> 964927.54 | N16: =SUM(B16:M16) -> 10281305
A17: Денежные выплаты по расходам | B17: =B8+B9+B11+B13 -> 497530.72 | C17: =C8+C9+C11+C13 -> 503553.1 | D17: =D8+D9+D11+D13 -> 509678.44 | E17: =E8+E9+E11+E13 -> 515908.7 | F17: =F8+F9+F11+F13 -> 522245.91 | G17: =G8+G9+G11+G13 -> 528692.14 | H17: =H8+H9+H11+H13 -> 535249.48 | I17: =I8+I9+I11+I13 -> 541920.09 | ... M17: =M8+M9+M11+M13 -> 570041.14 | N17: =SUM(B17:M17) -> 6391805.7
A18: Налоги: сценарный платёж | B18: =B12 -> 46716 | C18: =C12 -> 47650.32 | D18: =D12 -> 48603.326 | E18: =E12 -> 49575.393 | F18: =F12 -> 50566.901 | G18: =G12 -> 51578.239 | H18: =H12 -> 52609.804 | I18: =I12 -> 53662 | ... M18: =M12 -> 58085.474 | N18: =SUM(B18:M18) -> 626559.18
A19: Тело кредита по графику | B19: =SUMIFS(КРЕДИТ!$E$20:$E$79,КРЕДИТ!$A$20:$A$79,">="&B$6,КРЕДИТ!$A$20:$A$79,"<"&EDATE(B$6,1))+SUMIFS(КРЕДИТ!$F$20:$F$79,КРЕДИТ!$A$20:$A$79,">="&B$6,КРЕДИТ!$A$20:$A$79,"<"&EDATE(B$6,1)) -> 12936.81 | C19: =SUMIFS(КРЕДИТ!$E$20:$E$79,КРЕДИТ!$A$20:$A$79,">="&C$6,КРЕДИТ!$A$20:$A$79,"<"&EDATE(C$6,1))+SUMIFS(КРЕДИТ!$F$20:$F$79,КРЕДИТ!$A$20:$A$79,">="&C$6,КРЕДИТ!$A$20:$A$79,"<"&EDATE(C$6,1)) -> 13130.86 | D19: =SUMIFS(КРЕДИТ!$E$20:$E$79,КРЕДИТ!$A$20:$A$79,">="&D$6,КРЕДИТ!$A$20:$A$79,"<"&EDATE(D$6,1))+SUMIFS(КРЕДИТ!$F$20:$F$79,КРЕДИТ!$A$20:$A$79,">="&D$6,КРЕДИТ!$A$20:$A$79,"<"&EDATE(D$6,1)) -> 13327.82 | E19: =SUMIFS(КРЕДИТ!$E$20:$E$79,КРЕДИТ!$A$20:$A$79,">="&E$6,КРЕДИТ!$A$20:$A$79,"<"&EDATE(E$6,1))+SUMIFS(КРЕДИТ!$F$20:$F$79,КРЕДИТ!$A$20:$A$79,">="&E$6,КРЕДИТ!$A$20:$A$79,"<"&EDATE(E$6,1)) -> 13527.74 | F19: =SUMIFS(КРЕДИТ!$E$20:$E$79,КРЕДИТ!$A$20:$A$79,">="&F$6,КРЕДИТ!$A$20:$A$79,"<"&EDATE(F$6,1))+SUMIFS(КРЕДИТ!$F$20:$F$79,КРЕДИТ!$A$20:$A$79,">="&F$6,КРЕДИТ!$A$20:$A$79,"<"&EDATE(F$6,1)) -> 13730.66 | G19: =SUMIFS(КРЕДИТ!$E$20:$E$79,КРЕДИТ!$A$20:$A$79,">="&G$6,КРЕДИТ!$A$20:$A$79,"<"&EDATE(G$6,1))+SUMIFS(КРЕДИТ!$F$20:$F$79,КРЕДИТ!$A$20:$A$79,">="&G$6,КРЕДИТ!$A$20:$A$79,"<"&EDATE(G$6,1)) -> 13936.62 | H19: =SUMIFS(КРЕДИТ!$E$20:$E$79,КРЕДИТ!$A$20:$A$79,">="&H$6,КРЕДИТ!$A$20:$A$79,"<"&EDATE(H$6,1))+SUMIFS(КРЕДИТ!$F$20:$F$79,КРЕДИТ!$A$20:$A$79,">="&H$6,КРЕДИТ!$A$20:$A$79,"<"&EDATE(H$6,1)) -> 14145.67 | I19: =SUMIFS(КРЕДИТ!$E$20:$E$79,КРЕДИТ!$A$20:$A$79,">="&I$6,КРЕДИТ!$A$20:$A$79,"<"&EDATE(I$6,1))+SUMIFS(КРЕДИТ!$F$20:$F$79,КРЕДИТ!$A$20:$A$79,">="&I$6,КРЕДИТ!$A$20:$A$79,"<"&EDATE(I$6,1)) -> 14357.85 | ... M19: =SUMIFS(КРЕДИТ!$E$20:$E$79,КРЕДИТ!$A$20:$A$79,">="&M$6,КРЕДИТ!$A$20:$A$79,"<"&EDATE(M$6,1))+SUMIFS(КРЕДИТ!$F$20:$F$79,КРЕДИТ!$A$20:$A$79,">="&M$6,КРЕДИТ!$A$20:$A$79,"<"&EDATE(M$6,1)) -> 0 | N19: =SUM(B19:M19) -> 136028.15
A20: Старая КЗ и налоги: погашение | B20: =НАСТРОЙКИ!$B$31+БАЛАНС!$B$16 -> 319657.2 | C20: =0 -> 0 | D20: =0 -> 0 | E20: =0 -> 0 | F20: =0 -> 0 | G20: =0 -> 0 | H20: =0 -> 0 | I20: =0 -> 0 | J20: =0 -> 0 | ... M20: =0 -> 0 | N20: =SUM(B20:M20) -> 319657.2
A21: Начальный денежный остаток | B21: =СЧЕТА!$B$19 -> 1675043.2 | C21: =B22 -> 1447035.8 | D21: =C22 -> 1674278.2 | E21: =D22 -> 1910076.8 | F21: =E22 -> 2154621.4 | G21: =F22 -> 2408105.4 | H21: =G22 -> 2670726.4 | I21: =H22 -> 2942686.1 | J21: =I22 -> 3224190.1 | ... M21: =L22 -> 4145496.6 | N21: =M21 -> 4145496.6
A22: Конечный денежный остаток | B22: =B21+B16-SUM(B17:B20) -> 1447035.8 | C22: =C21+C16-SUM(C17:C20) -> 1674278.2 | D22: =D21+D16-SUM(D17:D20) -> 1910076.8 | E22: =E21+E16-SUM(E17:E20) -> 2154621.4 | F22: =F21+F16-SUM(F17:F20) -> 2408105.4 | G22: =G21+G16-SUM(G17:G20) -> 2670726.4 | H22: =H21+H16-SUM(H17:H20) -> 2942686.1 | I22: =I21+I16-SUM(I17:I20) -> 3224190.1 | ... M22: =M21+M16-SUM(M17:M20) -> 4482297.6 | N22: =M22 -> 4482297.6
A23: Рентабельность | B23: =IF(B7=0,"н/д",B15/B7) -> 0.29457138 | C23: =IF(C7=0,"н/д",C15/C7) -> 0.29964362 | D23: =IF(D7=0,"н/д",D15/D7) -> 0.30463801 | E23: =IF(E7=0,"н/д",E15/E7) -> 0.30955574 | F23: =IF(F7=0,"н/д",F15/F7) -> 0.314398 | G23: =IF(G7=0,"н/д",G15/G7) -> 0.31916593 | H23: =IF(H7=0,"н/д",H15/H7) -> 0.32386068 | I23: =IF(I7=0,"н/д",I15/I7) -> 0.32848337 | ... N23: =IF(N7=0,"н/д",N15/N7) -> 0.32216796
A24: Покрытие резерва | B24: =B22-РЕЗЕРВЫ!$B$9 -> 695785.84 | C24: =C22-РЕЗЕРВЫ!$B$9 -> 923028.22 | D24: =D22-РЕЗЕРВЫ!$B$9 -> 1158826.8 | E24: =E22-РЕЗЕРВЫ!$B$9 -> 1403371.4 | F24: =F22-РЕЗЕРВЫ!$B$9 -> 1656855.4 | G24: =G22-РЕЗЕРВЫ!$B$9 -> 1919476.4 | H24: =H22-РЕЗЕРВЫ!$B$9 -> 2191436.1 | I24: =I22-РЕЗЕРВЫ!$B$9 -> 2472940.1 | ... M24: =M22-РЕЗЕРВЫ!$B$9 -> 3731047.6 | N24: =M24 -> 3731047.6
A27: Горизонт | B27: Прибыль | C27: Денежный остаток | D27: Пояснение
A28: 3 месяцев | B28: =SUM(B15:D15) -> 714095.53 | C28: =D22 -> 1910076.8 | D28: Сценарная оценка, не налоговая декларация
A29: 6 месяцев | B29: =SUM(B15:G15) -> 1509203.8 | C29: =G22 -> 2670726.4 | D29: Сценарная оценка, не налоговая декларация
A30: 12 месяцев | B30: =SUM(B15:M15) -> 3364288.2 | C30: =M22 -> 4482297.6 | D30: Сценарная оценка, не налоговая декларация

Sheet РИСКИ
A1: Главная панель | D1: Настройки | F1: Контроль
A2: РИСКИ
A3: LEO STUDIO • Управленческий учёт • RUB
A6: Допущение | B6: Базовый | C6: Оптимистичный | D6: Пессимистичный | E6: Кризисный | F6: Активное
A7: Рост выручки / месяц | B7: 0.02 | C7: 0.04 | D7: -0.03 | E7: -0.08 | F7: =INDEX(B7:E7,1,MATCH(Сценарий,$B$6:$E$6,0)) -> 0.02
A8: Рост постоянных затрат / месяц | B8: 0.005 | C8: 0.003 | D8: 0.015 | E8: 0.025 | F8: =INDEX(B8:E8,1,MATCH(Сценарий,$B$6:$E$6,0)) -> 0.005
A9: Задержка оплаты, дней | B9: 5 | C9: 0 | D9: 15 | E9: 30 | F9: =INDEX(B9:E9,1,MATCH(Сценарий,$B$6:$E$6,0)) -> 5
A10: Потеря выручки от клиентов | B10: 0 | C10: 0 | D10: 0.15 | E10: 0.3 | F10: =INDEX(B10:E10,1,MATCH(Сценарий,$B$6:$E$6,0)) -> 0
A11: Доп. налоговая нагрузка, п.п. | B11: 0 | C11: 0 | D11: 0.02 | E11: 0.04 | F11: =INDEX(B11:E11,1,MATCH(Сценарий,$B$6:$E$6,0)) -> 0
A12: Рост ставки кредита, п.п. | B12: 0 | C12: 0 | D12: 0.03 | E12: 0.08 | F12: =INDEX(B12:E12,1,MATCH(Сценарий,$B$6:$E$6,0)) -> 0
A13: Внеплановые расходы / месяц | B13: 0 | C13: 0 | D13: 30000 | E13: 100000 | F13: =INDEX(B13:E13,1,MATCH(Сценарий,$B$6:$E$6,0)) -> 0
A14: Сценарная ставка налогов | B14: 0.06 | C14: 0.06 | D14: 0.06 | E14: 0.06 | F14: =INDEX(B14:E14,1,MATCH(Сценарий,$B$6:$E$6,0)) -> 0.06
A16: Активный сценарий | B16: =Сценарий -> Базовый
A17: Минимум денег за 12 месяцев | B17: =MIN(ПРОГНОЗ!B22:M22) -> 1447035.8
A18: Первый кассовый разрыв | B18: =IF(COUNTIF(ПРОГНОЗ!B22:M22,"<0")=0,"Не выявлен",MONTH(INDEX(ПРОГНОЗ!B6:M6,1,MATCH(TRUE,INDEX(ПРОГНОЗ!B22:M22<0,0),0)))&" / "&YEAR(INDEX(ПРОГНОЗ!B6:M6,1,MATCH(TRUE,INDEX(ПРОГНОЗ!B22:M22<0,0),0)))) -> Не выявлен
A19: Прибыль за 12 месяцев | B19: =SUM(ПРОГНОЗ!B15:M15) -> 3364288.2
A20: Деньги после защиты резерва | B20: =ПРОГНОЗ!M22-РЕЗЕРВЫ!B9 -> 3731047.6
A21: Оценка платёжеспособности | B21: =IF(B17<0,"Риск кассового разрыва","По сценарию деньги неотрицательны") -> По сценарию деньги неотрицательны
A24: Сценарий — оценка по допущениям, не вероятность и не гарантия результата.
A25: Задержка 0–30 дней: доля выручки переносится на следующий месяц. Более длинные задержки не моделируются.

Sheet ПОКАЗАТЕЛИ
A1: Главная панель | D1: Настройки | F1: Контроль
A2: ПОКАЗАТЕЛИ
A3: LEO STUDIO • Управленческий учёт • RUB
A6: Показатель | B6: Значение | C6: Расчёт / ограничение
A7: Валовая рентабельность | B7: =IF(ОПиУ!N7=0,"н/д",ОПиУ!N9/ОПиУ!N7) -> 0.67985448 | C7: Валовая прибыль / выручка
A8: Операционная рентабельность | B8: =IF(ОПиУ!N7=0,"н/д",ОПиУ!N12/ОПиУ!N7) -> 0.21600728 | C8: Операционная прибыль / выручка
A9: Итоговая рентабельность | B9: =ОПиУ!N17 -> 0.13221129 | C9: Результат после налогов / выручка
A10: Расходы / выручка | B10: =IF(ОПиУ!N7=0,"н/д",(ОПиУ!N7-ОПиУ!N16)/ОПиУ!N7) -> 0.86778871 | C10: Включает налоги, проценты и амортизацию
A11: Текущая ликвидность | B11: =IF(OR(НАСТРОЙКИ!B33<>0,НАСТРОЙКИ!B38<>0,НАСТРОЙКИ!B39<>0,SUMIFS(Cash[Поток],Cash[Дата],"<="&ДатаОтчета,Cash[Статус],"Проведён",Cash[Тип],"Займ участника")+SUMIFS(Cash[Поток],Cash[Дата],"<="&ДатаОтчета,Cash[Статус],"Проведён",Cash[Тип],"Возврат займа")<>0,(БАЛАНС!B14+БАЛАНС!B16+MIN(БАЛАНС!B15,SUMIFS(КРЕДИТ!E20:E79,КРЕДИТ!A20:A79,">"&ДатаОтчета,КРЕДИТ!A20:A79,"<="&EDATE(ДатаОтчета,12))+SUMIFS(КРЕДИТ!F20:F79,КРЕДИТ!A20:A79,">"&ДатаОтчета,КРЕДИТ!A20:A79,"<="&EDATE(ДатаОтчета,12))))=0),"н/д",(БАЛАНС!B7+БАЛАНС!B8+БАЛАНС!B10)/(БАЛАНС!B14+БАЛАНС!B16+MIN(БАЛАНС!B15,SUMIFS(КРЕДИТ!E20:E79,КРЕДИТ!A20:A79,">"&ДатаОтчета,КРЕДИТ!A20:A79,"<="&EDATE(ДатаОтчета,12))+SUMIFS(КРЕДИТ!F20:F79,КРЕДИТ!A20:A79,">"&ДатаОтчета,КРЕДИТ!A20:A79,"<="&EDATE(ДатаОтчета,12))))) -> 2.9547223 | C11: Оборотные активы / КЗ, налоги и тело кредита следующих 12 мес. При неизвестных сроках: н/д.
A12: Долги / активы | B12: =IF(БАЛАНС!B11=0,"н/д",БАЛАНС!B18/БАЛАНС!B11) -> 0.31568535 | C12: Все обязательства / активы
A13: Покрытие расходов деньгами | B13: =IF(РЕЗЕРВЫ!B7=0,"н/д",СЧЕТА!B19/РЕЗЕРВЫ!B7) -> 6.6890246 | C13: Месяцы без поступлений, при прежних расходах
A14: Оборот ДЗ | B14: =IF((НАСТРОЙКИ!B36+SUMIFS(Docs[Сумма],Docs[Вид],"Начальная ДЗ",Docs[Статус],"Проведён",Docs[Дата],"<="&ДатаОтчета)+БАЛАНС!B8)/2=0,"н/д",ОПиУ!N7/((НАСТРОЙКИ!B36+SUMIFS(Docs[Сумма],Docs[Вид],"Начальная ДЗ",Docs[Статус],"Проведён",Docs[Дата],"<="&ДатаОтчета)+БАЛАНС!B8)/2)) -> 223.47561 | C14: Упрощённо: выручка / средняя начальная и конечная ДЗ
A15: Постоянные затраты | B15: =ОПиУ!N10+ОПиУ!N11 -> 3060000 | C15: За период, до процентов и налогов
A16: Переменные затраты | B16: =ОПиУ!N8 -> 2112000 | C16: Себестоимость услуг
A17: Маржинальный доход | B17: =ОПиУ!N7-B16 -> 4485000 | C17: Выручка минус переменные затраты
A18: Маржинальность | B18: =IF(ОПиУ!N7=0,"н/д",B17/ОПиУ!N7) -> 0.67985448 | C18: Доля маржинального дохода
A19: Точка безубыточности | B19: =IF(NOT(ISNUMBER(B18)),"н/д",IF(B18<=0,"н/д",B15/B18)) -> 4500963.2 | C19: Выручка периода для покрытия постоянных затрат
A20: Запас прочности | B20: =IF(OR(ОПиУ!N7=0,NOT(ISNUMBER(B19))),"н/д",(ОПиУ!N7-B19)/ОПиУ!N7) -> 0.31772575 | C20: (Выручка − безубыточность) / выручка

Sheet АНАЛИТИКА
A1: Главная панель | D1: Настройки | F1: Контроль
A2: АНАЛИТИКА
A3: LEO STUDIO • Управленческий учёт • RUB
A6: Контрагент | B6: Выручка | C6: Доля | D6: Поступления | E6: Дебиторка | F6: Кредиторка
A7: =IF(СПРАВОЧНИКИ!G7="","",СПРАВОЧНИКИ!G7) -> Клиент Альфа | B7: =IF(A7="","",SUMIFS(Docs[Сумма],Docs[Дата],"<="&ДатаОтчета,Docs[Статус],"Проведён",Docs[Вид],"Выручка",Docs[Контрагент],A7)) -> 1845000 | C7: =IF(A7="","",IF(ОПиУ!$N$7=0,"н/д",B7/ОПиУ!$N$7)) -> 0.27967258 | D7: =IF(A7="","",SUMIFS(Cash[Поток],Cash[Дата],"<="&ДатаОтчета,Cash[Статус],"Проведён",Cash[Тип],"Оплата клиента",Cash[Контрагент],A7)+SUMIFS(Cash[Поток],Cash[Дата],"<="&ДатаОтчета,Cash[Статус],"Проведён",Cash[Тип],"Возврат клиенту",Cash[Контрагент],A7)) -> 1845000 | E7: =IF(A7="","",SUMIFS(Docs[Остаток],Docs[Дата],"<="&ДатаОтчета,Docs[Статус],"Проведён",Docs[Тип долга],"ДЗ",Docs[Контрагент],A7)) -> 0 | F7: =IF(A7="","",SUMIFS(Docs[Остаток],Docs[Дата],"<="&ДатаОтчета,Docs[Статус],"Проведён",Docs[Контрагент],A7,Docs[Тип долга],"КЗ")) -> 0
A8: =IF(СПРАВОЧНИКИ!G8="","",СПРАВОЧНИКИ!G8) -> Клиент Вектор | B8: =IF(A8="","",SUMIFS(Docs[Сумма],Docs[Дата],"<="&ДатаОтчета,Docs[Статус],"Проведён",Docs[Вид],"Выручка",Docs[Контрагент],A8)) -> 1452000 | C8: =IF(A8="","",IF(ОПиУ!$N$7=0,"н/д",B8/ОПиУ!$N$7)) -> 0.22010005 | D8: =IF(A8="","",SUMIFS(Cash[Поток],Cash[Дата],"<="&ДатаОтчета,Cash[Статус],"Проведён",Cash[Тип],"Оплата клиента",Cash[Контрагент],A8)+SUMIFS(Cash[Поток],Cash[Дата],"<="&ДатаОтчета,Cash[Статус],"Проведён",Cash[Тип],"Возврат клиенту",Cash[Контрагент],A8)) -> 1452000 | E8: =IF(A8="","",SUMIFS(Docs[Остаток],Docs[Дата],"<="&ДатаОтчета,Docs[Статус],"Проведён",Docs[Тип долга],"ДЗ",Docs[Контрагент],A8)) -> 0 | F8: =IF(A8="","",SUMIFS(Docs[Остаток],Docs[Дата],"<="&ДатаОтчета,Docs[Статус],"Проведён",Docs[Контрагент],A8,Docs[Тип долга],"КЗ")) -> 0
A9: =IF(СПРАВОЧНИКИ!G9="","",СПРАВОЧНИКИ!G9) -> Клиент Гамма | B9: =IF(A9="","",SUMIFS(Docs[Сумма],Docs[Дата],"<="&ДатаОтчета,Docs[Статус],"Проведён",Docs[Вид],"Выручка",Docs[Контрагент],A9)) -> 1188000 | C9: =IF(A9="","",IF(ОПиУ!$N$7=0,"н/д",B9/ОПиУ!$N$7)) -> 0.18008186 | D9: =IF(A9="","",SUMIFS(Cash[Поток],Cash[Дата],"<="&ДатаОтчета,Cash[Статус],"Проведён",Cash[Тип],"Оплата клиента",Cash[Контрагент],A9)+SUMIFS(Cash[Поток],Cash[Дата],"<="&ДатаОтчета,Cash[Статус],"Проведён",Cash[Тип],"Возврат клиенту",Cash[Контрагент],A9)) -> 1188000 | E9: =IF(A9="","",SUMIFS(Docs[Остаток],Docs[Дата],"<="&ДатаОтчета,Docs[Статус],"Проведён",Docs[Тип долга],"ДЗ",Docs[Контрагент],A9)) -> 0 | F9: =IF(A9="","",SUMIFS(Docs[Остаток],Docs[Дата],"<="&ДатаОтчета,Docs[Статус],"Проведён",Docs[Контрагент],A9,Docs[Тип долга],"КЗ")) -> 0
A10: =IF(СПРАВОЧНИКИ!G10="","",СПРАВОЧНИКИ!G10) -> Клиент Дельта | B10: =IF(A10="","",SUMIFS(Docs[Сумма],Docs[Дата],"<="&ДатаОтчета,Docs[Статус],"Проведён",Docs[Вид],"Выручка",Docs[Контрагент],A10)) -> 924000 | C10: =IF(A10="","",IF(ОПиУ!$N$7=0,"н/д",B10/ОПиУ!$N$7)) -> 0.14006367 | D10: =IF(A10="","",SUMIFS(Cash[Поток],Cash[Дата],"<="&ДатаОтчета,Cash[Статус],"Проведён",Cash[Тип],"Оплата клиента",Cash[Контрагент],A10)+SUMIFS(Cash[Поток],Cash[Дата],"<="&ДатаОтчета,Cash[Статус],"Проведён",Cash[Тип],"Возврат клиенту",Cash[Контрагент],A10)) -> 924000 | E10: =IF(A10="","",SUMIFS(Docs[Остаток],Docs[Дата],"<="&ДатаОтчета,Docs[Статус],"Проведён",Docs[Тип долга],"ДЗ",Docs[Контрагент],A10)) -> 0 | F10: =IF(A10="","",SUMIFS(Docs[Остаток],Docs[Дата],"<="&ДатаОтчета,Docs[Статус],"Проведён",Docs[Контрагент],A10,Docs[Тип долга],"КЗ")) -> 0
A11: =IF(СПРАВОЧНИКИ!G11="","",СПРАВОЧНИКИ!G11) -> Клиент Елена | B11: =IF(A11="","",SUMIFS(Docs[Сумма],Docs[Дата],"<="&ДатаОтчета,Docs[Статус],"Проведён",Docs[Вид],"Выручка",Docs[Контрагент],A11)) -> 660000 | C11: =IF(A11="","",IF(ОПиУ!$N$7=0,"н/д",B11/ОПиУ!$N$7)) -> 0.10004548 | D11: =IF(A11="","",SUMIFS(Cash[Поток],Cash[Дата],"<="&ДатаОтчета,Cash[Статус],"Проведён",Cash[Тип],"Оплата клиента",Cash[Контрагент],A11)+SUMIFS(Cash[Поток],Cash[Дата],"<="&ДатаОтчета,Cash[Статус],"Проведён",Cash[Тип],"Возврат клиенту",Cash[Контрагент],A11)) -> 627200 | E11: =IF(A11="","",SUMIFS(Docs[Остаток],Docs[Дата],"<="&ДатаОтчета,Docs[Статус],"Проведён",Docs[Тип долга],"ДЗ",Docs[Контрагент],A11)) -> 32800 | F11: =IF(A11="","",SUMIFS(Docs[Остаток],Docs[Дата],"<="&ДатаОтчета,Docs[Статус],"Проведён",Docs[Контрагент],A11,Docs[Тип долга],"КЗ")) -> 0
A12: =IF(СПРАВОЧНИКИ!G12="","",СПРАВОЧНИКИ!G12) -> Клиент Фокус | B12: =IF(A12="","",SUMIFS(Docs[Сумма],Docs[Дата],"<="&ДатаОтчета,Docs[Статус],"Проведён",Docs[Вид],"Выручка",Docs[Контрагент],A12)) -> 528000 | C12: =IF(A12="","",IF(ОПиУ!$N$7=0,"н/д",B12/ОПиУ!$N$7)) -> 0.08003638 | D12: =IF(A12="","",SUMIFS(Cash[Поток],Cash[Дата],"<="&ДатаОтчета,Cash[Статус],"Проведён",Cash[Тип],"Оплата клиента",Cash[Контрагент],A12)+SUMIFS(Cash[Поток],Cash[Дата],"<="&ДатаОтчета,Cash[Статус],"Проведён",Cash[Тип],"Возврат клиенту",Cash[Контрагент],A12)) -> 501760 | E12: =IF(A12="","",SUMIFS(Docs[Остаток],Docs[Дата],"<="&ДатаОтчета,Docs[Статус],"Проведён",Docs[Тип долга],"ДЗ",Docs[Контрагент],A12)) -> 26240 | F12: =IF(A12="","",SUMIFS(Docs[Остаток],Docs[Дата],"<="&ДатаОтчета,Docs[Статус],"Проведён",Docs[Контрагент],A12,Docs[Тип долга],"КЗ")) -> 0
A13: =IF(СПРАВОЧНИКИ!G13="","",СПРАВОЧНИКИ!G13) -> Подрядчик Север | B13: =IF(A13="","",SUMIFS(Docs[Сумма],Docs[Дата],"<="&ДатаОтчета,Docs[Статус],"Проведён",Docs[Вид],"Выручка",Docs[Контрагент],A13)) -> 0 | C13: =IF(A13="","",IF(ОПиУ!$N$7=0,"н/д",B13/ОПиУ!$N$7)) -> 0 | D13: =IF(A13="","",SUMIFS(Cash[Поток],Cash[Дата],"<="&ДатаОтчета,Cash[Статус],"Проведён",Cash[Тип],"Оплата клиента",Cash[Контрагент],A13)+SUMIFS(Cash[Поток],Cash[Дата],"<="&ДатаОтчета,Cash[Статус],"Проведён",Cash[Тип],"Возврат клиенту",Cash[Контрагент],A13)) -> 0 | E13: =IF(A13="","",SUMIFS(Docs[Остаток],Docs[Дата],"<="&ДатаОтчета,Docs[Статус],"Проведён",Docs[Тип долга],"ДЗ",Docs[Контрагент],A13)) -> 0 | F13: =IF(A13="","",SUMIFS(Docs[Остаток],Docs[Дата],"<="&ДатаОтчета,Docs[Статус],"Проведён",Docs[Контрагент],A13,Docs[Тип долга],"КЗ")) -> 131200
A14: =IF(СПРАВОЧНИКИ!G14="","",СПРАВОЧНИКИ!G14) -> Арендодатель | B14: =IF(A14="","",SUMIFS(Docs[Сумма],Docs[Дата],"<="&ДатаОтчета,Docs[Статус],"Проведён",Docs[Вид],"Выручка",Docs[Контрагент],A14)) -> 0 | C14: =IF(A14="","",IF(ОПиУ!$N$7=0,"н/д",B14/ОПиУ!$N$7)) -> 0 | D14: =IF(A14="","",SUMIFS(Cash[Поток],Cash[Дата],"<="&ДатаОтчета,Cash[Статус],"Проведён",Cash[Тип],"Оплата клиента",Cash[Контрагент],A14)+SUMIFS(Cash[Поток],Cash[Дата],"<="&ДатаОтчета,Cash[Статус],"Проведён",Cash[Тип],"Возврат клиенту",Cash[Контрагент],A14)) -> 0 | E14: =IF(A14="","",SUMIFS(Docs[Остаток],Docs[Дата],"<="&ДатаОтчета,Docs[Статус],"Проведён",Docs[Тип долга],"ДЗ",Docs[Контрагент],A14)) -> 0 | F14: =IF(A14="","",SUMIFS(Docs[Остаток],Docs[Дата],"<="&ДатаОтчета,Docs[Статус],"Проведён",Docs[Контрагент],A14,Docs[Тип долга],"КЗ")) -> 0
A15: =IF(СПРАВОЧНИКИ!G15="","",СПРАВОЧНИКИ!G15) -> Рекламная площадка | B15: =IF(A15="","",SUMIFS(Docs[Сумма],Docs[Дата],"<="&ДатаОтчета,Docs[Статус],"Проведён",Docs[Вид],"Выручка",Docs[Контрагент],A15)) -> 0 | C15: =IF(A15="","",IF(ОПиУ!$N$7=0,"н/д",B15/ОПиУ!$N$7)) -> 0 | D15: =IF(A15="","",SUMIFS(Cash[Поток],Cash[Дата],"<="&ДатаОтчета,Cash[Статус],"Проведён",Cash[Тип],"Оплата клиента",Cash[Контрагент],A15)+SUMIFS(Cash[Поток],Cash[Дата],"<="&ДатаОтчета,Cash[Статус],"Проведён",Cash[Тип],"Возврат клиенту",Cash[Контрагент],A15)) -> 0 | E15: =IF(A15="","",SUMIFS(Docs[Остаток],Docs[Дата],"<="&ДатаОтчета,Docs[Статус],"Проведён",Docs[Тип долга],"ДЗ",Docs[Контрагент],A15)) -> 0 | F15: =IF(A15="","",SUMIFS(Docs[Остаток],Docs[Дата],"<="&ДатаОтчета,Docs[Статус],"Проведён",Docs[Контрагент],A15,Docs[Тип долга],"КЗ")) -> 0
A16: =IF(СПРАВОЧНИКИ!G16="","",СПРАВОЧНИКИ!G16) -> Облачные сервисы | B16: =IF(A16="","",SUMIFS(Docs[Сумма],Docs[Дата],"<="&ДатаОтчета,Docs[Статус],"Проведён",Docs[Вид],"Выручка",Docs[Контрагент],A16)) -> 0 | C16: =IF(A16="","",IF(ОПиУ!$N$7=0,"н/д",B16/ОПиУ!$N$7)) -> 0 | D16: =IF(A16="","",SUMIFS(Cash[Поток],Cash[Дата],"<="&ДатаОтчета,Cash[Статус],"Проведён",Cash[Тип],"Оплата клиента",Cash[Контрагент],A16)+SUMIFS(Cash[Поток],Cash[Дата],"<="&ДатаОтчета,Cash[Статус],"Проведён",Cash[Тип],"Возврат клиенту",Cash[Контрагент],A16)) -> 0 | E16: =IF(A16="","",SUMIFS(Docs[Остаток],Docs[Дата],"<="&ДатаОтчета,Docs[Статус],"Проведён",Docs[Тип долга],"ДЗ",Docs[Контрагент],A16)) -> 0 | F16: =IF(A16="","",SUMIFS(Docs[Остаток],Docs[Дата],"<="&ДатаОтчета,Docs[Статус],"Проведён",Docs[Контрагент],A16,Docs[Тип долга],"КЗ")) -> 0
A17: =IF(СПРАВОЧНИКИ!G17="","",СПРАВОЧНИКИ!G17) -> Сотрудники | B17: =IF(A17="","",SUMIFS(Docs[Сумма],Docs[Дата],"<="&ДатаОтчета,Docs[Статус],"Проведён",Docs[Вид],"Выручка",Docs[Контрагент],A17)) -> 0 | C17: =IF(A17="","",IF(ОПиУ!$N$7=0,"н/д",B17/ОПиУ!$N$7)) -> 0 | D17: =IF(A17="","",SUMIFS(Cash[Поток],Cash[Дата],"<="&ДатаОтчета,Cash[Статус],"Проведён",Cash[Тип],"Оплата клиента",Cash[Контрагент],A17)+SUMIFS(Cash[Поток],Cash[Дата],"<="&ДатаОтчета,Cash[Статус],"Проведён",Cash[Тип],"Возврат клиенту",Cash[Контрагент],A17)) -> 0 | E17: =IF(A17="","",SUMIFS(Docs[Остаток],Docs[Дата],"<="&ДатаОтчета,Docs[Статус],"Проведён",Docs[Тип долга],"ДЗ",Docs[Контрагент],A17)) -> 0 | F17: =IF(A17="","",SUMIFS(Docs[Остаток],Docs[Дата],"<="&ДатаОтчета,Docs[Статус],"Проведён",Docs[Контрагент],A17,Docs[Тип долга],"КЗ")) -> 0
A18: =IF(СПРАВОЧНИКИ!G18="","",СПРАВОЧНИКИ!G18) -> Бюджет | B18: =IF(A18="","",SUMIFS(Docs[Сумма],Docs[Дата],"<="&ДатаОтчета,Docs[Статус],"Проведён",Docs[Вид],"Выручка",Docs[Контрагент],A18)) -> 0 | C18: =IF(A18="","",IF(ОПиУ!$N$7=0,"н/д",B18/ОПиУ!$N$7)) -> 0 | D18: =IF(A18="","",SUMIFS(Cash[Поток],Cash[Дата],"<="&ДатаОтчета,Cash[Статус],"Проведён",Cash[Тип],"Оплата клиента",Cash[Контрагент],A18)+SUMIFS(Cash[Поток],Cash[Дата],"<="&ДатаОтчета,Cash[Статус],"Проведён",Cash[Тип],"Возврат клиенту",Cash[Контрагент],A18)) -> 0 | E18: =IF(A18="","",SUMIFS(Docs[Остаток],Docs[Дата],"<="&ДатаОтчета,Docs[Статус],"Проведён",Docs[Тип долга],"ДЗ",Docs[Контрагент],A18)) -> 0 | F18: =IF(A18="","",SUMIFS(Docs[Остаток],Docs[Дата],"<="&ДатаОтчета,Docs[Статус],"Проведён",Docs[Контрагент],A18,Docs[Тип долга],"КЗ")) -> 0
... A66: =IF(СПРАВОЧНИКИ!G66="","",СПРАВОЧНИКИ!G66) | B66: =IF(A66="","",SUMIFS(Docs[Сумма],Docs[Дата],"<="&ДатаОтчета,Docs[Статус],"Проведён",Docs[Вид],"Выручка",Docs[Контрагент],A66)) | C66: =IF(A66="","",IF(ОПиУ!$N$7=0,"н/д",B66/ОПиУ!$N$7)) | D66: =IF(A66="","",SUMIFS(Cash[Поток],Cash[Дата],"<="&ДатаОтчета,Cash[Статус],"Проведён",Cash[Тип],"Оплата клиента",Cash[Контрагент],A66)+SUMIFS(Cash[Поток],Cash[Дата],"<="&ДатаОтчета,Cash[Статус],"Проведён",Cash[Тип],"Возврат клиенту",Cash[Контрагент],A66)) | E66: =IF(A66="","",SUMIFS(Docs[Остаток],Docs[Дата],"<="&ДатаОтчета,Docs[Статус],"Проведён",Docs[Тип долга],"ДЗ",Docs[Контрагент],A66)) | F66: =IF(A66="","",SUMIFS(Docs[Остаток],Docs[Дата],"<="&ДатаОтчета,Docs[Статус],"Проведён",Docs[Контрагент],A66,Docs[Тип долга],"КЗ"))
A69: Доля крупнейшего клиента | B69: =IF(ОПиУ!N7=0,"н/д",MAX(B7:B66)/ОПиУ!N7) -> 0.27967258
A70: Риск концентрации | B70: =IF(NOT(ISNUMBER(B69)),"Нет выручки",IF(B69>0.3,"Крупнейший клиент >30%","Крупнейший клиент ≤30%")) -> Крупнейший клиент ≤30%
A73: Направление | B73: Выручка | C73: Прямые расходы | D73: Маржинальный результат
A74: Консалтинг | B74: =SUMIFS(Docs[Сумма],Docs[Дата],"<="&ДатаОтчета,Docs[Статус],"Проведён",Docs[Вид],"Выручка",Docs[Проект],A74) -> 2769000 | C74: =SUMIFS(Docs[Сумма],Docs[Дата],"<="&ДатаОтчета,Docs[Статус],"Проведён",Docs[Вид],"Себестоимость",Docs[Проект],A74) -> 0 | D74: =B74-C74 -> 2769000
A75: Автоматизация | B75: =SUMIFS(Docs[Сумма],Docs[Дата],"<="&ДатаОтчета,Docs[Статус],"Проведён",Docs[Вид],"Выручка",Docs[Проект],A75) -> 2112000 | C75: =SUMIFS(Docs[Сумма],Docs[Дата],"<="&ДатаОтчета,Docs[Статус],"Проведён",Docs[Вид],"Себестоимость",Docs[Проект],A75) -> 2112000 | D75: =B75-C75 -> 0
A76: Поддержка | B76: =SUMIFS(Docs[Сумма],Docs[Дата],"<="&ДатаОтчета,Docs[Статус],"Проведён",Docs[Вид],"Выручка",Docs[Проект],A76) -> 1716000 | C76: =SUMIFS(Docs[Сумма],Docs[Дата],"<="&ДатаОтчета,Docs[Статус],"Проведён",Docs[Вид],"Себестоимость",Docs[Проект],A76) -> 0 | D76: =B76-C76 -> 1716000
A77: Общие | B77: =SUMIFS(Docs[Сумма],Docs[Дата],"<="&ДатаОтчета,Docs[Статус],"Проведён",Docs[Вид],"Выручка",Docs[Проект],A77) -> 0 | C77: =SUMIFS(Docs[Сумма],Docs[Дата],"<="&ДатаОтчета,Docs[Статус],"Проведён",Docs[Вид],"Себестоимость",Docs[Проект],A77) -> 0 | D77: =B77-C77 -> 0
A80: Возраст долга | B80: Дебиторка | C80: Кредиторка
A81: Не просрочена | B81: =SUMIFS(Docs[Остаток],Docs[Дата],"<="&ДатаОтчета,Docs[Статус],"Проведён",Docs[Тип долга],"ДЗ",Docs[Возраст],A81) -> 0 | C81: =SUMIFS(Docs[Остаток],Docs[Дата],"<="&ДатаОтчета,Docs[Статус],"Проведён",Docs[Возраст],A81,Docs[Тип долга],"КЗ") -> 0
A82: 1–30 дней | B82: =SUMIFS(Docs[Остаток],Docs[Дата],"<="&ДатаОтчета,Docs[Статус],"Проведён",Docs[Тип долга],"ДЗ",Docs[Возраст],A82) -> 59040 | C82: =SUMIFS(Docs[Остаток],Docs[Дата],"<="&ДатаОтчета,Docs[Статус],"Проведён",Docs[Возраст],A82,Docs[Тип долга],"КЗ") -> 131200
A83: 31–60 дней | B83: =SUMIFS(Docs[Остаток],Docs[Дата],"<="&ДатаОтчета,Docs[Статус],"Проведён",Docs[Тип долга],"ДЗ",Docs[Возраст],A83) -> 0 | C83: =SUMIFS(Docs[Остаток],Docs[Дата],"<="&ДатаОтчета,Docs[Статус],"Проведён",Docs[Возраст],A83,Docs[Тип долга],"КЗ") -> 0
A84: 61–90 дней | B84: =SUMIFS(Docs[Остаток],Docs[Дата],"<="&ДатаОтчета,Docs[Статус],"Проведён",Docs[Тип долга],"ДЗ",Docs[Возраст],A84) -> 0 | C84: =SUMIFS(Docs[Остаток],Docs[Дата],"<="&ДатаОтчета,Docs[Статус],"Проведён",Docs[Возраст],A84,Docs[Тип долга],"КЗ") -> 0
A85: Более 90 дней | B85: =SUMIFS(Docs[Остаток],Docs[Дата],"<="&ДатаОтчета,Docs[Статус],"Проведён",Docs[Тип долга],"ДЗ",Docs[Возраст],A85) -> 0 | C85: =SUMIFS(Docs[Остаток],Docs[Дата],"<="&ДатаОтчета,Docs[Статус],"Проведён",Docs[Возраст],A85,Docs[Тип долга],"КЗ") -> 0
A87: Просроченная ДЗ | B87: =SUM(B82:B85) -> 59040
A88: Просроченная КЗ | B88: =SUM(C82:C85) -> 131200

Sheet КРЕДИТ
A1: Главная панель | D1: Настройки | F1: Контроль
A2: КРЕДИТ
A3: LEO STUDIO • Управленческий учёт • RUB
A6: Параметр | B6: Значение | C6: Условие
A7: ID кредита | B7: КР-1 | C7: Один новый кредит в графике
A8: Кредитор | B8: Банк | C8: Дополнительные займы: ручная аналитика
A9: Сумма | B9: 300000 | C9: Сверяется с получением в ОПЕРАЦИИ
A10: Годовая ставка | B10: 0.18 | C10: Изменение ставки только будущего графика вручную
A11: Дата выдачи | B11: 46027 | C11: Первый платёж через месяц условно в конце января
A12: Срок, месяцев | B12: 24 | C12: Не более 60 месяцев
A13: Аннуитет | B13: =IF(B10=0,B9/B12,-PMT(B10/12,B12,B9)) -> 14977.231 | C13: Ежемесячно, проценты на остаток
A14: Получено фактически | B14: =SUMIFS(Cash[Сумма],Cash[Дата],"<="&ДатаОтчета,Cash[Статус],"Проведён",Cash[Тип],"Получение кредита",Cash[Документ],B7) -> 300000 | C14: Сумма за период
A15: Погашено тело | B15: =SUMIFS(Cash[Сумма],Cash[Дата],"<="&ДатаОтчета,Cash[Статус],"Проведён",Cash[Тип],"Тело кредита",Cash[Документ],B7) -> 163971.85 | C15: Досрочное включено
A16: Остаток долга | B16: =B14-B15 -> 136028.15 | C16: Движение денег, без подмены графиком
A19: Период | B19: Начальный долг | C19: Проценты | D19: Плановый платёж | E19: Плановое тело | F19: Досрочно план | G19: Конечный долг | H19: Тело факт | I19: Проценты факт | J19: Отклонение тела
A20: =DATE(YEAR(EDATE($B$11,0)),MONTH(EDATE($B$11,0)),28) -> 46050 | B20: =$B$9 -> 300000 | C20: =ROUND(B20*$B$10/12,2) -> 4500 | D20: =IF(B20=0,0,ROUND(MIN($B$13,B20+C20),2)) -> 14977.23 | E20: =MAX(0,D20-C20) -> 10477.23 | F20: 0 | G20: =MAX(0,B20-E20-F20) -> 289522.77 | H20: =SUMIFS(Cash[Сумма],Cash[Дата],"<="&ДатаОтчета,Cash[Статус],"Проведён",Cash[Тип],"Тело кредита",Cash[Дата],">="&EOMONTH(A20,-1)+1,Cash[Дата],"<"&EDATE(EOMONTH(A20,-1)+1,1),Cash[Документ],$B$7) -> 10477.23 | I20: =SUMIFS(Cash[Сумма],Cash[Дата],"<="&ДатаОтчета,Cash[Статус],"Проведён",Cash[Тип],"Проценты",Cash[Дата],">="&EOMONTH(A20,-1)+1,Cash[Дата],"<"&EDATE(EOMONTH(A20,-1)+1,1)) -> 4500 | J20: =IF(A20>ДатаОтчета,"",H20-E20-F20) -> 0
A21: =DATE(YEAR(EDATE($B$11,1)),MONTH(EDATE($B$11,1)),28) -> 46081 | B21: =G20 -> 289522.77 | C21: =ROUND(B21*$B$10/12,2) -> 4342.84 | D21: =IF(B21=0,0,ROUND(MIN($B$13,B21+C21),2)) -> 14977.23 | E21: =MAX(0,D21-C21) -> 10634.39 | F21: 0 | G21: =MAX(0,B21-E21-F21) -> 278888.38 | H21: =SUMIFS(Cash[Сумма],Cash[Дата],"<="&ДатаОтчета,Cash[Статус],"Проведён",Cash[Тип],"Тело кредита",Cash[Дата],">="&EOMONTH(A21,-1)+1,Cash[Дата],"<"&EDATE(EOMONTH(A21,-1)+1,1),Cash[Документ],$B$7) -> 10634.39 | I21: =SUMIFS(Cash[Сумма],Cash[Дата],"<="&ДатаОтчета,Cash[Статус],"Проведён",Cash[Тип],"Проценты",Cash[Дата],">="&EOMONTH(A21,-1)+1,Cash[Дата],"<"&EDATE(EOMONTH(A21,-1)+1,1)) -> 4342.84 | J21: =IF(A21>ДатаОтчета,"",H21-E21-F21) -> 0
A22: =DATE(YEAR(EDATE($B$11,2)),MONTH(EDATE($B$11,2)),28) -> 46109 | B22: =G21 -> 278888.38 | C22: =ROUND(B22*$B$10/12,2) -> 4183.33 | D22: =IF(B22=0,0,ROUND(MIN($B$13,B22+C22),2)) -> 14977.23 | E22: =MAX(0,D22-C22) -> 10793.9 | F22: 0 | G22: =MAX(0,B22-E22-F22) -> 268094.48 | H22: =SUMIFS(Cash[Сумма],Cash[Дата],"<="&ДатаОтчета,Cash[Статус],"Проведён",Cash[Тип],"Тело кредита",Cash[Дата],">="&EOMONTH(A22,-1)+1,Cash[Дата],"<"&EDATE(EOMONTH(A22,-1)+1,1),Cash[Документ],$B$7) -> 10793.9 | I22: =SUMIFS(Cash[Сумма],Cash[Дата],"<="&ДатаОтчета,Cash[Статус],"Проведён",Cash[Тип],"Проценты",Cash[Дата],">="&EOMONTH(A22,-1)+1,Cash[Дата],"<"&EDATE(EOMONTH(A22,-1)+1,1)) -> 4183.33 | J22: =IF(A22>ДатаОтчета,"",H22-E22-F22) -> 0
A23: =DATE(YEAR(EDATE($B$11,3)),MONTH(EDATE($B$11,3)),28) -> 46140 | B23: =G22 -> 268094.48 | C23: =ROUND(B23*$B$10/12,2) -> 4021.42 | D23: =IF(B23=0,0,ROUND(MIN($B$13,B23+C23),2)) -> 14977.23 | E23: =MAX(0,D23-C23) -> 10955.81 | F23: 0 | G23: =MAX(0,B23-E23-F23) -> 257138.67 | H23: =SUMIFS(Cash[Сумма],Cash[Дата],"<="&ДатаОтчета,Cash[Статус],"Проведён",Cash[Тип],"Тело кредита",Cash[Дата],">="&EOMONTH(A23,-1)+1,Cash[Дата],"<"&EDATE(EOMONTH(A23,-1)+1,1),Cash[Документ],$B$7) -> 10955.81 | I23: =SUMIFS(Cash[Сумма],Cash[Дата],"<="&ДатаОтчета,Cash[Статус],"Проведён",Cash[Тип],"Проценты",Cash[Дата],">="&EOMONTH(A23,-1)+1,Cash[Дата],"<"&EDATE(EOMONTH(A23,-1)+1,1)) -> 4021.42 | J23: =IF(A23>ДатаОтчета,"",H23-E23-F23) -> 0
A24: =DATE(YEAR(EDATE($B$11,4)),MONTH(EDATE($B$11,4)),28) -> 46170 | B24: =G23 -> 257138.67 | C24: =ROUND(B24*$B$10/12,2) -> 3857.08 | D24: =IF(B24=0,0,ROUND(MIN($B$13,B24+C24),2)) -> 14977.23 | E24: =MAX(0,D24-C24) -> 11120.15 | F24: 0 | G24: =MAX(0,B24-E24-F24) -> 246018.52 | H24: =SUMIFS(Cash[Сумма],Cash[Дата],"<="&ДатаОтчета,Cash[Статус],"Проведён",Cash[Тип],"Тело кредита",Cash[Дата],">="&EOMONTH(A24,-1)+1,Cash[Дата],"<"&EDATE(EOMONTH(A24,-1)+1,1),Cash[Документ],$B$7) -> 11120.15 | I24: =SUMIFS(Cash[Сумма],Cash[Дата],"<="&ДатаОтчета,Cash[Статус],"Проведён",Cash[Тип],"Проценты",Cash[Дата],">="&EOMONTH(A24,-1)+1,Cash[Дата],"<"&EDATE(EOMONTH(A24,-1)+1,1)) -> 3857.08 | J24: =IF(A24>ДатаОтчета,"",H24-E24-F24) -> 0
A25: =DATE(YEAR(EDATE($B$11,5)),MONTH(EDATE($B$11,5)),28) -> 46201 | B25: =G24 -> 246018.52 | C25: =ROUND(B25*$B$10/12,2) -> 3690.28 | D25: =IF(B25=0,0,ROUND(MIN($B$13,B25+C25),2)) -> 14977.23 | E25: =MAX(0,D25-C25) -> 11286.95 | F25: 25000 | G25: =MAX(0,B25-E25-F25) -> 209731.57 | H25: =SUMIFS(Cash[Сумма],Cash[Дата],"<="&ДатаОтчета,Cash[Статус],"Проведён",Cash[Тип],"Тело кредита",Cash[Дата],">="&EOMONTH(A25,-1)+1,Cash[Дата],"<"&EDATE(EOMONTH(A25,-1)+1,1),Cash[Документ],$B$7) -> 36286.95 | I25: =SUMIFS(Cash[Сумма],Cash[Дата],"<="&ДатаОтчета,Cash[Статус],"Проведён",Cash[Тип],"Проценты",Cash[Дата],">="&EOMONTH(A25,-1)+1,Cash[Дата],"<"&EDATE(EOMONTH(A25,-1)+1,1)) -> 3690.28 | J25: =IF(A25>ДатаОтчета,"",H25-E25-F25) -> 0
A26: =DATE(YEAR(EDATE($B$11,6)),MONTH(EDATE($B$11,6)),28) -> 46231 | B26: =G25 -> 209731.57 | C26: =ROUND(B26*$B$10/12,2) -> 3145.97 | D26: =IF(B26=0,0,ROUND(MIN($B$13,B26+C26),2)) -> 14977.23 | E26: =MAX(0,D26-C26) -> 11831.26 | F26: 0 | G26: =MAX(0,B26-E26-F26) -> 197900.31 | H26: =SUMIFS(Cash[Сумма],Cash[Дата],"<="&ДатаОтчета,Cash[Статус],"Проведён",Cash[Тип],"Тело кредита",Cash[Дата],">="&EOMONTH(A26,-1)+1,Cash[Дата],"<"&EDATE(EOMONTH(A26,-1)+1,1),Cash[Документ],$B$7) -> 11831.26 | I26: =SUMIFS(Cash[Сумма],Cash[Дата],"<="&ДатаОтчета,Cash[Статус],"Проведён",Cash[Тип],"Проценты",Cash[Дата],">="&EOMONTH(A26,-1)+1,Cash[Дата],"<"&EDATE(EOMONTH(A26,-1)+1,1)) -> 3145.97 | J26: =IF(A26>ДатаОтчета,"",H26-E26-F26) -> 0
A27: =DATE(YEAR(EDATE($B$11,7)),MONTH(EDATE($B$11,7)),28) -> 46262 | B27: =G26 -> 197900.31 | C27: =ROUND(B27*$B$10/12,2) -> 2968.5 | D27: =IF(B27=0,0,ROUND(MIN($B$13,B27+C27),2)) -> 14977.23 | E27: =MAX(0,D27-C27) -> 12008.73 | F27: 0 | G27: =MAX(0,B27-E27-F27) -> 185891.58 | H27: =SUMIFS(Cash[Сумма],Cash[Дата],"<="&ДатаОтчета,Cash[Статус],"Проведён",Cash[Тип],"Тело кредита",Cash[Дата],">="&EOMONTH(A27,-1)+1,Cash[Дата],"<"&EDATE(EOMONTH(A27,-1)+1,1),Cash[Документ],$B$7) -> 12008.73 | I27: =SUMIFS(Cash[Сумма],Cash[Дата],"<="&ДатаОтчета,Cash[Статус],"Проведён",Cash[Тип],"Проценты",Cash[Дата],">="&EOMONTH(A27,-1)+1,Cash[Дата],"<"&EDATE(EOMONTH(A27,-1)+1,1)) -> 2968.5 | J27: =IF(A27>ДатаОтчета,"",H27-E27-F27) -> 0
A28: =DATE(YEAR(EDATE($B$11,8)),MONTH(EDATE($B$11,8)),28) -> 46293 | B28: =G27 -> 185891.58 | C28: =ROUND(B28*$B$10/12,2) -> 2788.37 | D28: =IF(B28=0,0,ROUND(MIN($B$13,B28+C28),2)) -> 14977.23 | E28: =MAX(0,D28-C28) -> 12188.86 | F28: 0 | G28: =MAX(0,B28-E28-F28) -> 173702.72 | H28: =SUMIFS(Cash[Сумма],Cash[Дата],"<="&ДатаОтчета,Cash[Статус],"Проведён",Cash[Тип],"Тело кредита",Cash[Дата],">="&EOMONTH(A28,-1)+1,Cash[Дата],"<"&EDATE(EOMONTH(A28,-1)+1,1),Cash[Документ],$B$7) -> 12188.86 | I28: =SUMIFS(Cash[Сумма],Cash[Дата],"<="&ДатаОтчета,Cash[Статус],"Проведён",Cash[Тип],"Проценты",Cash[Дата],">="&EOMONTH(A28,-1)+1,Cash[Дата],"<"&EDATE(EOMONTH(A28,-1)+1,1)) -> 2788.37 | J28: =IF(A28>ДатаОтчета,"",H28-E28-F28) -> 0
A29: =DATE(YEAR(EDATE($B$11,9)),MONTH(EDATE($B$11,9)),28) -> 46323 | B29: =G28 -> 173702.72 | C29: =ROUND(B29*$B$10/12,2) -> 2605.54 | D29: =IF(B29=0,0,ROUND(MIN($B$13,B29+C29),2)) -> 14977.23 | E29: =MAX(0,D29-C29) -> 12371.69 | F29: 0 | G29: =MAX(0,B29-E29-F29) -> 161331.03 | H29: =SUMIFS(Cash[Сумма],Cash[Дата],"<="&ДатаОтчета,Cash[Статус],"Проведён",Cash[Тип],"Тело кредита",Cash[Дата],">="&EOMONTH(A29,-1)+1,Cash[Дата],"<"&EDATE(EOMONTH(A29,-1)+1,1),Cash[Документ],$B$7) -> 12371.69 | I29: =SUMIFS(Cash[Сумма],Cash[Дата],"<="&ДатаОтчета,Cash[Статус],"Проведён",Cash[Тип],"Проценты",Cash[Дата],">="&EOMONTH(A29,-1)+1,Cash[Дата],"<"&EDATE(EOMONTH(A29,-1)+1,1)) -> 2605.54 | J29: =IF(A29>ДатаОтчета,"",H29-E29-F29) -> 1.8189894e-12
A30: =DATE(YEAR(EDATE($B$11,10)),MONTH(EDATE($B$11,10)),28) -> 46354 | B30: =G29 -> 161331.03 | C30: =ROUND(B30*$B$10/12,2) -> 2419.97 | D30: =IF(B30=0,0,ROUND(MIN($B$13,B30+C30),2)) -> 14977.23 | E30: =MAX(0,D30-C30) -> 12557.26 | F30: 0 | G30: =MAX(0,B30-E30-F30) -> 148773.77 | H30: =SUMIFS(Cash[Сумма],Cash[Дата],"<="&ДатаОтчета,Cash[Статус],"Проведён",Cash[Тип],"Тело кредита",Cash[Дата],">="&EOMONTH(A30,-1)+1,Cash[Дата],"<"&EDATE(EOMONTH(A30,-1)+1,1),Cash[Документ],$B$7) -> 12557.26 | I30: =SUMIFS(Cash[Сумма],Cash[Дата],"<="&ДатаОтчета,Cash[Статус],"Проведён",Cash[Тип],"Проценты",Cash[Дата],">="&EOMONTH(A30,-1)+1,Cash[Дата],"<"&EDATE(EOMONTH(A30,-1)+1,1)) -> 2419.97 | J30: =IF(A30>ДатаОтчета,"",H30-E30-F30) -> 0
A31: =DATE(YEAR(EDATE($B$11,11)),MONTH(EDATE($B$11,11)),28) -> 46384 | B31: =G30 -> 148773.77 | C31: =ROUND(B31*$B$10/12,2) -> 2231.61 | D31: =IF(B31=0,0,ROUND(MIN($B$13,B31+C31),2)) -> 14977.23 | E31: =MAX(0,D31-C31) -> 12745.62 | F31: 0 | G31: =MAX(0,B31-E31-F31) -> 136028.15 | H31: =SUMIFS(Cash[Сумма],Cash[Дата],"<="&ДатаОтчета,Cash[Статус],"Проведён",Cash[Тип],"Тело кредита",Cash[Дата],">="&EOMONTH(A31,-1)+1,Cash[Дата],"<"&EDATE(EOMONTH(A31,-1)+1,1),Cash[Документ],$B$7) -> 12745.62 | I31: =SUMIFS(Cash[Сумма],Cash[Дата],"<="&ДатаОтчета,Cash[Статус],"Проведён",Cash[Тип],"Проценты",Cash[Дата],">="&EOMONTH(A31,-1)+1,Cash[Дата],"<"&EDATE(EOMONTH(A31,-1)+1,1)) -> 2231.61 | J31: =IF(A31>ДатаОтчета,"",H31-E31-F31) -> 1.8189894e-12
A32: =DATE(YEAR(EDATE($B$11,12)),MONTH(EDATE($B$11,12)),28) -> 46415 | B32: =G31 -> 136028.15 | C32: =ROUND(B32*$B$10/12,2) -> 2040.42 | D32: =IF(B32=0,0,ROUND(MIN($B$13,B32+C32),2)) -> 14977.23 | E32: =MAX(0,D32-C32) -> 12936.81 | F32: 0 | G32: =MAX(0,B32-E32-F32) -> 123091.34 | H32: =SUMIFS(Cash[Сумма],Cash[Дата],"<="&ДатаОтчета,Cash[Статус],"Проведён",Cash[Тип],"Тело кредита",Cash[Дата],">="&EOMONTH(A32,-1)+1,Cash[Дата],"<"&EDATE(EOMONTH(A32,-1)+1,1),Cash[Документ],$B$7) -> 0 | I32: =SUMIFS(Cash[Сумма],Cash[Дата],"<="&ДатаОтчета,Cash[Статус],"Проведён",Cash[Тип],"Проценты",Cash[Дата],">="&EOMONTH(A32,-1)+1,Cash[Дата],"<"&EDATE(EOMONTH(A32,-1)+1,1)) -> 0 | J32: =IF(A32>ДатаОтчета,"",H32-E32-F32)
A33: =DATE(YEAR(EDATE($B$11,13)),MONTH(EDATE($B$11,13)),28) -> 46446 | B33: =G32 -> 123091.34 | C33: =ROUND(B33*$B$10/12,2) -> 1846.37 | D33: =IF(B33=0,0,ROUND(MIN($B$13,B33+C33),2)) -> 14977.23 | E33: =MAX(0,D33-C33) -> 13130.86 | F33: 0 | G33: =MAX(0,B33-E33-F33) -> 109960.48 | H33: =SUMIFS(Cash[Сумма],Cash[Дата],"<="&ДатаОтчета,Cash[Статус],"Проведён",Cash[Тип],"Тело кредита",Cash[Дата],">="&EOMONTH(A33,-1)+1,Cash[Дата],"<"&EDATE(EOMONTH(A33,-1)+1,1),Cash[Документ],$B$7) -> 0 | I33: =SUMIFS(Cash[Сумма],Cash[Дата],"<="&ДатаОтчета,Cash[Статус],"Проведён",Cash[Тип],"Проценты",Cash[Дата],">="&EOMONTH(A33,-1)+1,Cash[Дата],"<"&EDATE(EOMONTH(A33,-1)+1,1)) -> 0 | J33: =IF(A33>ДатаОтчета,"",H33-E33-F33)
A34: =DATE(YEAR(EDATE($B$11,14)),MONTH(EDATE($B$11,14)),28) -> 46474 | B34: =G33 -> 109960.48 | C34: =ROUND(B34*$B$10/12,2) -> 1649.41 | D34: =IF(B34=0,0,ROUND(MIN($B$13,B34+C34),2)) -> 14977.23 | E34: =MAX(0,D34-C34) -> 13327.82 | F34: 0 | G34: =MAX(0,B34-E34-F34) -> 96632.66 | H34: =SUMIFS(Cash[Сумма],Cash[Дата],"<="&ДатаОтчета,Cash[Статус],"Проведён",Cash[Тип],"Тело кредита",Cash[Дата],">="&EOMONTH(A34,-1)+1,Cash[Дата],"<"&EDATE(EOMONTH(A34,-1)+1,1),Cash[Документ],$B$7) -> 0 | I34: =SUMIFS(Cash[Сумма],Cash[Дата],"<="&ДатаОтчета,Cash[Статус],"Проведён",Cash[Тип],"Проценты",Cash[Дата],">="&EOMONTH(A34,-1)+1,Cash[Дата],"<"&EDATE(EOMONTH(A34,-1)+1,1)) -> 0 | J34: =IF(A34>ДатаОтчета,"",H34-E34-F34)
A35: =DATE(YEAR(EDATE($B$11,15)),MONTH(EDATE($B$11,15)),28) -> 46505 | B35: =G34 -> 96632.66 | C35: =ROUND(B35*$B$10/12,2) -> 1449.49 | D35: =IF(B35=0,0,ROUND(MIN($B$13,B35+C35),2)) -> 14977.23 | E35: =MAX(0,D35-C35) -> 13527.74 | F35: 0 | G35: =MAX(0,B35-E35-F35) -> 83104.92 | H35: =SUMIFS(Cash[Сумма],Cash[Дата],"<="&ДатаОтчета,Cash[Статус],"Проведён",Cash[Тип],"Тело кредита",Cash[Дата],">="&EOMONTH(A35,-1)+1,Cash[Дата],"<"&EDATE(EOMONTH(A35,-1)+1,1),Cash[Документ],$B$7) -> 0 | I35: =SUMIFS(Cash[Сумма],Cash[Дата],"<="&ДатаОтчета,Cash[Статус],"Проведён",Cash[Тип],"Проценты",Cash[Дата],">="&EOMONTH(A35,-1)+1,Cash[Дата],"<"&EDATE(EOMONTH(A35,-1)+1,1)) -> 0 | J35: =IF(A35>ДатаОтчета,"",H35-E35-F35)
A36: =DATE(YEAR(EDATE($B$11,16)),MONTH(EDATE($B$11,16)),28) -> 46535 | B36: =G35 -> 83104.92 | C36: =ROUND(B36*$B$10/12,2) -> 1246.57 | D36: =IF(B36=0,0,ROUND(MIN($B$13,B36+C36),2)) -> 14977.23 | E36: =MAX(0,D36-C36) -> 13730.66 | F36: 0 | G36: =MAX(0,B36-E36-F36) -> 69374.26 | H36: =SUMIFS(Cash[Сумма],Cash[Дата],"<="&ДатаОтчета,Cash[Статус],"Проведён",Cash[Тип],"Тело кредита",Cash[Дата],">="&EOMONTH(A36,-1)+1,Cash[Дата],"<"&EDATE(EOMONTH(A36,-1)+1,1),Cash[Документ],$B$7) -> 0 | I36: =SUMIFS(Cash[Сумма],Cash[Дата],"<="&ДатаОтчета,Cash[Статус],"Проведён",Cash[Тип],"Проценты",Cash[Дата],">="&EOMONTH(A36,-1)+1,Cash[Дата],"<"&EDATE(EOMONTH(A36,-1)+1,1)) -> 0 | J36: =IF(A36>ДатаОтчета,"",H36-E36-F36)
A37: =DATE(YEAR(EDATE($B$11,17)),MONTH(EDATE($B$11,17)),28) -> 46566 | B37: =G36 -> 69374.26 | C37: =ROUND(B37*$B$10/12,2) -> 1040.61 | D37: =IF(B37=0,0,ROUND(MIN($B$13,B37+C37),2)) -> 14977.23 | E37: =MAX(0,D37-C37) -> 13936.62 | F37: 0 | G37: =MAX(0,B37-E37-F37) -> 55437.64 | H37: =SUMIFS(Cash[Сумма],Cash[Дата],"<="&ДатаОтчета,Cash[Статус],"Проведён",Cash[Тип],"Тело кредита",Cash[Дата],">="&EOMONTH(A37,-1)+1,Cash[Дата],"<"&EDATE(EOMONTH(A37,-1)+1,1),Cash[Документ],$B$7) -> 0 | I37: =SUMIFS(Cash[Сумма],Cash[Дата],"<="&ДатаОтчета,Cash[Статус],"Проведён",Cash[Тип],"Проценты",Cash[Дата],">="&EOMONTH(A37,-1)+1,Cash[Дата],"<"&EDATE(EOMONTH(A37,-1)+1,1)) -> 0 | J37: =IF(A37>ДатаОтчета,"",H37-E37-F37)
A38: =DATE(YEAR(EDATE($B$11,18)),MONTH(EDATE($B$11,18)),28) -> 46596 | B38: =G37 -> 55437.64 | C38: =ROUND(B38*$B$10/12,2) -> 831.56 | D38: =IF(B38=0,0,ROUND(MIN($B$13,B38+C38),2)) -> 14977.23 | E38: =MAX(0,D38-C38) -> 14145.67 | F38: 0 | G38: =MAX(0,B38-E38-F38) -> 41291.97 | H38: =SUMIFS(Cash[Сумма],Cash[Дата],"<="&ДатаОтчета,Cash[Статус],"Проведён",Cash[Тип],"Тело кредита",Cash[Дата],">="&EOMONTH(A38,-1)+1,Cash[Дата],"<"&EDATE(EOMONTH(A38,-1)+1,1),Cash[Документ],$B$7) -> 0 | I38: =SUMIFS(Cash[Сумма],Cash[Дата],"<="&ДатаОтчета,Cash[Статус],"Проведён",Cash[Тип],"Проценты",Cash[Дата],">="&EOMONTH(A38,-1)+1,Cash[Дата],"<"&EDATE(EOMONTH(A38,-1)+1,1)) -> 0 | J38: =IF(A38>ДатаОтчета,"",H38-E38-F38)
A39: =DATE(YEAR(EDATE($B$11,19)),MONTH(EDATE($B$11,19)),28) -> 46627 | B39: =G38 -> 41291.97 | C39: =ROUND(B39*$B$10/12,2) -> 619.38 | D39: =IF(B39=0,0,ROUND(MIN($B$13,B39+C39),2)) -> 14977.23 | E39: =MAX(0,D39-C39) -> 14357.85 | F39: 0 | G39: =MAX(0,B39-E39-F39) -> 26934.12 | H39: =SUMIFS(Cash[Сумма],Cash[Дата],"<="&ДатаОтчета,Cash[Статус],"Проведён",Cash[Тип],"Тело кредита",Cash[Дата],">="&EOMONTH(A39,-1)+1,Cash[Дата],"<"&EDATE(EOMONTH(A39,-1)+1,1),Cash[Документ],$B$7) -> 0 | I39: =SUMIFS(Cash[Сумма],Cash[Дата],"<="&ДатаОтчета,Cash[Статус],"Проведён",Cash[Тип],"Проценты",Cash[Дата],">="&EOMONTH(A39,-1)+1,Cash[Дата],"<"&EDATE(EOMONTH(A39,-1)+1,1)) -> 0 | J39: =IF(A39>ДатаОтчета,"",H39-E39-F39)
A40: =DATE(YEAR(EDATE($B$11,20)),MONTH(EDATE($B$11,20)),28) -> 46658 | B40: =G39 -> 26934.12 | C40: =ROUND(B40*$B$10/12,2) -> 404.01 | D40: =IF(B40=0,0,ROUND(MIN($B$13,B40+C40),2)) -> 14977.23 | E40: =MAX(0,D40-C40) -> 14573.22 | F40: 0 | G40: =MAX(0,B40-E40-F40) -> 12360.9 | H40: =SUMIFS(Cash[Сумма],Cash[Дата],"<="&ДатаОтчета,Cash[Статус],"Проведён",Cash[Тип],"Тело кредита",Cash[Дата],">="&EOMONTH(A40,-1)+1,Cash[Дата],"<"&EDATE(EOMONTH(A40,-1)+1,1),Cash[Документ],$B$7) -> 0 | I40: =SUMIFS(Cash[Сумма],Cash[Дата],"<="&ДатаОтчета,Cash[Статус],"Проведён",Cash[Тип],"Проценты",Cash[Дата],">="&EOMONTH(A40,-1)+1,Cash[Дата],"<"&EDATE(EOMONTH(A40,-1)+1,1)) -> 0 | J40: =IF(A40>ДатаОтчета,"",H40-E40-F40)
A41: =DATE(YEAR(EDATE($B$11,21)),MONTH(EDATE($B$11,21)),28) -> 46688 | B41: =G40 -> 12360.9 | C41: =ROUND(B41*$B$10/12,2) -> 185.41 | D41: =IF(B41=0,0,ROUND(MIN($B$13,B41+C41),2)) -> 12546.31 | E41: =MAX(0,D41-C41) -> 12360.9 | F41: 0 | G41: =MAX(0,B41-E41-F41) -> 0 | H41: =SUMIFS(Cash[Сумма],Cash[Дата],"<="&ДатаОтчета,Cash[Статус],"Проведён",Cash[Тип],"Тело кредита",Cash[Дата],">="&EOMONTH(A41,-1)+1,Cash[Дата],"<"&EDATE(EOMONTH(A41,-1)+1,1),Cash[Документ],$B$7) -> 0 | I41: =SUMIFS(Cash[Сумма],Cash[Дата],"<="&ДатаОтчета,Cash[Статус],"Проведён",Cash[Тип],"Проценты",Cash[Дата],">="&EOMONTH(A41,-1)+1,Cash[Дата],"<"&EDATE(EOMONTH(A41,-1)+1,1)) -> 0 | J41: =IF(A41>ДатаОтчета,"",H41-E41-F41)
A42: =DATE(YEAR(EDATE($B$11,22)),MONTH(EDATE($B$11,22)),28) -> 46719 | B42: =G41 -> 0 | C42: =ROUND(B42*$B$10/12,2) -> 0 | D42: =IF(B42=0,0,ROUND(MIN($B$13,B42+C42),2)) -> 0 | E42: =MAX(0,D42-C42) -> 0 | F42: 0 | G42: =MAX(0,B42-E42-F42) -> 0 | H42: =SUMIFS(Cash[Сумма],Cash[Дата],"<="&ДатаОтчета,Cash[Статус],"Проведён",Cash[Тип],"Тело кредита",Cash[Дата],">="&EOMONTH(A42,-1)+1,Cash[Дата],"<"&EDATE(EOMONTH(A42,-1)+1,1),Cash[Документ],$B$7) -> 0 | I42: =SUMIFS(Cash[Сумма],Cash[Дата],"<="&ДатаОтчета,Cash[Статус],"Проведён",Cash[Тип],"Проценты",Cash[Дата],">="&EOMONTH(A42,-1)+1,Cash[Дата],"<"&EDATE(EOMONTH(A42,-1)+1,1)) -> 0 | J42: =IF(A42>ДатаОтчета,"",H42-E42-F42)
A43: =DATE(YEAR(EDATE($B$11,23)),MONTH(EDATE($B$11,23)),28) -> 46749 | B43: =G42 -> 0 | C43: =ROUND(B43*$B$10/12,2) -> 0 | D43: =IF(B43=0,0,ROUND(MIN($B$13,B43+C43),2)) -> 0 | E43: =MAX(0,D43-C43) -> 0 | F43: 0 | G43: =MAX(0,B43-E43-F43) -> 0 | H43: =SUMIFS(Cash[Сумма],Cash[Дата],"<="&ДатаОтчета,Cash[Статус],"Проведён",Cash[Тип],"Тело кредита",Cash[Дата],">="&EOMONTH(A43,-1)+1,Cash[Дата],"<"&EDATE(EOMONTH(A43,-1)+1,1),Cash[Документ],$B$7) -> 0 | I43: =SUMIFS(Cash[Сумма],Cash[Дата],"<="&ДатаОтчета,Cash[Статус],"Проведён",Cash[Тип],"Проценты",Cash[Дата],">="&EOMONTH(A43,-1)+1,Cash[Дата],"<"&EDATE(EOMONTH(A43,-1)+1,1)) -> 0 | J43: =IF(A43>ДатаОтчета,"",H43-E43-F43)
A44: =DATE(YEAR(EDATE($B$11,24)),MONTH(EDATE($B$11,24)),28) -> 46780 | B44: =G43 -> 0 | C44: =ROUND(B44*$B$10/12,2) -> 0 | D44: =IF(B44=0,0,ROUND(MIN($B$13,B44+C44),2)) -> 0 | E44: =MAX(0,D44-C44) -> 0 | F44: 0 | G44: =MAX(0,B44-E44-F44) -> 0 | H44: =SUMIFS(Cash[Сумма],Cash[Дата],"<="&ДатаОтчета,Cash[Статус],"Проведён",Cash[Тип],"Тело кредита",Cash[Дата],">="&EOMONTH(A44,-1)+1,Cash[Дата],"<"&EDATE(EOMONTH(A44,-1)+1,1),Cash[Документ],$B$7) -> 0 | I44: =SUMIFS(Cash[Сумма],Cash[Дата],"<="&ДатаОтчета,Cash[Статус],"Проведён",Cash[Тип],"Проценты",Cash[Дата],">="&EOMONTH(A44,-1)+1,Cash[Дата],"<"&EDATE(EOMONTH(A44,-1)+1,1)) -> 0 | J44: =IF(A44>ДатаОтчета,"",H44-E44-F44)
A45: =DATE(YEAR(EDATE($B$11,25)),MONTH(EDATE($B$11,25)),28) -> 46811 | B45: =G44 -> 0 | C45: =ROUND(B45*$B$10/12,2) -> 0 | D45: =IF(B45=0,0,ROUND(MIN($B$13,B45+C45),2)) -> 0 | E45: =MAX(0,D45-C45) -> 0 | F45: 0 | G45: =MAX(0,B45-E45-F45) -> 0 | H45: =SUMIFS(Cash[Сумма],Cash[Дата],"<="&ДатаОтчета,Cash[Статус],"Проведён",Cash[Тип],"Тело кредита",Cash[Дата],">="&EOMONTH(A45,-1)+1,Cash[Дата],"<"&EDATE(EOMONTH(A45,-1)+1,1),Cash[Документ],$B$7) -> 0 | I45: =SUMIFS(Cash[Сумма],Cash[Дата],"<="&ДатаОтчета,Cash[Статус],"Проведён",Cash[Тип],"Проценты",Cash[Дата],">="&EOMONTH(A45,-1)+1,Cash[Дата],"<"&EDATE(EOMONTH(A45,-1)+1,1)) -> 0 | J45: =IF(A45>ДатаОтчета,"",H45-E45-F45)
A46: =DATE(YEAR(EDATE($B$11,26)),MONTH(EDATE($B$11,26)),28) -> 46840 | B46: =G45 -> 0 | C46: =ROUND(B46*$B$10/12,2) -> 0 | D46: =IF(B46=0,0,ROUND(MIN($B$13,B46+C46),2)) -> 0 | E46: =MAX(0,D46-C46) -> 0 | F46: 0 | G46: =MAX(0,B46-E46-F46) -> 0 | H46: =SUMIFS(Cash[Сумма],Cash[Дата],"<="&ДатаОтчета,Cash[Статус],"Проведён",Cash[Тип],"Тело кредита",Cash[Дата],">="&EOMONTH(A46,-1)+1,Cash[Дата],"<"&EDATE(EOMONTH(A46,-1)+1,1),Cash[Документ],$B$7) -> 0 | I46: =SUMIFS(Cash[Сумма],Cash[Дата],"<="&ДатаОтчета,Cash[Статус],"Проведён",Cash[Тип],"Проценты",Cash[Дата],">="&EOMONTH(A46,-1)+1,Cash[Дата],"<"&EDATE(EOMONTH(A46,-1)+1,1)) -> 0 | J46: =IF(A46>ДатаОтчета,"",H46-E46-F46)
A47: =DATE(YEAR(EDATE($B$11,27)),MONTH(EDATE($B$11,27)),28) -> 46871 | B47: =G46 -> 0 | C47: =ROUND(B47*$B$10/12,2) -> 0 | D47: =IF(B47=0,0,ROUND(MIN($B$13,B47+C47),2)) -> 0 | E47: =MAX(0,D47-C47) -> 0 | F47: 0 | G47: =MAX(0,B47-E47-F47) -> 0 | H47: =SUMIFS(Cash[Сумма],Cash[Дата],"<="&ДатаОтчета,Cash[Статус],"Проведён",Cash[Тип],"Тело кредита",Cash[Дата],">="&EOMONTH(A47,-1)+1,Cash[Дата],"<"&EDATE(EOMONTH(A47,-1)+1,1),Cash[Документ],$B$7) -> 0 | I47: =SUMIFS(Cash[Сумма],Cash[Дата],"<="&ДатаОтчета,Cash[Статус],"Проведён",Cash[Тип],"Проценты",Cash[Дата],">="&EOMONTH(A47,-1)+1,Cash[Дата],"<"&EDATE(EOMONTH(A47,-1)+1,1)) -> 0 | J47: =IF(A47>ДатаОтчета,"",H47-E47-F47)
A48: =DATE(YEAR(EDATE($B$11,28)),MONTH(EDATE($B$11,28)),28) -> 46901 | B48: =G47 -> 0 | C48: =ROUND(B48*$B$10/12,2) -> 0 | D48: =IF(B48=0,0,ROUND(MIN($B$13,B48+C48),2)) -> 0 | E48: =MAX(0,D48-C48) -> 0 | F48: 0 | G48: =MAX(0,B48-E48-F48) -> 0 | H48: =SUMIFS(Cash[Сумма],Cash[Дата],"<="&ДатаОтчета,Cash[Статус],"Проведён",Cash[Тип],"Тело кредита",Cash[Дата],">="&EOMONTH(A48,-1)+1,Cash[Дата],"<"&EDATE(EOMONTH(A48,-1)+1,1),Cash[Документ],$B$7) -> 0 | I48: =SUMIFS(Cash[Сумма],Cash[Дата],"<="&ДатаОтчета,Cash[Статус],"Проведён",Cash[Тип],"Проценты",Cash[Дата],">="&EOMONTH(A48,-1)+1,Cash[Дата],"<"&EDATE(EOMONTH(A48,-1)+1,1)) -> 0 | J48: =IF(A48>ДатаОтчета,"",H48-E48-F48)
A49: =DATE(YEAR(EDATE($B$11,29)),MONTH(EDATE($B$11,29)),28) -> 46932 | B49: =G48 -> 0 | C49: =ROUND(B49*$B$10/12,2) -> 0 | D49: =IF(B49=0,0,ROUND(MIN($B$13,B49+C49),2)) -> 0 | E49: =MAX(0,D49-C49) -> 0 | F49: 0 | G49: =MAX(0,B49-E49-F49) -> 0 | H49: =SUMIFS(Cash[Сумма],Cash[Дата],"<="&ДатаОтчета,Cash[Статус],"Проведён",Cash[Тип],"Тело кредита",Cash[Дата],">="&EOMONTH(A49,-1)+1,Cash[Дата],"<"&EDATE(EOMONTH(A49,-1)+1,1),Cash[Документ],$B$7) -> 0 | I49: =SUMIFS(Cash[Сумма],Cash[Дата],"<="&ДатаОтчета,Cash[Статус],"Проведён",Cash[Тип],"Проценты",Cash[Дата],">="&EOMONTH(A49,-1)+1,Cash[Дата],"<"&EDATE(EOMONTH(A49,-1)+1,1)) -> 0 | J49: =IF(A49>ДатаОтчета,"",H49-E49-F49)
A50: =DATE(YEAR(EDATE($B$11,30)),MONTH(EDATE($B$11,30)),28) -> 46962 | B50: =G49 -> 0 | C50: =ROUND(B50*$B$10/12,2) -> 0 | D50: =IF(B50=0,0,ROUND(MIN($B$13,B50+C50),2)) -> 0 | E50: =MAX(0,D50-C50) -> 0 | F50: 0 | G50: =MAX(0,B50-E50-F50) -> 0 | H50: =SUMIFS(Cash[Сумма],Cash[Дата],"<="&ДатаОтчета,Cash[Статус],"Проведён",Cash[Тип],"Тело кредита",Cash[Дата],">="&EOMONTH(A50,-1)+1,Cash[Дата],"<"&EDATE(EOMONTH(A50,-1)+1,1),Cash[Документ],$B$7) -> 0 | I50: =SUMIFS(Cash[Сумма],Cash[Дата],"<="&ДатаОтчета,Cash[Статус],"Проведён",Cash[Тип],"Проценты",Cash[Дата],">="&EOMONTH(A50,-1)+1,Cash[Дата],"<"&EDATE(EOMONTH(A50,-1)+1,1)) -> 0 | J50: =IF(A50>ДатаОтчета,"",H50-E50-F50)
A51: =DATE(YEAR(EDATE($B$11,31)),MONTH(EDATE($B$11,31)),28) -> 46993 | B51: =G50 -> 0 | C51: =ROUND(B51*$B$10/12,2) -> 0 | D51: =IF(B51=0,0,ROUND(MIN($B$13,B51+C51),2)) -> 0 | E51: =MAX(0,D51-C51) -> 0 | F51: 0 | G51: =MAX(0,B51-E51-F51) -> 0 | H51: =SUMIFS(Cash[Сумма],Cash[Дата],"<="&ДатаОтчета,Cash[Статус],"Проведён",Cash[Тип],"Тело кредита",Cash[Дата],">="&EOMONTH(A51,-1)+1,Cash[Дата],"<"&EDATE(EOMONTH(A51,-1)+1,1),Cash[Документ],$B$7) -> 0 | I51: =SUMIFS(Cash[Сумма],Cash[Дата],"<="&ДатаОтчета,Cash[Статус],"Проведён",Cash[Тип],"Проценты",Cash[Дата],">="&EOMONTH(A51,-1)+1,Cash[Дата],"<"&EDATE(EOMONTH(A51,-1)+1,1)) -> 0 | J51: =IF(A51>ДатаОтчета,"",H51-E51-F51)
A52: =DATE(YEAR(EDATE($B$11,32)),MONTH(EDATE($B$11,32)),28) -> 47024 | B52: =G51 -> 0 | C52: =ROUND(B52*$B$10/12,2) -> 0 | D52: =IF(B52=0,0,ROUND(MIN($B$13,B52+C52),2)) -> 0 | E52: =MAX(0,D52-C52) -> 0 | F52: 0 | G52: =MAX(0,B52-E52-F52) -> 0 | H52: =SUMIFS(Cash[Сумма],Cash[Дата],"<="&ДатаОтчета,Cash[Статус],"Проведён",Cash[Тип],"Тело кредита",Cash[Дата],">="&EOMONTH(A52,-1)+1,Cash[Дата],"<"&EDATE(EOMONTH(A52,-1)+1,1),Cash[Документ],$B$7) -> 0 | I52: =SUMIFS(Cash[Сумма],Cash[Дата],"<="&ДатаОтчета,Cash[Статус],"Проведён",Cash[Тип],"Проценты",Cash[Дата],">="&EOMONTH(A52,-1)+1,Cash[Дата],"<"&EDATE(EOMONTH(A52,-1)+1,1)) -> 0 | J52: =IF(A52>ДатаОтчета,"",H52-E52-F52)
A53: =DATE(YEAR(EDATE($B$11,33)),MONTH(EDATE($B$11,33)),28) -> 47054 | B53: =G52 -> 0 | C53: =ROUND(B53*$B$10/12,2) -> 0 | D53: =IF(B53=0,0,ROUND(MIN($B$13,B53+C53),2)) -> 0 | E53: =MAX(0,D53-C53) -> 0 | F53: 0 | G53: =MAX(0,B53-E53-F53) -> 0 | H53: =SUMIFS(Cash[Сумма],Cash[Дата],"<="&ДатаОтчета,Cash[Статус],"Проведён",Cash[Тип],"Тело кредита",Cash[Дата],">="&EOMONTH(A53,-1)+1,Cash[Дата],"<"&EDATE(EOMONTH(A53,-1)+1,1),Cash[Документ],$B$7) -> 0 | I53: =SUMIFS(Cash[Сумма],Cash[Дата],"<="&ДатаОтчета,Cash[Статус],"Проведён",Cash[Тип],"Проценты",Cash[Дата],">="&EOMONTH(A53,-1)+1,Cash[Дата],"<"&EDATE(EOMONTH(A53,-1)+1,1)) -> 0 | J53: =IF(A53>ДатаОтчета,"",H53-E53-F53)
A54: =DATE(YEAR(EDATE($B$11,34)),MONTH(EDATE($B$11,34)),28) -> 47085 | B54: =G53 -> 0 | C54: =ROUND(B54*$B$10/12,2) -> 0 | D54: =IF(B54=0,0,ROUND(MIN($B$13,B54+C54),2)) -> 0 | E54: =MAX(0,D54-C54) -> 0 | F54: 0 | G54: =MAX(0,B54-E54-F54) -> 0 | H54: =SUMIFS(Cash[Сумма],Cash[Дата],"<="&ДатаОтчета,Cash[Статус],"Проведён",Cash[Тип],"Тело кредита",Cash[Дата],">="&EOMONTH(A54,-1)+1,Cash[Дата],"<"&EDATE(EOMONTH(A54,-1)+1,1),Cash[Документ],$B$7) -> 0 | I54: =SUMIFS(Cash[Сумма],Cash[Дата],"<="&ДатаОтчета,Cash[Статус],"Проведён",Cash[Тип],"Проценты",Cash[Дата],">="&EOMONTH(A54,-1)+1,Cash[Дата],"<"&EDATE(EOMONTH(A54,-1)+1,1)) -> 0 | J54: =IF(A54>ДатаОтчета,"",H54-E54-F54)
A55: =DATE(YEAR(EDATE($B$11,35)),MONTH(EDATE($B$11,35)),28) -> 47115 | B55: =G54 -> 0 | C55: =ROUND(B55*$B$10/12,2) -> 0 | D55: =IF(B55=0,0,ROUND(MIN($B$13,B55+C55),2)) -> 0 | E55: =MAX(0,D55-C55) -> 0 | F55: 0 | G55: =MAX(0,B55-E55-F55) -> 0 | H55: =SUMIFS(Cash[Сумма],Cash[Дата],"<="&ДатаОтчета,Cash[Статус],"Проведён",Cash[Тип],"Тело кредита",Cash[Дата],">="&EOMONTH(A55,-1)+1,Cash[Дата],"<"&EDATE(EOMONTH(A55,-1)+1,1),Cash[Документ],$B$7) -> 0 | I55: =SUMIFS(Cash[Сумма],Cash[Дата],"<="&ДатаОтчета,Cash[Статус],"Проведён",Cash[Тип],"Проценты",Cash[Дата],">="&EOMONTH(A55,-1)+1,Cash[Дата],"<"&EDATE(EOMONTH(A55,-1)+1,1)) -> 0 | J55: =IF(A55>ДатаОтчета,"",H55-E55-F55)
A56: =DATE(YEAR(EDATE($B$11,36)),MONTH(EDATE($B$11,36)),28) -> 47146 | B56: =G55 -> 0 | C56: =ROUND(B56*$B$10/12,2) -> 0 | D56: =IF(B56=0,0,ROUND(MIN($B$13,B56+C56),2)) -> 0 | E56: =MAX(0,D56-C56) -> 0 | F56: 0 | G56: =MAX(0,B56-E56-F56) -> 0 | H56: =SUMIFS(Cash[Сумма],Cash[Дата],"<="&ДатаОтчета,Cash[Статус],"Проведён",Cash[Тип],"Тело кредита",Cash[Дата],">="&EOMONTH(A56,-1)+1,Cash[Дата],"<"&EDATE(EOMONTH(A56,-1)+1,1),Cash[Документ],$B$7) -> 0 | I56: =SUMIFS(Cash[Сумма],Cash[Дата],"<="&ДатаОтчета,Cash[Статус],"Проведён",Cash[Тип],"Проценты",Cash[Дата],">="&EOMONTH(A56,-1)+1,Cash[Дата],"<"&EDATE(EOMONTH(A56,-1)+1,1)) -> 0 | J56: =IF(A56>ДатаОтчета,"",H56-E56-F56)
A57: =DATE(YEAR(EDATE($B$11,37)),MONTH(EDATE($B$11,37)),28) -> 47177 | B57: =G56 -> 0 | C57: =ROUND(B57*$B$10/12,2) -> 0 | D57: =IF(B57=0,0,ROUND(MIN($B$13,B57+C57),2)) -> 0 | E57: =MAX(0,D57-C57) -> 0 | F57: 0 | G57: =MAX(0,B57-E57-F57) -> 0 | H57: =SUMIFS(Cash[Сумма],Cash[Дата],"<="&ДатаОтчета,Cash[Статус],"Проведён",Cash[Тип],"Тело кредита",Cash[Дата],">="&EOMONTH(A57,-1)+1,Cash[Дата],"<"&EDATE(EOMONTH(A57,-1)+1,1),Cash[Документ],$B$7) -> 0 | I57: =SUMIFS(Cash[Сумма],Cash[Дата],"<="&ДатаОтчета,Cash[Статус],"Проведён",Cash[Тип],"Проценты",Cash[Дата],">="&EOMONTH(A57,-1)+1,Cash[Дата],"<"&EDATE(EOMONTH(A57,-1)+1,1)) -> 0 | J57: =IF(A57>ДатаОтчета,"",H57-E57-F57)
A58: =DATE(YEAR(EDATE($B$11,38)),MONTH(EDATE($B$11,38)),28) -> 47205 | B58: =G57 -> 0 | C58: =ROUND(B58*$B$10/12,2) -> 0 | D58: =IF(B58=0,0,ROUND(MIN($B$13,B58+C58),2)) -> 0 | E58: =MAX(0,D58-C58) -> 0 | F58: 0 | G58: =MAX(0,B58-E58-F58) -> 0 | H58: =SUMIFS(Cash[Сумма],Cash[Дата],"<="&ДатаОтчета,Cash[Статус],"Проведён",Cash[Тип],"Тело кредита",Cash[Дата],">="&EOMONTH(A58,-1)+1,Cash[Дата],"<"&EDATE(EOMONTH(A58,-1)+1,1),Cash[Документ],$B$7) -> 0 | I58: =SUMIFS(Cash[Сумма],Cash[Дата],"<="&ДатаОтчета,Cash[Статус],"Проведён",Cash[Тип],"Проценты",Cash[Дата],">="&EOMONTH(A58,-1)+1,Cash[Дата],"<"&EDATE(EOMONTH(A58,-1)+1,1)) -> 0 | J58: =IF(A58>ДатаОтчета,"",H58-E58-F58)
A59: =DATE(YEAR(EDATE($B$11,39)),MONTH(EDATE($B$11,39)),28) -> 47236 | B59: =G58 -> 0 | C59: =ROUND(B59*$B$10/12,2) -> 0 | D59: =IF(B59=0,0,ROUND(MIN($B$13,B59+C59),2)) -> 0 | E59: =MAX(0,D59-C59) -> 0 | F59: 0 | G59: =MAX(0,B59-E59-F59) -> 0 | H59: =SUMIFS(Cash[Сумма],Cash[Дата],"<="&ДатаОтчета,Cash[Статус],"Проведён",Cash[Тип],"Тело кредита",Cash[Дата],">="&EOMONTH(A59,-1)+1,Cash[Дата],"<"&EDATE(EOMONTH(A59,-1)+1,1),Cash[Документ],$B$7) -> 0 | I59: =SUMIFS(Cash[Сумма],Cash[Дата],"<="&ДатаОтчета,Cash[Статус],"Проведён",Cash[Тип],"Проценты",Cash[Дата],">="&EOMONTH(A59,-1)+1,Cash[Дата],"<"&EDATE(EOMONTH(A59,-1)+1,1)) -> 0 | J59: =IF(A59>ДатаОтчета,"",H59-E59-F59)
A60: =DATE(YEAR(EDATE($B$11,40)),MONTH(EDATE($B$11,40)),28) -> 47266 | B60: =G59 -> 0 | C60: =ROUND(B60*$B$10/12,2) -> 0 | D60: =IF(B60=0,0,ROUND(MIN($B$13,B60+C60),2)) -> 0 | E60: =MAX(0,D60-C60) -> 0 | F60: 0 | G60: =MAX(0,B60-E60-F60) -> 0 | H60: =SUMIFS(Cash[Сумма],Cash[Дата],"<="&ДатаОтчета,Cash[Статус],"Проведён",Cash[Тип],"Тело кредита",Cash[Дата],">="&EOMONTH(A60,-1)+1,Cash[Дата],"<"&EDATE(EOMONTH(A60,-1)+1,1),Cash[Документ],$B$7) -> 0 | I60: =SUMIFS(Cash[Сумма],Cash[Дата],"<="&ДатаОтчета,Cash[Статус],"Проведён",Cash[Тип],"Проценты",Cash[Дата],">="&EOMONTH(A60,-1)+1,Cash[Дата],"<"&EDATE(EOMONTH(A60,-1)+1,1)) -> 0 | J60: =IF(A60>ДатаОтчета,"",H60-E60-F60)
A61: =DATE(YEAR(EDATE($B$11,41)),MONTH(EDATE($B$11,41)),28) -> 47297 | B61: =G60 -> 0 | C61: =ROUND(B61*$B$10/12,2) -> 0 | D61: =IF(B61=0,0,ROUND(MIN($B$13,B61+C61),2)) -> 0 | E61: =MAX(0,D61-C61) -> 0 | F61: 0 | G61: =MAX(0,B61-E61-F61) -> 0 | H61: =SUMIFS(Cash[Сумма],Cash[Дата],"<="&ДатаОтчета,Cash[Статус],"Проведён",Cash[Тип],"Тело кредита",Cash[Дата],">="&EOMONTH(A61,-1)+1,Cash[Дата],"<"&EDATE(EOMONTH(A61,-1)+1,1),Cash[Документ],$B$7) -> 0 | I61: =SUMIFS(Cash[Сумма],Cash[Дата],"<="&ДатаОтчета,Cash[Статус],"Проведён",Cash[Тип],"Проценты",Cash[Дата],">="&EOMONTH(A61,-1)+1,Cash[Дата],"<"&EDATE(EOMONTH(A61,-1)+1,1)) -> 0 | J61: =IF(A61>ДатаОтчета,"",H61-E61-F61)
A62: =DATE(YEAR(EDATE($B$11,42)),MONTH(EDATE($B$11,42)),28) -> 47327 | B62: =G61 -> 0 | C62: =ROUND(B62*$B$10/12,2) -> 0 | D62: =IF(B62=0,0,ROUND(MIN($B$13,B62+C62),2)) -> 0 | E62: =MAX(0,D62-C62) -> 0 | F62: 0 | G62: =MAX(0,B62-E62-F62) -> 0 | H62: =SUMIFS(Cash[Сумма],Cash[Дата],"<="&ДатаОтчета,Cash[Статус],"Проведён",Cash[Тип],"Тело кредита",Cash[Дата],">="&EOMONTH(A62,-1)+1,Cash[Дата],"<"&EDATE(EOMONTH(A62,-1)+1,1),Cash[Документ],$B$7) -> 0 | I62: =SUMIFS(Cash[Сумма],Cash[Дата],"<="&ДатаОтчета,Cash[Статус],"Проведён",Cash[Тип],"Проценты",Cash[Дата],">="&EOMONTH(A62,-1)+1,Cash[Дата],"<"&EDATE(EOMONTH(A62,-1)+1,1)) -> 0 | J62: =IF(A62>ДатаОтчета,"",H62-E62-F62)
A63: =DATE(YEAR(EDATE($B$11,43)),MONTH(EDATE($B$11,43)),28) -> 47358 | B63: =G62 -> 0 | C63: =ROUND(B63*$B$10/12,2) -> 0 | D63: =IF(B63=0,0,ROUND(MIN($B$13,B63+C63),2)) -> 0 | E63: =MAX(0,D63-C63) -> 0 | F63: 0 | G63: =MAX(0,B63-E63-F63) -> 0 | H63: =SUMIFS(Cash[Сумма],Cash[Дата],"<="&ДатаОтчета,Cash[Статус],"Проведён",Cash[Тип],"Тело кредита",Cash[Дата],">="&EOMONTH(A63,-1)+1,Cash[Дата],"<"&EDATE(EOMONTH(A63,-1)+1,1),Cash[Документ],$B$7) -> 0 | I63: =SUMIFS(Cash[Сумма],Cash[Дата],"<="&ДатаОтчета,Cash[Статус],"Проведён",Cash[Тип],"Проценты",Cash[Дата],">="&EOMONTH(A63,-1)+1,Cash[Дата],"<"&EDATE(EOMONTH(A63,-1)+1,1)) -> 0 | J63: =IF(A63>ДатаОтчета,"",H63-E63-F63)
A64: =DATE(YEAR(EDATE($B$11,44)),MONTH(EDATE($B$11,44)),28) -> 47389 | B64: =G63 -> 0 | C64: =ROUND(B64*$B$10/12,2) -> 0 | D64: =IF(B64=0,0,ROUND(MIN($B$13,B64+C64),2)) -> 0 | E64: =MAX(0,D64-C64) -> 0 | F64: 0 | G64: =MAX(0,B64-E64-F64) -> 0 | H64: =SUMIFS(Cash[Сумма],Cash[Дата],"<="&ДатаОтчета,Cash[Статус],"Проведён",Cash[Тип],"Тело кредита",Cash[Дата],">="&EOMONTH(A64,-1)+1,Cash[Дата],"<"&EDATE(EOMONTH(A64,-1)+1,1),Cash[Документ],$B$7) -> 0 | I64: =SUMIFS(Cash[Сумма],Cash[Дата],"<="&ДатаОтчета,Cash[Статус],"Проведён",Cash[Тип],"Проценты",Cash[Дата],">="&EOMONTH(A64,-1)+1,Cash[Дата],"<"&EDATE(EOMONTH(A64,-1)+1,1)) -> 0 | J64: =IF(A64>ДатаОтчета,"",H64-E64-F64)
A65: =DATE(YEAR(EDATE($B$11,45)),MONTH(EDATE($B$11,45)),28) -> 47419 | B65: =G64 -> 0 | C65: =ROUND(B65*$B$10/12,2) -> 0 | D65: =IF(B65=0,0,ROUND(MIN($B$13,B65+C65),2)) -> 0 | E65: =MAX(0,D65-C65) -> 0 | F65: 0 | G65: =MAX(0,B65-E65-F65) -> 0 | H65: =SUMIFS(Cash[Сумма],Cash[Дата],"<="&ДатаОтчета,Cash[Статус],"Проведён",Cash[Тип],"Тело кредита",Cash[Дата],">="&EOMONTH(A65,-1)+1,Cash[Дата],"<"&EDATE(EOMONTH(A65,-1)+1,1),Cash[Документ],$B$7) -> 0 | I65: =SUMIFS(Cash[Сумма],Cash[Дата],"<="&ДатаОтчета,Cash[Статус],"Проведён",Cash[Тип],"Проценты",Cash[Дата],">="&EOMONTH(A65,-1)+1,Cash[Дата],"<"&EDATE(EOMONTH(A65,-1)+1,1)) -> 0 | J65: =IF(A65>ДатаОтчета,"",H65-E65-F65)
A66: =DATE(YEAR(EDATE($B$11,46)),MONTH(EDATE($B$11,46)),28) -> 47450 | B66: =G65 -> 0 | C66: =ROUND(B66*$B$10/12,2) -> 0 | D66: =IF(B66=0,0,ROUND(MIN($B$13,B66+C66),2)) -> 0 | E66: =MAX(0,D66-C66) -> 0 | F66: 0 | G66: =MAX(0,B66-E66-F66) -> 0 | H66: =SUMIFS(Cash[Сумма],Cash[Дата],"<="&ДатаОтчета,Cash[Статус],"Проведён",Cash[Тип],"Тело кредита",Cash[Дата],">="&EOMONTH(A66,-1)+1,Cash[Дата],"<"&EDATE(EOMONTH(A66,-1)+1,1),Cash[Документ],$B$7) -> 0 | I66: =SUMIFS(Cash[Сумма],Cash[Дата],"<="&ДатаОтчета,Cash[Статус],"Проведён",Cash[Тип],"Проценты",Cash[Дата],">="&EOMONTH(A66,-1)+1,Cash[Дата],"<"&EDATE(EOMONTH(A66,-1)+1,1)) -> 0 | J66: =IF(A66>ДатаОтчета,"",H66-E66-F66)
A67: =DATE(YEAR(EDATE($B$11,47)),MONTH(EDATE($B$11,47)),28) -> 47480 | B67: =G66 -> 0 | C67: =ROUND(B67*$B$10/12,2) -> 0 | D67: =IF(B67=0,0,ROUND(MIN($B$13,B67+C67),2)) -> 0 | E67: =MAX(0,D67-C67) -> 0 | F67: 0 | G67: =MAX(0,B67-E67-F67) -> 0 | H67: =SUMIFS(Cash[Сумма],Cash[Дата],"<="&ДатаОтчета,Cash[Статус],"Проведён",Cash[Тип],"Тело кредита",Cash[Дата],">="&EOMONTH(A67,-1)+1,Cash[Дата],"<"&EDATE(EOMONTH(A67,-1)+1,1),Cash[Документ],$B$7) -> 0 | I67: =SUMIFS(Cash[Сумма],Cash[Дата],"<="&ДатаОтчета,Cash[Статус],"Проведён",Cash[Тип],"Проценты",Cash[Дата],">="&EOMONTH(A67,-1)+1,Cash[Дата],"<"&EDATE(EOMONTH(A67,-1)+1,1)) -> 0 | J67: =IF(A67>ДатаОтчета,"",H67-E67-F67)
A68: =DATE(YEAR(EDATE($B$11,48)),MONTH(EDATE($B$11,48)),28) -> 47511 | B68: =G67 -> 0 | C68: =ROUND(B68*$B$10/12,2) -> 0 | D68: =IF(B68=0,0,ROUND(MIN($B$13,B68+C68),2)) -> 0 | E68: =MAX(0,D68-C68) -> 0 | F68: 0 | G68: =MAX(0,B68-E68-F68) -> 0 | H68: =SUMIFS(Cash[Сумма],Cash[Дата],"<="&ДатаОтчета,Cash[Статус],"Проведён",Cash[Тип],"Тело кредита",Cash[Дата],">="&EOMONTH(A68,-1)+1,Cash[Дата],"<"&EDATE(EOMONTH(A68,-1)+1,1),Cash[Документ],$B$7) -> 0 | I68: =SUMIFS(Cash[Сумма],Cash[Дата],"<="&ДатаОтчета,Cash[Статус],"Проведён",Cash[Тип],"Проценты",Cash[Дата],">="&EOMONTH(A68,-1)+1,Cash[Дата],"<"&EDATE(EOMONTH(A68,-1)+1,1)) -> 0 | J68: =IF(A68>ДатаОтчета,"",H68-E68-F68)
A69: =DATE(YEAR(EDATE($B$11,49)),MONTH(EDATE($B$11,49)),28) -> 47542 | B69: =G68 -> 0 | C69: =ROUND(B69*$B$10/12,2) -> 0 | D69: =IF(B69=0,0,ROUND(MIN($B$13,B69+C69),2)) -> 0 | E69: =MAX(0,D69-C69) -> 0 | F69: 0 | G69: =MAX(0,B69-E69-F69) -> 0 | H69: =SUMIFS(Cash[Сумма],Cash[Дата],"<="&ДатаОтчета,Cash[Статус],"Проведён",Cash[Тип],"Тело кредита",Cash[Дата],">="&EOMONTH(A69,-1)+1,Cash[Дата],"<"&EDATE(EOMONTH(A69,-1)+1,1),Cash[Документ],$B$7) -> 0 | I69: =SUMIFS(Cash[Сумма],Cash[Дата],"<="&ДатаОтчета,Cash[Статус],"Проведён",Cash[Тип],"Проценты",Cash[Дата],">="&EOMONTH(A69,-1)+1,Cash[Дата],"<"&EDATE(EOMONTH(A69,-1)+1,1)) -> 0 | J69: =IF(A69>ДатаОтчета,"",H69-E69-F69)
A70: =DATE(YEAR(EDATE($B$11,50)),MONTH(EDATE($B$11,50)),28) -> 47570 | B70: =G69 -> 0 | C70: =ROUND(B70*$B$10/12,2) -> 0 | D70: =IF(B70=0,0,ROUND(MIN($B$13,B70+C70),2)) -> 0 | E70: =MAX(0,D70-C70) -> 0 | F70: 0 | G70: =MAX(0,B70-E70-F70) -> 0 | H70: =SUMIFS(Cash[Сумма],Cash[Дата],"<="&ДатаОтчета,Cash[Статус],"Проведён",Cash[Тип],"Тело кредита",Cash[Дата],">="&EOMONTH(A70,-1)+1,Cash[Дата],"<"&EDATE(EOMONTH(A70,-1)+1,1),Cash[Документ],$B$7) -> 0 | I70: =SUMIFS(Cash[Сумма],Cash[Дата],"<="&ДатаОтчета,Cash[Статус],"Проведён",Cash[Тип],"Проценты",Cash[Дата],">="&EOMONTH(A70,-1)+1,Cash[Дата],"<"&EDATE(EOMONTH(A70,-1)+1,1)) -> 0 | J70: =IF(A70>ДатаОтчета,"",H70-E70-F70)
A71: =DATE(YEAR(EDATE($B$11,51)),MONTH(EDATE($B$11,51)),28) -> 47601 | B71: =G70 -> 0 | C71: =ROUND(B71*$B$10/12,2) -> 0 | D71: =IF(B71=0,0,ROUND(MIN($B$13,B71+C71),2)) -> 0 | E71: =MAX(0,D71-C71) -> 0 | F71: 0 | G71: =MAX(0,B71-E71-F71) -> 0 | H71: =SUMIFS(Cash[Сумма],Cash[Дата],"<="&ДатаОтчета,Cash[Статус],"Проведён",Cash[Тип],"Тело кредита",Cash[Дата],">="&EOMONTH(A71,-1)+1,Cash[Дата],"<"&EDATE(EOMONTH(A71,-1)+1,1),Cash[Документ],$B$7) -> 0 | I71: =SUMIFS(Cash[Сумма],Cash[Дата],"<="&ДатаОтчета,Cash[Статус],"Проведён",Cash[Тип],"Проценты",Cash[Дата],">="&EOMONTH(A71,-1)+1,Cash[Дата],"<"&EDATE(EOMONTH(A71,-1)+1,1)) -> 0 | J71: =IF(A71>ДатаОтчета,"",H71-E71-F71)
A72: =DATE(YEAR(EDATE($B$11,52)),MONTH(EDATE($B$11,52)),28) -> 47631 | B72: =G71 -> 0 | C72: =ROUND(B72*$B$10/12,2) -> 0 | D72: =IF(B72=0,0,ROUND(MIN($B$13,B72+C72),2)) -> 0 | E72: =MAX(0,D72-C72) -> 0 | F72: 0 | G72: =MAX(0,B72-E72-F72) -> 0 | H72: =SUMIFS(Cash[Сумма],Cash[Дата],"<="&ДатаОтчета,Cash[Статус],"Проведён",Cash[Тип],"Тело кредита",Cash[Дата],">="&EOMONTH(A72,-1)+1,Cash[Дата],"<"&EDATE(EOMONTH(A72,-1)+1,1),Cash[Документ],$B$7) -> 0 | I72: =SUMIFS(Cash[Сумма],Cash[Дата],"<="&ДатаОтчета,Cash[Статус],"Проведён",Cash[Тип],"Проценты",Cash[Дата],">="&EOMONTH(A72,-1)+1,Cash[Дата],"<"&EDATE(EOMONTH(A72,-1)+1,1)) -> 0 | J72: =IF(A72>ДатаОтчета,"",H72-E72-F72)
A73: =DATE(YEAR(EDATE($B$11,53)),MONTH(EDATE($B$11,53)),28) -> 47662 | B73: =G72 -> 0 | C73: =ROUND(B73*$B$10/12,2) -> 0 | D73: =IF(B73=0,0,ROUND(MIN($B$13,B73+C73),2)) -> 0 | E73: =MAX(0,D73-C73) -> 0 | F73: 0 | G73: =MAX(0,B73-E73-F73) -> 0 | H73: =SUMIFS(Cash[Сумма],Cash[Дата],"<="&ДатаОтчета,Cash[Статус],"Проведён",Cash[Тип],"Тело кредита",Cash[Дата],">="&EOMONTH(A73,-1)+1,Cash[Дата],"<"&EDATE(EOMONTH(A73,-1)+1,1),Cash[Документ],$B$7) -> 0 | I73: =SUMIFS(Cash[Сумма],Cash[Дата],"<="&ДатаОтчета,Cash[Статус],"Проведён",Cash[Тип],"Проценты",Cash[Дата],">="&EOMONTH(A73,-1)+1,Cash[Дата],"<"&EDATE(EOMONTH(A73,-1)+1,1)) -> 0 | J73: =IF(A73>ДатаОтчета,"",H73-E73-F73)
A74: =DATE(YEAR(EDATE($B$11,54)),MONTH(EDATE($B$11,54)),28) -> 47692 | B74: =G73 -> 0 | C74: =ROUND(B74*$B$10/12,2) -> 0 | D74: =IF(B74=0,0,ROUND(MIN($B$13,B74+C74),2)) -> 0 | E74: =MAX(0,D74-C74) -> 0 | F74: 0 | G74: =MAX(0,B74-E74-F74) -> 0 | H74: =SUMIFS(Cash[Сумма],Cash[Дата],"<="&ДатаОтчета,Cash[Статус],"Проведён",Cash[Тип],"Тело кредита",Cash[Дата],">="&EOMONTH(A74,-1)+1,Cash[Дата],"<"&EDATE(EOMONTH(A74,-1)+1,1),Cash[Документ],$B$7) -> 0 | I74: =SUMIFS(Cash[Сумма],Cash[Дата],"<="&ДатаОтчета,Cash[Статус],"Проведён",Cash[Тип],"Проценты",Cash[Дата],">="&EOMONTH(A74,-1)+1,Cash[Дата],"<"&EDATE(EOMONTH(A74,-1)+1,1)) -> 0 | J74: =IF(A74>ДатаОтчета,"",H74-E74-F74)
A75: =DATE(YEAR(EDATE($B$11,55)),MONTH(EDATE($B$11,55)),28) -> 47723 | B75: =G74 -> 0 | C75: =ROUND(B75*$B$10/12,2) -> 0 | D75: =IF(B75=0,0,ROUND(MIN($B$13,B75+C75),2)) -> 0 | E75: =MAX(0,D75-C75) -> 0 | F75: 0 | G75: =MAX(0,B75-E75-F75) -> 0 | H75: =SUMIFS(Cash[Сумма],Cash[Дата],"<="&ДатаОтчета,Cash[Статус],"Проведён",Cash[Тип],"Тело кредита",Cash[Дата],">="&EOMONTH(A75,-1)+1,Cash[Дата],"<"&EDATE(EOMONTH(A75,-1)+1,1),Cash[Документ],$B$7) -> 0 | I75: =SUMIFS(Cash[Сумма],Cash[Дата],"<="&ДатаОтчета,Cash[Статус],"Проведён",Cash[Тип],"Проценты",Cash[Дата],">="&EOMONTH(A75,-1)+1,Cash[Дата],"<"&EDATE(EOMONTH(A75,-1)+1,1)) -> 0 | J75: =IF(A75>ДатаОтчета,"",H75-E75-F75)
A76: =DATE(YEAR(EDATE($B$11,56)),MONTH(EDATE($B$11,56)),28) -> 47754 | B76: =G75 -> 0 | C76: =ROUND(B76*$B$10/12,2) -> 0 | D76: =IF(B76=0,0,ROUND(MIN($B$13,B76+C76),2)) -> 0 | E76: =MAX(0,D76-C76) -> 0 | F76: 0 | G76: =MAX(0,B76-E76-F76) -> 0 | H76: =SUMIFS(Cash[Сумма],Cash[Дата],"<="&ДатаОтчета,Cash[Статус],"Проведён",Cash[Тип],"Тело кредита",Cash[Дата],">="&EOMONTH(A76,-1)+1,Cash[Дата],"<"&EDATE(EOMONTH(A76,-1)+1,1),Cash[Документ],$B$7) -> 0 | I76: =SUMIFS(Cash[Сумма],Cash[Дата],"<="&ДатаОтчета,Cash[Статус],"Проведён",Cash[Тип],"Проценты",Cash[Дата],">="&EOMONTH(A76,-1)+1,Cash[Дата],"<"&EDATE(EOMONTH(A76,-1)+1,1)) -> 0 | J76: =IF(A76>ДатаОтчета,"",H76-E76-F76)
A77: =DATE(YEAR(EDATE($B$11,57)),MONTH(EDATE($B$11,57)),28) -> 47784 | B77: =G76 -> 0 | C77: =ROUND(B77*$B$10/12,2) -> 0 | D77: =IF(B77=0,0,ROUND(MIN($B$13,B77+C77),2)) -> 0 | E77: =MAX(0,D77-C77) -> 0 | F77: 0 | G77: =MAX(0,B77-E77-F77) -> 0 | H77: =SUMIFS(Cash[Сумма],Cash[Дата],"<="&ДатаОтчета,Cash[Статус],"Проведён",Cash[Тип],"Тело кредита",Cash[Дата],">="&EOMONTH(A77,-1)+1,Cash[Дата],"<"&EDATE(EOMONTH(A77,-1)+1,1),Cash[Документ],$B$7) -> 0 | I77: =SUMIFS(Cash[Сумма],Cash[Дата],"<="&ДатаОтчета,Cash[Статус],"Проведён",Cash[Тип],"Проценты",Cash[Дата],">="&EOMONTH(A77,-1)+1,Cash[Дата],"<"&EDATE(EOMONTH(A77,-1)+1,1)) -> 0 | J77: =IF(A77>ДатаОтчета,"",H77-E77-F77)
A78: =DATE(YEAR(EDATE($B$11,58)),MONTH(EDATE($B$11,58)),28) -> 47815 | B78: =G77 -> 0 | C78: =ROUND(B78*$B$10/12,2) -> 0 | D78: =IF(B78=0,0,ROUND(MIN($B$13,B78+C78),2)) -> 0 | E78: =MAX(0,D78-C78) -> 0 | F78: 0 | G78: =MAX(0,B78-E78-F78) -> 0 | H78: =SUMIFS(Cash[Сумма],Cash[Дата],"<="&ДатаОтчета,Cash[Статус],"Проведён",Cash[Тип],"Тело кредита",Cash[Дата],">="&EOMONTH(A78,-1)+1,Cash[Дата],"<"&EDATE(EOMONTH(A78,-1)+1,1),Cash[Документ],$B$7) -> 0 | I78: =SUMIFS(Cash[Сумма],Cash[Дата],"<="&ДатаОтчета,Cash[Статус],"Проведён",Cash[Тип],"Проценты",Cash[Дата],">="&EOMONTH(A78,-1)+1,Cash[Дата],"<"&EDATE(EOMONTH(A78,-1)+1,1)) -> 0 | J78: =IF(A78>ДатаОтчета,"",H78-E78-F78)
A79: =DATE(YEAR(EDATE($B$11,59)),MONTH(EDATE($B$11,59)),28) -> 47845 | B79: =G78 -> 0 | C79: =ROUND(B79*$B$10/12,2) -> 0 | D79: =IF(B79=0,0,ROUND(MIN($B$13,B79+C79),2)) -> 0 | E79: =MAX(0,D79-C79) -> 0 | F79: 0 | G79: =MAX(0,B79-E79-F79) -> 0 | H79: =SUMIFS(Cash[Сумма],Cash[Дата],"<="&ДатаОтчета,Cash[Статус],"Проведён",Cash[Тип],"Тело кредита",Cash[Дата],">="&EOMONTH(A79,-1)+1,Cash[Дата],"<"&EDATE(EOMONTH(A79,-1)+1,1),Cash[Документ],$B$7) -> 0 | I79: =SUMIFS(Cash[Сумма],Cash[Дата],"<="&ДатаОтчета,Cash[Статус],"Проведён",Cash[Тип],"Проценты",Cash[Дата],">="&EOMONTH(A79,-1)+1,Cash[Дата],"<"&EDATE(EOMONTH(A79,-1)+1,1)) -> 0 | J79: =IF(A79>ДатаОтчета,"",H79-E79-F79)

Sheet АКТИВЫ
A1: Главная панель | D1: Настройки | F1: Контроль
A2: АКТИВЫ
A3: LEO STUDIO • Управленческий учёт • RUB
A6: ID | B6: Актив | C6: Дата ввода | D6: Стоимость | E6: Срок месяцев | F6: Аморт. начальная | G6: Накопленная | H6: Остаточная | I6: Оплачено | J6: Расхождение | K6: =DATE(Год,1,1) -> 46023 | L6: =DATE(Год,2,1) -> 46054 | M6: =DATE(Год,3,1) -> 46082 | N6: =DATE(Год,4,1) -> 46113 | O6: =DATE(Год,5,1) -> 46143 | P6: =DATE(Год,6,1) -> 46174 | Q6: =DATE(Год,7,1) -> 46204 | R6: =DATE(Год,8,1) -> 46235 | S6: =DATE(Год,9,1) -> 46266 | T6: =DATE(Год,10,1) -> 46296 | U6: =DATE(Год,11,1) -> 46327 | V6: =DATE(Год,12,1) -> 46357 | W6: Проверка
A7: ОС-1 | B7: Рабочие станции | C7: 46032 | D7: 180000 | E7: 36 | F7: 0 | G7: =IF(A7="","",IF(C7>ДатаОтчета,0,IF(E7<=0,0,MIN(D7,F7+ROUND(D7/E7*MAX(0,(YEAR(ДатаОтчета)-YEAR(MAX(C7,EDATE(НачалоУчета,-1))))*12+MONTH(ДатаОтчета)-MONTH(MAX(C7,EDATE(НачалоУчета,-1)))),2))))) -> 55000 | H7: =IF(A7="","",IF(C7>ДатаОтчета,0,D7-G7)) -> 125000 | I7: =IF(A7="","",SUMIFS(Cash[Сумма],Cash[Дата],"<="&ДатаОтчета,Cash[Статус],"Проведён",Cash[Тип],"Покупка ОС",Cash[Документ],A7)) -> 180000 | J7: =IF(A7="","",IF(OR(C7>ДатаОтчета,C7<НачалоУчета),0,D7-I7)) -> 0 | K7: =IF(A7="",0,IF(OR(E7<=0,K$6>ДатаОтчета,C7>=K$6),0,MAX(0,MIN(D7-F7,ROUND(D7/E7*MAX(0,(YEAR(K$6)-YEAR(MAX(C7,EDATE(НачалоУчета,-1))))*12+MONTH(K$6)-MONTH(MAX(C7,EDATE(НачалоУчета,-1)))),2))-MIN(D7-F7,ROUND(D7/E7*MAX(0,(YEAR(K$6)-YEAR(MAX(C7,EDATE(НачалоУчета,-1))))*12+MONTH(K$6)-MONTH(MAX(C7,EDATE(НачалоУчета,-1)))-1),2))))) -> 0 | L7: =IF(A7="",0,IF(OR(E7<=0,L$6>ДатаОтчета,C7>=L$6),0,MAX(0,MIN(D7-F7,ROUND(D7/E7*MAX(0,(YEAR(L$6)-YEAR(MAX(C7,EDATE(НачалоУчета,-1))))*12+MONTH(L$6)-MONTH(MAX(C7,EDATE(НачалоУчета,-1)))),2))-MIN(D7-F7,ROUND(D7/E7*MAX(0,(YEAR(L$6)-YEAR(MAX(C7,EDATE(НачалоУчета,-1))))*12+MONTH(L$6)-MONTH(MAX(C7,EDATE(НачалоУчета,-1)))-1),2))))) -> 5000 | M7: =IF(A7="",0,IF(OR(E7<=0,M$6>ДатаОтчета,C7>=M$6),0,MAX(0,MIN(D7-F7,ROUND(D7/E7*MAX(0,(YEAR(M$6)-YEAR(MAX(C7,EDATE(НачалоУчета,-1))))*12+MONTH(M$6)-MONTH(MAX(C7,EDATE(НачалоУчета,-1)))),2))-MIN(D7-F7,ROUND(D7/E7*MAX(0,(YEAR(M$6)-YEAR(MAX(C7,EDATE(НачалоУчета,-1))))*12+MONTH(M$6)-MONTH(MAX(C7,EDATE(НачалоУчета,-1)))-1),2))))) -> 5000 | N7: =IF(A7="",0,IF(OR(E7<=0,N$6>ДатаОтчета,C7>=N$6),0,MAX(0,MIN(D7-F7,ROUND(D7/E7*MAX(0,(YEAR(N$6)-YEAR(MAX(C7,EDATE(НачалоУчета,-1))))*12+MONTH(N$6)-MONTH(MAX(C7,EDATE(НачалоУчета,-1)))),2))-MIN(D7-F7,ROUND(D7/E7*MAX(0,(YEAR(N$6)-YEAR(MAX(C7,EDATE(НачалоУчета,-1))))*12+MONTH(N$6)-MONTH(MAX(C7,EDATE(НачалоУчета,-1)))-1),2))))) -> 5000 | O7: =IF(A7="",0,IF(OR(E7<=0,O$6>ДатаОтчета,C7>=O$6),0,MAX(0,MIN(D7-F7,ROUND(D7/E7*MAX(0,(YEAR(O$6)-YEAR(MAX(C7,EDATE(НачалоУчета,-1))))*12+MONTH(O$6)-MONTH(MAX(C7,EDATE(НачалоУчета,-1)))),2))-MIN(D7-F7,ROUND(D7/E7*MAX(0,(YEAR(O$6)-YEAR(MAX(C7,EDATE(НачалоУчета,-1))))*12+MONTH(O$6)-MONTH(MAX(C7,EDATE(НачалоУчета,-1)))-1),2))))) -> 5000 | P7: =IF(A7="",0,IF(OR(E7<=0,P$6>ДатаОтчета,C7>=P$6),0,MAX(0,MIN(D7-F7,ROUND(D7/E7*MAX(0,(YEAR(P$6)-YEAR(MAX(C7,EDATE(НачалоУчета,-1))))*12+MONTH(P$6)-MONTH(MAX(C7,EDATE(НачалоУчета,-1)))),2))-MIN(D7-F7,ROUND(D7/E7*MAX(0,(YEAR(P$6)-YEAR(MAX(C7,EDATE(НачалоУчета,-1))))*12+MONTH(P$6)-MONTH(MAX(C7,EDATE(НачалоУчета,-1)))-1),2))))) -> 5000 | Q7: =IF(A7="",0,IF(OR(E7<=0,Q$6>ДатаОтчета,C7>=Q$6),0,MAX(0,MIN(D7-F7,ROUND(D7/E7*MAX(0,(YEAR(Q$6)-YEAR(MAX(C7,EDATE(НачалоУчета,-1))))*12+MONTH(Q$6)-MONTH(MAX(C7,EDATE(НачалоУчета,-1)))),2))-MIN(D7-F7,ROUND(D7/E7*MAX(0,(YEAR(Q$6)-YEAR(MAX(C7,EDATE(НачалоУчета,-1))))*12+MONTH(Q$6)-MONTH(MAX(C7,EDATE(НачалоУчета,-1)))-1),2))))) -> 5000 | R7: =IF(A7="",0,IF(OR(E7<=0,R$6>ДатаОтчета,C7>=R$6),0,MAX(0,MIN(D7-F7,ROUND(D7/E7*MAX(0,(YEAR(R$6)-YEAR(MAX(C7,EDATE(НачалоУчета,-1))))*12+MONTH(R$6)-MONTH(MAX(C7,EDATE(НачалоУчета,-1)))),2))-MIN(D7-F7,ROUND(D7/E7*MAX(0,(YEAR(R$6)-YEAR(MAX(C7,EDATE(НачалоУчета,-1))))*12+MONTH(R$6)-MONTH(MAX(C7,EDATE(НачалоУчета,-1)))-1),2))))) -> 5000 | S7: =IF(A7="",0,IF(OR(E7<=0,S$6>ДатаОтчета,C7>=S$6),0,MAX(0,MIN(D7-F7,ROUND(D7/E7*MAX(0,(YEAR(S$6)-YEAR(MAX(C7,EDATE(НачалоУчета,-1))))*12+MONTH(S$6)-MONTH(MAX(C7,EDATE(НачалоУчета,-1)))),2))-MIN(D7-F7,ROUND(D7/E7*MAX(0,(YEAR(S$6)-YEAR(MAX(C7,EDATE(НачалоУчета,-1))))*12+MONTH(S$6)-MONTH(MAX(C7,EDATE(НачалоУчета,-1)))-1),2))))) -> 5000 | T7: =IF(A7="",0,IF(OR(E7<=0,T$6>ДатаОтчета,C7>=T$6),0,MAX(0,MIN(D7-F7,ROUND(D7/E7*MAX(0,(YEAR(T$6)-YEAR(MAX(C7,EDATE(НачалоУчета,-1))))*12+MONTH(T$6)-MONTH(MAX(C7,EDATE(НачалоУчета,-1)))),2))-MIN(D7-F7,ROUND(D7/E7*MAX(0,(YEAR(T$6)-YEAR(MAX(C7,EDATE(НачалоУчета,-1))))*12+MONTH(T$6)-MONTH(MAX(C7,EDATE(НачалоУчета,-1)))-1),2))))) -> 5000 | U7: =IF(A7="",0,IF(OR(E7<=0,U$6>ДатаОтчета,C7>=U$6),0,MAX(0,MIN(D7-F7,ROUND(D7/E7*MAX(0,(YEAR(U$6)-YEAR(MAX(C7,EDATE(НачалоУчета,-1))))*12+MONTH(U$6)-MONTH(MAX(C7,EDATE(НачалоУчета,-1)))),2))-MIN(D7-F7,ROUND(D7/E7*MAX(0,(YEAR(U$6)-YEAR(MAX(C7,EDATE(НачалоУчета,-1))))*12+MONTH(U$6)-MONTH(MAX(C7,EDATE(НачалоУчета,-1)))-1),2))))) -> 5000 | V7: =IF(A7="",0,IF(OR(E7<=0,V$6>ДатаОтчета,C7>=V$6),0,MAX(0,MIN(D7-F7,ROUND(D7/E7*MAX(0,(YEAR(V$6)-YEAR(MAX(C7,EDATE(НачалоУчета,-1))))*12+MONTH(V$6)-MONTH(MAX(C7,EDATE(НачалоУчета,-1)))),2))-MIN(D7-F7,ROUND(D7/E7*MAX(0,(YEAR(V$6)-YEAR(MAX(C7,EDATE(НачалоУчета,-1))))*12+MONTH(V$6)-MONTH(MAX(C7,EDATE(НачалоУчета,-1)))-1),2))))) -> 5000 | W7: =IF(A7="",IF(COUNTA(B7:F7)>0,"ОШИБКА",""),IF(OR(COUNTIF(Assets[ID],A7)<>1,B7="",NOT(ISNUMBER(C7)),NOT(ISNUMBER(D7)),D7<0,NOT(ISNUMBER(E7)),E7<=0,F7<0,F7>D7),"ОШИБКА","ОК")) -> ОК
G8: =IF(A8="","",IF(C8>ДатаОтчета,0,IF(E8<=0,0,MIN(D8,F8+ROUND(D8/E8*MAX(0,(YEAR(ДатаОтчета)-YEAR(MAX(C8,EDATE(НачалоУчета,-1))))*12+MONTH(ДатаОтчета)-MONTH(MAX(C8,EDATE(НачалоУчета,-1)))),2))))) | H8: =IF(A8="","",IF(C8>ДатаОтчета,0,D8-G8)) | I8: =IF(A8="","",SUMIFS(Cash[Сумма],Cash[Дата],"<="&ДатаОтчета,Cash[Статус],"Проведён",Cash[Тип],"Покупка ОС",Cash[Документ],A8)) | J8: =IF(A8="","",IF(OR(C8>ДатаОтчета,C8<НачалоУчета),0,D8-I8)) | K8: =IF(A8="",0,IF(OR(E8<=0,K$6>ДатаОтчета,C8>=K$6),0,MAX(0,MIN(D8-F8,ROUND(D8/E8*MAX(0,(YEAR(K$6)-YEAR(MAX(C8,EDATE(НачалоУчета,-1))))*12+MONTH(K$6)-MONTH(MAX(C8,EDATE(НачалоУчета,-1)))),2))-MIN(D8-F8,ROUND(D8/E8*MAX(0,(YEAR(K$6)-YEAR(MAX(C8,EDATE(НачалоУчета,-1))))*12+MONTH(K$6)-MONTH(MAX(C8,EDATE(НачалоУчета,-1)))-1),2))))) -> 0 | L8: =IF(A8="",0,IF(OR(E8<=0,L$6>ДатаОтчета,C8>=L$6),0,MAX(0,MIN(D8-F8,ROUND(D8/E8*MAX(0,(YEAR(L$6)-YEAR(MAX(C8,EDATE(НачалоУчета,-1))))*12+MONTH(L$6)-MONTH(MAX(C8,EDATE(НачалоУчета,-1)))),2))-MIN(D8-F8,ROUND(D8/E8*MAX(0,(YEAR(L$6)-YEAR(MAX(C8,EDATE(НачалоУчета,-1))))*12+MONTH(L$6)-MONTH(MAX(C8,EDATE(НачалоУчета,-1)))-1),2))))) -> 0 | M8: =IF(A8="",0,IF(OR(E8<=0,M$6>ДатаОтчета,C8>=M$6),0,MAX(0,MIN(D8-F8,ROUND(D8/E8*MAX(0,(YEAR(M$6)-YEAR(MAX(C8,EDATE(НачалоУчета,-1))))*12+MONTH(M$6)-MONTH(MAX(C8,EDATE(НачалоУчета,-1)))),2))-MIN(D8-F8,ROUND(D8/E8*MAX(0,(YEAR(M$6)-YEAR(MAX(C8,EDATE(НачалоУчета,-1))))*12+MONTH(M$6)-MONTH(MAX(C8,EDATE(НачалоУчета,-1)))-1),2))))) -> 0 | N8: =IF(A8="",0,IF(OR(E8<=0,N$6>ДатаОтчета,C8>=N$6),0,MAX(0,MIN(D8-F8,ROUND(D8/E8*MAX(0,(YEAR(N$6)-YEAR(MAX(C8,EDATE(НачалоУчета,-1))))*12+MONTH(N$6)-MONTH(MAX(C8,EDATE(НачалоУчета,-1)))),2))-MIN(D8-F8,ROUND(D8/E8*MAX(0,(YEAR(N$6)-YEAR(MAX(C8,EDATE(НачалоУчета,-1))))*12+MONTH(N$6)-MONTH(MAX(C8,EDATE(НачалоУчета,-1)))-1),2))))) -> 0 | O8: =IF(A8="",0,IF(OR(E8<=0,O$6>ДатаОтчета,C8>=O$6),0,MAX(0,MIN(D8-F8,ROUND(D8/E8*MAX(0,(YEAR(O$6)-YEAR(MAX(C8,EDATE(НачалоУчета,-1))))*12+MONTH(O$6)-MONTH(MAX(C8,EDATE(НачалоУчета,-1)))),2))-MIN(D8-F8,ROUND(D8/E8*MAX(0,(YEAR(O$6)-YEAR(MAX(C8,EDATE(НачалоУчета,-1))))*12+MONTH(O$6)-MONTH(MAX(C8,EDATE(НачалоУчета,-1)))-1),2))))) -> 0 | P8: =IF(A8="",0,IF(OR(E8<=0,P$6>ДатаОтчета,C8>=P$6),0,MAX(0,MIN(D8-F8,ROUND(D8/E8*MAX(0,(YEAR(P$6)-YEAR(MAX(C8,EDATE(НачалоУчета,-1))))*12+MONTH(P$6)-MONTH(MAX(C8,EDATE(НачалоУчета,-1)))),2))-MIN(D8-F8,ROUND(D8/E8*MAX(0,(YEAR(P$6)-YEAR(MAX(C8,EDATE(НачалоУчета,-1))))*12+MONTH(P$6)-MONTH(MAX(C8,EDATE(НачалоУчета,-1)))-1),2))))) -> 0 | Q8: =IF(A8="",0,IF(OR(E8<=0,Q$6>ДатаОтчета,C8>=Q$6),0,MAX(0,MIN(D8-F8,ROUND(D8/E8*MAX(0,(YEAR(Q$6)-YEAR(MAX(C8,EDATE(НачалоУчета,-1))))*12+MONTH(Q$6)-MONTH(MAX(C8,EDATE(НачалоУчета,-1)))),2))-MIN(D8-F8,ROUND(D8/E8*MAX(0,(YEAR(Q$6)-YEAR(MAX(C8,EDATE(НачалоУчета,-1))))*12+MONTH(Q$6)-MONTH(MAX(C8,EDATE(НачалоУчета,-1)))-1),2))))) -> 0 | R8: =IF(A8="",0,IF(OR(E8<=0,R$6>ДатаОтчета,C8>=R$6),0,MAX(0,MIN(D8-F8,ROUND(D8/E8*MAX(0,(YEAR(R$6)-YEAR(MAX(C8,EDATE(НачалоУчета,-1))))*12+MONTH(R$6)-MONTH(MAX(C8,EDATE(НачалоУчета,-1)))),2))-MIN(D8-F8,ROUND(D8/E8*MAX(0,(YEAR(R$6)-YEAR(MAX(C8,EDATE(НачалоУчета,-1))))*12+MONTH(R$6)-MONTH(MAX(C8,EDATE(НачалоУчета,-1)))-1),2))))) -> 0 | S8: =IF(A8="",0,IF(OR(E8<=0,S$6>ДатаОтчета,C8>=S$6),0,MAX(0,MIN(D8-F8,ROUND(D8/E8*MAX(0,(YEAR(S$6)-YEAR(MAX(C8,EDATE(НачалоУчета,-1))))*12+MONTH(S$6)-MONTH(MAX(C8,EDATE(НачалоУчета,-1)))),2))-MIN(D8-F8,ROUND(D8/E8*MAX(0,(YEAR(S$6)-YEAR(MAX(C8,EDATE(НачалоУчета,-1))))*12+MONTH(S$6)-MONTH(MAX(C8,EDATE(НачалоУчета,-1)))-1),2))))) -> 0 | T8: =IF(A8="",0,IF(OR(E8<=0,T$6>ДатаОтчета,C8>=T$6),0,MAX(0,MIN(D8-F8,ROUND(D8/E8*MAX(0,(YEAR(T$6)-YEAR(MAX(C8,EDATE(НачалоУчета,-1))))*12+MONTH(T$6)-MONTH(MAX(C8,EDATE(НачалоУчета,-1)))),2))-MIN(D8-F8,ROUND(D8/E8*MAX(0,(YEAR(T$6)-YEAR(MAX(C8,EDATE(НачалоУчета,-1))))*12+MONTH(T$6)-MONTH(MAX(C8,EDATE(НачалоУчета,-1)))-1),2))))) -> 0 | U8: =IF(A8="",0,IF(OR(E8<=0,U$6>ДатаОтчета,C8>=U$6),0,MAX(0,MIN(D8-F8,ROUND(D8/E8*MAX(0,(YEAR(U$6)-YEAR(MAX(C8,EDATE(НачалоУчета,-1))))*12+MONTH(U$6)-MONTH(MAX(C8,EDATE(НачалоУчета,-1)))),2))-MIN(D8-F8,ROUND(D8/E8*MAX(0,(YEAR(U$6)-YEAR(MAX(C8,EDATE(НачалоУчета,-1))))*12+MONTH(U$6)-MONTH(MAX(C8,EDATE(НачалоУчета,-1)))-1),2))))) -> 0 | V8: =IF(A8="",0,IF(OR(E8<=0,V$6>ДатаОтчета,C8>=V$6),0,MAX(0,MIN(D8-F8,ROUND(D8/E8*MAX(0,(YEAR(V$6)-YEAR(MAX(C8,EDATE(НачалоУчета,-1))))*12+MONTH(V$6)-MONTH(MAX(C8,EDATE(НачалоУчета,-1)))),2))-MIN(D8-F8,ROUND(D8/E8*MAX(0,(YEAR(V$6)-YEAR(MAX(C8,EDATE(НачалоУчета,-1))))*12+MONTH(V$6)-MONTH(MAX(C8,EDATE(НачалоУчета,-1)))-1),2))))) -> 0 | W8: =IF(A8="",IF(COUNTA(B8:F8)>0,"ОШИБКА",""),IF(OR(COUNTIF(Assets[ID],A8)<>1,B8="",NOT(ISNUMBER(C8)),NOT(ISNUMBER(D8)),D8<0,NOT(ISNUMBER(E8)),E8<=0,F8<0,F8>D8),"ОШИБКА","ОК"))
G9: =IF(A9="","",IF(C9>ДатаОтчета,0,IF(E9<=0,0,MIN(D9,F9+ROUND(D9/E9*MAX(0,(YEAR(ДатаОтчета)-YEAR(MAX(C9,EDATE(НачалоУчета,-1))))*12+MONTH(ДатаОтчета)-MONTH(MAX(C9,EDATE(НачалоУчета,-1)))),2))))) | H9: =IF(A9="","",IF(C9>ДатаОтчета,0,D9-G9)) | I9: =IF(A9="","",SUMIFS(Cash[Сумма],Cash[Дата],"<="&ДатаОтчета,Cash[Статус],"Проведён",Cash[Тип],"Покупка ОС",Cash[Документ],A9)) | J9: =IF(A9="","",IF(OR(C9>ДатаОтчета,C9<НачалоУчета),0,D9-I9)) | K9: =IF(A9="",0,IF(OR(E9<=0,K$6>ДатаОтчета,C9>=K$6),0,MAX(0,MIN(D9-F9,ROUND(D9/E9*MAX(0,(YEAR(K$6)-YEAR(MAX(C9,EDATE(НачалоУчета,-1))))*12+MONTH(K$6)-MONTH(MAX(C9,EDATE(НачалоУчета,-1)))),2))-MIN(D9-F9,ROUND(D9/E9*MAX(0,(YEAR(K$6)-YEAR(MAX(C9,EDATE(НачалоУчета,-1))))*12+MONTH(K$6)-MONTH(MAX(C9,EDATE(НачалоУчета,-1)))-1),2))))) -> 0 | L9: =IF(A9="",0,IF(OR(E9<=0,L$6>ДатаОтчета,C9>=L$6),0,MAX(0,MIN(D9-F9,ROUND(D9/E9*MAX(0,(YEAR(L$6)-YEAR(MAX(C9,EDATE(НачалоУчета,-1))))*12+MONTH(L$6)-MONTH(MAX(C9,EDATE(НачалоУчета,-1)))),2))-MIN(D9-F9,ROUND(D9/E9*MAX(0,(YEAR(L$6)-YEAR(MAX(C9,EDATE(НачалоУчета,-1))))*12+MONTH(L$6)-MONTH(MAX(C9,EDATE(НачалоУчета,-1)))-1),2))))) -> 0 | M9: =IF(A9="",0,IF(OR(E9<=0,M$6>ДатаОтчета,C9>=M$6),0,MAX(0,MIN(D9-F9,ROUND(D9/E9*MAX(0,(YEAR(M$6)-YEAR(MAX(C9,EDATE(НачалоУчета,-1))))*12+MONTH(M$6)-MONTH(MAX(C9,EDATE(НачалоУчета,-1)))),2))-MIN(D9-F9,ROUND(D9/E9*MAX(0,(YEAR(M$6)-YEAR(MAX(C9,EDATE(НачалоУчета,-1))))*12+MONTH(M$6)-MONTH(MAX(C9,EDATE(НачалоУчета,-1)))-1),2))))) -> 0 | N9: =IF(A9="",0,IF(OR(E9<=0,N$6>ДатаОтчета,C9>=N$6),0,MAX(0,MIN(D9-F9,ROUND(D9/E9*MAX(0,(YEAR(N$6)-YEAR(MAX(C9,EDATE(НачалоУчета,-1))))*12+MONTH(N$6)-MONTH(MAX(C9,EDATE(НачалоУчета,-1)))),2))-MIN(D9-F9,ROUND(D9/E9*MAX(0,(YEAR(N$6)-YEAR(MAX(C9,EDATE(НачалоУчета,-1))))*12+MONTH(N$6)-MONTH(MAX(C9,EDATE(НачалоУчета,-1)))-1),2))))) -> 0 | O9: =IF(A9="",0,IF(OR(E9<=0,O$6>ДатаОтчета,C9>=O$6),0,MAX(0,MIN(D9-F9,ROUND(D9/E9*MAX(0,(YEAR(O$6)-YEAR(MAX(C9,EDATE(НачалоУчета,-1))))*12+MONTH(O$6)-MONTH(MAX(C9,EDATE(НачалоУчета,-1)))),2))-MIN(D9-F9,ROUND(D9/E9*MAX(0,(YEAR(O$6)-YEAR(MAX(C9,EDATE(НачалоУчета,-1))))*12+MONTH(O$6)-MONTH(MAX(C9,EDATE(НачалоУчета,-1)))-1),2))))) -> 0 | P9: =IF(A9="",0,IF(OR(E9<=0,P$6>ДатаОтчета,C9>=P$6),0,MAX(0,MIN(D9-F9,ROUND(D9/E9*MAX(0,(YEAR(P$6)-YEAR(MAX(C9,EDATE(НачалоУчета,-1))))*12+MONTH(P$6)-MONTH(MAX(C9,EDATE(НачалоУчета,-1)))),2))-MIN(D9-F9,ROUND(D9/E9*MAX(0,(YEAR(P$6)-YEAR(MAX(C9,EDATE(НачалоУчета,-1))))*12+MONTH(P$6)-MONTH(MAX(C9,EDATE(НачалоУчета,-1)))-1),2))))) -> 0 | Q9: =IF(A9="",0,IF(OR(E9<=0,Q$6>ДатаОтчета,C9>=Q$6),0,MAX(0,MIN(D9-F9,ROUND(D9/E9*MAX(0,(YEAR(Q$6)-YEAR(MAX(C9,EDATE(НачалоУчета,-1))))*12+MONTH(Q$6)-MONTH(MAX(C9,EDATE(НачалоУчета,-1)))),2))-MIN(D9-F9,ROUND(D9/E9*MAX(0,(YEAR(Q$6)-YEAR(MAX(C9,EDATE(НачалоУчета,-1))))*12+MONTH(Q$6)-MONTH(MAX(C9,EDATE(НачалоУчета,-1)))-1),2))))) -> 0 | R9: =IF(A9="",0,IF(OR(E9<=0,R$6>ДатаОтчета,C9>=R$6),0,MAX(0,MIN(D9-F9,ROUND(D9/E9*MAX(0,(YEAR(R$6)-YEAR(MAX(C9,EDATE(НачалоУчета,-1))))*12+MONTH(R$6)-MONTH(MAX(C9,EDATE(НачалоУчета,-1)))),2))-MIN(D9-F9,ROUND(D9/E9*MAX(0,(YEAR(R$6)-YEAR(MAX(C9,EDATE(НачалоУчета,-1))))*12+MONTH(R$6)-MONTH(MAX(C9,EDATE(НачалоУчета,-1)))-1),2))))) -> 0 | S9: =IF(A9="",0,IF(OR(E9<=0,S$6>ДатаОтчета,C9>=S$6),0,MAX(0,MIN(D9-F9,ROUND(D9/E9*MAX(0,(YEAR(S$6)-YEAR(MAX(C9,EDATE(НачалоУчета,-1))))*12+MONTH(S$6)-MONTH(MAX(C9,EDATE(НачалоУчета,-1)))),2))-MIN(D9-F9,ROUND(D9/E9*MAX(0,(YEAR(S$6)-YEAR(MAX(C9,EDATE(НачалоУчета,-1))))*12+MONTH(S$6)-MONTH(MAX(C9,EDATE(НачалоУчета,-1)))-1),2))))) -> 0 | T9: =IF(A9="",0,IF(OR(E9<=0,T$6>ДатаОтчета,C9>=T$6),0,MAX(0,MIN(D9-F9,ROUND(D9/E9*MAX(0,(YEAR(T$6)-YEAR(MAX(C9,EDATE(НачалоУчета,-1))))*12+MONTH(T$6)-MONTH(MAX(C9,EDATE(НачалоУчета,-1)))),2))-MIN(D9-F9,ROUND(D9/E9*MAX(0,(YEAR(T$6)-YEAR(MAX(C9,EDATE(НачалоУчета,-1))))*12+MONTH(T$6)-MONTH(MAX(C9,EDATE(НачалоУчета,-1)))-1),2))))) -> 0 | U9: =IF(A9="",0,IF(OR(E9<=0,U$6>ДатаОтчета,C9>=U$6),0,MAX(0,MIN(D9-F9,ROUND(D9/E9*MAX(0,(YEAR(U$6)-YEAR(MAX(C9,EDATE(НачалоУчета,-1))))*12+MONTH(U$6)-MONTH(MAX(C9,EDATE(НачалоУчета,-1)))),2))-MIN(D9-F9,ROUND(D9/E9*MAX(0,(YEAR(U$6)-YEAR(MAX(C9,EDATE(НачалоУчета,-1))))*12+MONTH(U$6)-MONTH(MAX(C9,EDATE(НачалоУчета,-1)))-1),2))))) -> 0 | V9: =IF(A9="",0,IF(OR(E9<=0,V$6>ДатаОтчета,C9>=V$6),0,MAX(0,MIN(D9-F9,ROUND(D9/E9*MAX(0,(YEAR(V$6)-YEAR(MAX(C9,EDATE(НачалоУчета,-1))))*12+MONTH(V$6)-MONTH(MAX(C9,EDATE(НачалоУчета,-1)))),2))-MIN(D9-F9,ROUND(D9/E9*MAX(0,(YEAR(V$6)-YEAR(MAX(C9,EDATE(НачалоУчета,-1))))*12+MONTH(V$6)-MONTH(MAX(C9,EDATE(НачалоУчета,-1)))-1),2))))) -> 0 | W9: =IF(A9="",IF(COUNTA(B9:F9)>0,"ОШИБКА",""),IF(OR(COUNTIF(Assets[ID],A9)<>1,B9="",NOT(ISNUMBER(C9)),NOT(ISNUMBER(D9)),D9<0,NOT(ISNUMBER(E9)),E9<=0,F9<0,F9>D9),"ОШИБКА","ОК"))
G10: =IF(A10="","",IF(C10>ДатаОтчета,0,IF(E10<=0,0,MIN(D10,F10+ROUND(D10/E10*MAX(0,(YEAR(ДатаОтчета)-YEAR(MAX(C10,EDATE(НачалоУчета,-1))))*12+MONTH(ДатаОтчета)-MONTH(MAX(C10,EDATE(НачалоУчета,-1)))),2))))) | H10: =IF(A10="","",IF(C10>ДатаОтчета,0,D10-G10)) | I10: =IF(A10="","",SUMIFS(Cash[Сумма],Cash[Дата],"<="&ДатаОтчета,Cash[Статус],"Проведён",Cash[Тип],"Покупка ОС",Cash[Документ],A10)) | J10: =IF(A10="","",IF(OR(C10>ДатаОтчета,C10<НачалоУчета),0,D10-I10)) | K10: =IF(A10="",0,IF(OR(E10<=0,K$6>ДатаОтчета,C10>=K$6),0,MAX(0,MIN(D10-F10,ROUND(D10/E10*MAX(0,(YEAR(K$6)-YEAR(MAX(C10,EDATE(НачалоУчета,-1))))*12+MONTH(K$6)-MONTH(MAX(C10,EDATE(НачалоУчета,-1)))),2))-MIN(D10-F10,ROUND(D10/E10*MAX(0,(YEAR(K$6)-YEAR(MAX(C10,EDATE(НачалоУчета,-1))))*12+MONTH(K$6)-MONTH(MAX(C10,EDATE(НачалоУчета,-1)))-1),2))))) -> 0 | L10: =IF(A10="",0,IF(OR(E10<=0,L$6>ДатаОтчета,C10>=L$6),0,MAX(0,MIN(D10-F10,ROUND(D10/E10*MAX(0,(YEAR(L$6)-YEAR(MAX(C10,EDATE(НачалоУчета,-1))))*12+MONTH(L$6)-MONTH(MAX(C10,EDATE(НачалоУчета,-1)))),2))-MIN(D10-F10,ROUND(D10/E10*MAX(0,(YEAR(L$6)-YEAR(MAX(C10,EDATE(НачалоУчета,-1))))*12+MONTH(L$6)-MONTH(MAX(C10,EDATE(НачалоУчета,-1)))-1),2))))) -> 0 | M10: =IF(A10="",0,IF(OR(E10<=0,M$6>ДатаОтчета,C10>=M$6),0,MAX(0,MIN(D10-F10,ROUND(D10/E10*MAX(0,(YEAR(M$6)-YEAR(MAX(C10,EDATE(НачалоУчета,-1))))*12+MONTH(M$6)-MONTH(MAX(C10,EDATE(НачалоУчета,-1)))),2))-MIN(D10-F10,ROUND(D10/E10*MAX(0,(YEAR(M$6)-YEAR(MAX(C10,EDATE(НачалоУчета,-1))))*12+MONTH(M$6)-MONTH(MAX(C10,EDATE(НачалоУчета,-1)))-1),2))))) -> 0 | N10: =IF(A10="",0,IF(OR(E10<=0,N$6>ДатаОтчета,C10>=N$6),0,MAX(0,MIN(D10-F10,ROUND(D10/E10*MAX(0,(YEAR(N$6)-YEAR(MAX(C10,EDATE(НачалоУчета,-1))))*12+MONTH(N$6)-MONTH(MAX(C10,EDATE(НачалоУчета,-1)))),2))-MIN(D10-F10,ROUND(D10/E10*MAX(0,(YEAR(N$6)-YEAR(MAX(C10,EDATE(НачалоУчета,-1))))*12+MONTH(N$6)-MONTH(MAX(C10,EDATE(НачалоУчета,-1)))-1),2))))) -> 0 | O10: =IF(A10="",0,IF(OR(E10<=0,O$6>ДатаОтчета,C10>=O$6),0,MAX(0,MIN(D10-F10,ROUND(D10/E10*MAX(0,(YEAR(O$6)-YEAR(MAX(C10,EDATE(НачалоУчета,-1))))*12+MONTH(O$6)-MONTH(MAX(C10,EDATE(НачалоУчета,-1)))),2))-MIN(D10-F10,ROUND(D10/E10*MAX(0,(YEAR(O$6)-YEAR(MAX(C10,EDATE(НачалоУчета,-1))))*12+MONTH(O$6)-MONTH(MAX(C10,EDATE(НачалоУчета,-1)))-1),2))))) -> 0 | P10: =IF(A10="",0,IF(OR(E10<=0,P$6>ДатаОтчета,C10>=P$6),0,MAX(0,MIN(D10-F10,ROUND(D10/E10*MAX(0,(YEAR(P$6)-YEAR(MAX(C10,EDATE(НачалоУчета,-1))))*12+MONTH(P$6)-MONTH(MAX(C10,EDATE(НачалоУчета,-1)))),2))-MIN(D10-F10,ROUND(D10/E10*MAX(0,(YEAR(P$6)-YEAR(MAX(C10,EDATE(НачалоУчета,-1))))*12+MONTH(P$6)-MONTH(MAX(C10,EDATE(НачалоУчета,-1)))-1),2))))) -> 0 | Q10: =IF(A10="",0,IF(OR(E10<=0,Q$6>ДатаОтчета,C10>=Q$6),0,MAX(0,MIN(D10-F10,ROUND(D10/E10*MAX(0,(YEAR(Q$6)-YEAR(MAX(C10,EDATE(НачалоУчета,-1))))*12+MONTH(Q$6)-MONTH(MAX(C10,EDATE(НачалоУчета,-1)))),2))-MIN(D10-F10,ROUND(D10/E10*MAX(0,(YEAR(Q$6)-YEAR(MAX(C10,EDATE(НачалоУчета,-1))))*12+MONTH(Q$6)-MONTH(MAX(C10,EDATE(НачалоУчета,-1)))-1),2))))) -> 0 | R10: =IF(A10="",0,IF(OR(E10<=0,R$6>ДатаОтчета,C10>=R$6),0,MAX(0,MIN(D10-F10,ROUND(D10/E10*MAX(0,(YEAR(R$6)-YEAR(MAX(C10,EDATE(НачалоУчета,-1))))*12+MONTH(R$6)-MONTH(MAX(C10,EDATE(НачалоУчета,-1)))),2))-MIN(D10-F10,ROUND(D10/E10*MAX(0,(YEAR(R$6)-YEAR(MAX(C10,EDATE(НачалоУчета,-1))))*12+MONTH(R$6)-MONTH(MAX(C10,EDATE(НачалоУчета,-1)))-1),2))))) -> 0 | S10: =IF(A10="",0,IF(OR(E10<=0,S$6>ДатаОтчета,C10>=S$6),0,MAX(0,MIN(D10-F10,ROUND(D10/E10*MAX(0,(YEAR(S$6)-YEAR(MAX(C10,EDATE(НачалоУчета,-1))))*12+MONTH(S$6)-MONTH(MAX(C10,EDATE(НачалоУчета,-1)))),2))-MIN(D10-F10,ROUND(D10/E10*MAX(0,(YEAR(S$6)-YEAR(MAX(C10,EDATE(НачалоУчета,-1))))*12+MONTH(S$6)-MONTH(MAX(C10,EDATE(НачалоУчета,-1)))-1),2))))) -> 0 | T10: =IF(A10="",0,IF(OR(E10<=0,T$6>ДатаОтчета,C10>=T$6),0,MAX(0,MIN(D10-F10,ROUND(D10/E10*MAX(0,(YEAR(T$6)-YEAR(MAX(C10,EDATE(НачалоУчета,-1))))*12+MONTH(T$6)-MONTH(MAX(C10,EDATE(НачалоУчета,-1)))),2))-MIN(D10-F10,ROUND(D10/E10*MAX(0,(YEAR(T$6)-YEAR(MAX(C10,EDATE(НачалоУчета,-1))))*12+MONTH(T$6)-MONTH(MAX(C10,EDATE(НачалоУчета,-1)))-1),2))))) -> 0 | U10: =IF(A10="",0,IF(OR(E10<=0,U$6>ДатаОтчета,C10>=U$6),0,MAX(0,MIN(D10-F10,ROUND(D10/E10*MAX(0,(YEAR(U$6)-YEAR(MAX(C10,EDATE(НачалоУчета,-1))))*12+MONTH(U$6)-MONTH(MAX(C10,EDATE(НачалоУчета,-1)))),2))-MIN(D10-F10,ROUND(D10/E10*MAX(0,(YEAR(U$6)-YEAR(MAX(C10,EDATE(НачалоУчета,-1))))*12+MONTH(U$6)-MONTH(MAX(C10,EDATE(НачалоУчета,-1)))-1),2))))) -> 0 | V10: =IF(A10="",0,IF(OR(E10<=0,V$6>ДатаОтчета,C10>=V$6),0,MAX(0,MIN(D10-F10,ROUND(D10/E10*MAX(0,(YEAR(V$6)-YEAR(MAX(C10,EDATE(НачалоУчета,-1))))*12+MONTH(V$6)-MONTH(MAX(C10,EDATE(НачалоУчета,-1)))),2))-MIN(D10-F10,ROUND(D10/E10*MAX(0,(YEAR(V$6)-YEAR(MAX(C10,EDATE(НачалоУчета,-1))))*12+MONTH(V$6)-MONTH(MAX(C10,EDATE(НачалоУчета,-1)))-1),2))))) -> 0 | W10: =IF(A10="",IF(COUNTA(B10:F10)>0,"ОШИБКА",""),IF(OR(COUNTIF(Assets[ID],A10)<>1,B10="",NOT(ISNUMBER(C10)),NOT(ISNUMBER(D10)),D10<0,NOT(ISNUMBER(E10)),E10<=0,F10<0,F10>D10),"ОШИБКА","ОК"))
G11: =IF(A11="","",IF(C11>ДатаОтчета,0,IF(E11<=0,0,MIN(D11,F11+ROUND(D11/E11*MAX(0,(YEAR(ДатаОтчета)-YEAR(MAX(C11,EDATE(НачалоУчета,-1))))*12+MONTH(ДатаОтчета)-MONTH(MAX(C11,EDATE(НачалоУчета,-1)))),2))))) | H11: =IF(A11="","",IF(C11>ДатаОтчета,0,D11-G11)) | I11: =IF(A11="","",SUMIFS(Cash[Сумма],Cash[Дата],"<="&ДатаОтчета,Cash[Статус],"Проведён",Cash[Тип],"Покупка ОС",Cash[Документ],A11)) | J11: =IF(A11="","",IF(OR(C11>ДатаОтчета,C11<НачалоУчета),0,D11-I11)) | K11: =IF(A11="",0,IF(OR(E11<=0,K$6>ДатаОтчета,C11>=K$6),0,MAX(0,MIN(D11-F11,ROUND(D11/E11*MAX(0,(YEAR(K$6)-YEAR(MAX(C11,EDATE(НачалоУчета,-1))))*12+MONTH(K$6)-MONTH(MAX(C11,EDATE(НачалоУчета,-1)))),2))-MIN(D11-F11,ROUND(D11/E11*MAX(0,(YEAR(K$6)-YEAR(MAX(C11,EDATE(НачалоУчета,-1))))*12+MONTH(K$6)-MONTH(MAX(C11,EDATE(НачалоУчета,-1)))-1),2))))) -> 0 | L11: =IF(A11="",0,IF(OR(E11<=0,L$6>ДатаОтчета,C11>=L$6),0,MAX(0,MIN(D11-F11,ROUND(D11/E11*MAX(0,(YEAR(L$6)-YEAR(MAX(C11,EDATE(НачалоУчета,-1))))*12+MONTH(L$6)-MONTH(MAX(C11,EDATE(НачалоУчета,-1)))),2))-MIN(D11-F11,ROUND(D11/E11*MAX(0,(YEAR(L$6)-YEAR(MAX(C11,EDATE(НачалоУчета,-1))))*12+MONTH(L$6)-MONTH(MAX(C11,EDATE(НачалоУчета,-1)))-1),2))))) -> 0 | M11: =IF(A11="",0,IF(OR(E11<=0,M$6>ДатаОтчета,C11>=M$6),0,MAX(0,MIN(D11-F11,ROUND(D11/E11*MAX(0,(YEAR(M$6)-YEAR(MAX(C11,EDATE(НачалоУчета,-1))))*12+MONTH(M$6)-MONTH(MAX(C11,EDATE(НачалоУчета,-1)))),2))-MIN(D11-F11,ROUND(D11/E11*MAX(0,(YEAR(M$6)-YEAR(MAX(C11,EDATE(НачалоУчета,-1))))*12+MONTH(M$6)-MONTH(MAX(C11,EDATE(НачалоУчета,-1)))-1),2))))) -> 0 | N11: =IF(A11="",0,IF(OR(E11<=0,N$6>ДатаОтчета,C11>=N$6),0,MAX(0,MIN(D11-F11,ROUND(D11/E11*MAX(0,(YEAR(N$6)-YEAR(MAX(C11,EDATE(НачалоУчета,-1))))*12+MONTH(N$6)-MONTH(MAX(C11,EDATE(НачалоУчета,-1)))),2))-MIN(D11-F11,ROUND(D11/E11*MAX(0,(YEAR(N$6)-YEAR(MAX(C11,EDATE(НачалоУчета,-1))))*12+MONTH(N$6)-MONTH(MAX(C11,EDATE(НачалоУчета,-1)))-1),2))))) -> 0 | O11: =IF(A11="",0,IF(OR(E11<=0,O$6>ДатаОтчета,C11>=O$6),0,MAX(0,MIN(D11-F11,ROUND(D11/E11*MAX(0,(YEAR(O$6)-YEAR(MAX(C11,EDATE(НачалоУчета,-1))))*12+MONTH(O$6)-MONTH(MAX(C11,EDATE(НачалоУчета,-1)))),2))-MIN(D11-F11,ROUND(D11/E11*MAX(0,(YEAR(O$6)-YEAR(MAX(C11,EDATE(НачалоУчета,-1))))*12+MONTH(O$6)-MONTH(MAX(C11,EDATE(НачалоУчета,-1)))-1),2))))) -> 0 | P11: =IF(A11="",0,IF(OR(E11<=0,P$6>ДатаОтчета,C11>=P$6),0,MAX(0,MIN(D11-F11,ROUND(D11/E11*MAX(0,(YEAR(P$6)-YEAR(MAX(C11,EDATE(НачалоУчета,-1))))*12+MONTH(P$6)-MONTH(MAX(C11,EDATE(НачалоУчета,-1)))),2))-MIN(D11-F11,ROUND(D11/E11*MAX(0,(YEAR(P$6)-YEAR(MAX(C11,EDATE(НачалоУчета,-1))))*12+MONTH(P$6)-MONTH(MAX(C11,EDATE(НачалоУчета,-1)))-1),2))))) -> 0 | Q11: =IF(A11="",0,IF(OR(E11<=0,Q$6>ДатаОтчета,C11>=Q$6),0,MAX(0,MIN(D11-F11,ROUND(D11/E11*MAX(0,(YEAR(Q$6)-YEAR(MAX(C11,EDATE(НачалоУчета,-1))))*12+MONTH(Q$6)-MONTH(MAX(C11,EDATE(НачалоУчета,-1)))),2))-MIN(D11-F11,ROUND(D11/E11*MAX(0,(YEAR(Q$6)-YEAR(MAX(C11,EDATE(НачалоУчета,-1))))*12+MONTH(Q$6)-MONTH(MAX(C11,EDATE(НачалоУчета,-1)))-1),2))))) -> 0 | R11: =IF(A11="",0,IF(OR(E11<=0,R$6>ДатаОтчета,C11>=R$6),0,MAX(0,MIN(D11-F11,ROUND(D11/E11*MAX(0,(YEAR(R$6)-YEAR(MAX(C11,EDATE(НачалоУчета,-1))))*12+MONTH(R$6)-MONTH(MAX(C11,EDATE(НачалоУчета,-1)))),2))-MIN(D11-F11,ROUND(D11/E11*MAX(0,(YEAR(R$6)-YEAR(MAX(C11,EDATE(НачалоУчета,-1))))*12+MONTH(R$6)-MONTH(MAX(C11,EDATE(НачалоУчета,-1)))-1),2))))) -> 0 | S11: =IF(A11="",0,IF(OR(E11<=0,S$6>ДатаОтчета,C11>=S$6),0,MAX(0,MIN(D11-F11,ROUND(D11/E11*MAX(0,(YEAR(S$6)-YEAR(MAX(C11,EDATE(НачалоУчета,-1))))*12+MONTH(S$6)-MONTH(MAX(C11,EDATE(НачалоУчета,-1)))),2))-MIN(D11-F11,ROUND(D11/E11*MAX(0,(YEAR(S$6)-YEAR(MAX(C11,EDATE(НачалоУчета,-1))))*12+MONTH(S$6)-MONTH(MAX(C11,EDATE(НачалоУчета,-1)))-1),2))))) -> 0 | T11: =IF(A11="",0,IF(OR(E11<=0,T$6>ДатаОтчета,C11>=T$6),0,MAX(0,MIN(D11-F11,ROUND(D11/E11*MAX(0,(YEAR(T$6)-YEAR(MAX(C11,EDATE(НачалоУчета,-1))))*12+MONTH(T$6)-MONTH(MAX(C11,EDATE(НачалоУчета,-1)))),2))-MIN(D11-F11,ROUND(D11/E11*MAX(0,(YEAR(T$6)-YEAR(MAX(C11,EDATE(НачалоУчета,-1))))*12+MONTH(T$6)-MONTH(MAX(C11,EDATE(НачалоУчета,-1)))-1),2))))) -> 0 | U11: =IF(A11="",0,IF(OR(E11<=0,U$6>ДатаОтчета,C11>=U$6),0,MAX(0,MIN(D11-F11,ROUND(D11/E11*MAX(0,(YEAR(U$6)-YEAR(MAX(C11,EDATE(НачалоУчета,-1))))*12+MONTH(U$6)-MONTH(MAX(C11,EDATE(НачалоУчета,-1)))),2))-MIN(D11-F11,ROUND(D11/E11*MAX(0,(YEAR(U$6)-YEAR(MAX(C11,EDATE(НачалоУчета,-1))))*12+MONTH(U$6)-MONTH(MAX(C11,EDATE(НачалоУчета,-1)))-1),2))))) -> 0 | V11: =IF(A11="",0,IF(OR(E11<=0,V$6>ДатаОтчета,C11>=V$6),0,MAX(0,MIN(D11-F11,ROUND(D11/E11*MAX(0,(YEAR(V$6)-YEAR(MAX(C11,EDATE(НачалоУчета,-1))))*12+MONTH(V$6)-MONTH(MAX(C11,EDATE(НачалоУчета,-1)))),2))-MIN(D11-F11,ROUND(D11/E11*MAX(0,(YEAR(V$6)-YEAR(MAX(C11,EDATE(НачалоУчета,-1))))*12+MONTH(V$6)-MONTH(MAX(C11,EDATE(НачалоУчета,-1)))-1),2))))) -> 0 | W11: =IF(A11="",IF(COUNTA(B11:F11)>0,"ОШИБКА",""),IF(OR(COUNTIF(Assets[ID],A11)<>1,B11="",NOT(ISNUMBER(C11)),NOT(ISNUMBER(D11)),D11<0,NOT(ISNUMBER(E11)),E11<=0,F11<0,F11>D11),"ОШИБКА","ОК"))
G12: =IF(A12="","",IF(C12>ДатаОтчета,0,IF(E12<=0,0,MIN(D12,F12+ROUND(D12/E12*MAX(0,(YEAR(ДатаОтчета)-YEAR(MAX(C12,EDATE(НачалоУчета,-1))))*12+MONTH(ДатаОтчета)-MONTH(MAX(C12,EDATE(НачалоУчета,-1)))),2))))) | H12: =IF(A12="","",IF(C12>ДатаОтчета,0,D12-G12)) | I12: =IF(A12="","",SUMIFS(Cash[Сумма],Cash[Дата],"<="&ДатаОтчета,Cash[Статус],"Проведён",Cash[Тип],"Покупка ОС",Cash[Документ],A12)) | J12: =IF(A12="","",IF(OR(C12>ДатаОтчета,C12<НачалоУчета),0,D12-I12)) | K12: =IF(A12="",0,IF(OR(E12<=0,K$6>ДатаОтчета,C12>=K$6),0,MAX(0,MIN(D12-F12,ROUND(D12/E12*MAX(0,(YEAR(K$6)-YEAR(MAX(C12,EDATE(НачалоУчета,-1))))*12+MONTH(K$6)-MONTH(MAX(C12,EDATE(НачалоУчета,-1)))),2))-MIN(D12-F12,ROUND(D12/E12*MAX(0,(YEAR(K$6)-YEAR(MAX(C12,EDATE(НачалоУчета,-1))))*12+MONTH(K$6)-MONTH(MAX(C12,EDATE(НачалоУчета,-1)))-1),2))))) -> 0 | L12: =IF(A12="",0,IF(OR(E12<=0,L$6>ДатаОтчета,C12>=L$6),0,MAX(0,MIN(D12-F12,ROUND(D12/E12*MAX(0,(YEAR(L$6)-YEAR(MAX(C12,EDATE(НачалоУчета,-1))))*12+MONTH(L$6)-MONTH(MAX(C12,EDATE(НачалоУчета,-1)))),2))-MIN(D12-F12,ROUND(D12/E12*MAX(0,(YEAR(L$6)-YEAR(MAX(C12,EDATE(НачалоУчета,-1))))*12+MONTH(L$6)-MONTH(MAX(C12,EDATE(НачалоУчета,-1)))-1),2))))) -> 0 | M12: =IF(A12="",0,IF(OR(E12<=0,M$6>ДатаОтчета,C12>=M$6),0,MAX(0,MIN(D12-F12,ROUND(D12/E12*MAX(0,(YEAR(M$6)-YEAR(MAX(C12,EDATE(НачалоУчета,-1))))*12+MONTH(M$6)-MONTH(MAX(C12,EDATE(НачалоУчета,-1)))),2))-MIN(D12-F12,ROUND(D12/E12*MAX(0,(YEAR(M$6)-YEAR(MAX(C12,EDATE(НачалоУчета,-1))))*12+MONTH(M$6)-MONTH(MAX(C12,EDATE(НачалоУчета,-1)))-1),2))))) -> 0 | N12: =IF(A12="",0,IF(OR(E12<=0,N$6>ДатаОтчета,C12>=N$6),0,MAX(0,MIN(D12-F12,ROUND(D12/E12*MAX(0,(YEAR(N$6)-YEAR(MAX(C12,EDATE(НачалоУчета,-1))))*12+MONTH(N$6)-MONTH(MAX(C12,EDATE(НачалоУчета,-1)))),2))-MIN(D12-F12,ROUND(D12/E12*MAX(0,(YEAR(N$6)-YEAR(MAX(C12,EDATE(НачалоУчета,-1))))*12+MONTH(N$6)-MONTH(MAX(C12,EDATE(НачалоУчета,-1)))-1),2))))) -> 0 | O12: =IF(A12="",0,IF(OR(E12<=0,O$6>ДатаОтчета,C12>=O$6),0,MAX(0,MIN(D12-F12,ROUND(D12/E12*MAX(0,(YEAR(O$6)-YEAR(MAX(C12,EDATE(НачалоУчета,-1))))*12+MONTH(O$6)-MONTH(MAX(C12,EDATE(НачалоУчета,-1)))),2))-MIN(D12-F12,ROUND(D12/E12*MAX(0,(YEAR(O$6)-YEAR(MAX(C12,EDATE(НачалоУчета,-1))))*12+MONTH(O$6)-MONTH(MAX(C12,EDATE(НачалоУчета,-1)))-1),2))))) -> 0 | P12: =IF(A12="",0,IF(OR(E12<=0,P$6>ДатаОтчета,C12>=P$6),0,MAX(0,MIN(D12-F12,ROUND(D12/E12*MAX(0,(YEAR(P$6)-YEAR(MAX(C12,EDATE(НачалоУчета,-1))))*12+MONTH(P$6)-MONTH(MAX(C12,EDATE(НачалоУчета,-1)))),2))-MIN(D12-F12,ROUND(D12/E12*MAX(0,(YEAR(P$6)-YEAR(MAX(C12,EDATE(НачалоУчета,-1))))*12+MONTH(P$6)-MONTH(MAX(C12,EDATE(НачалоУчета,-1)))-1),2))))) -> 0 | Q12: =IF(A12="",0,IF(OR(E12<=0,Q$6>ДатаОтчета,C12>=Q$6),0,MAX(0,MIN(D12-F12,ROUND(D12/E12*MAX(0,(YEAR(Q$6)-YEAR(MAX(C12,EDATE(НачалоУчета,-1))))*12+MONTH(Q$6)-MONTH(MAX(C12,EDATE(НачалоУчета,-1)))),2))-MIN(D12-F12,ROUND(D12/E12*MAX(0,(YEAR(Q$6)-YEAR(MAX(C12,EDATE(НачалоУчета,-1))))*12+MONTH(Q$6)-MONTH(MAX(C12,EDATE(НачалоУчета,-1)))-1),2))))) -> 0 | R12: =IF(A12="",0,IF(OR(E12<=0,R$6>ДатаОтчета,C12>=R$6),0,MAX(0,MIN(D12-F12,ROUND(D12/E12*MAX(0,(YEAR(R$6)-YEAR(MAX(C12,EDATE(НачалоУчета,-1))))*12+MONTH(R$6)-MONTH(MAX(C12,EDATE(НачалоУчета,-1)))),2))-MIN(D12-F12,ROUND(D12/E12*MAX(0,(YEAR(R$6)-YEAR(MAX(C12,EDATE(НачалоУчета,-1))))*12+MONTH(R$6)-MONTH(MAX(C12,EDATE(НачалоУчета,-1)))-1),2))))) -> 0 | S12: =IF(A12="",0,IF(OR(E12<=0,S$6>ДатаОтчета,C12>=S$6),0,MAX(0,MIN(D12-F12,ROUND(D12/E12*MAX(0,(YEAR(S$6)-YEAR(MAX(C12,EDATE(НачалоУчета,-1))))*12+MONTH(S$6)-MONTH(MAX(C12,EDATE(НачалоУчета,-1)))),2))-MIN(D12-F12,ROUND(D12/E12*MAX(0,(YEAR(S$6)-YEAR(MAX(C12,EDATE(НачалоУчета,-1))))*12+MONTH(S$6)-MONTH(MAX(C12,EDATE(НачалоУчета,-1)))-1),2))))) -> 0 | T12: =IF(A12="",0,IF(OR(E12<=0,T$6>ДатаОтчета,C12>=T$6),0,MAX(0,MIN(D12-F12,ROUND(D12/E12*MAX(0,(YEAR(T$6)-YEAR(MAX(C12,EDATE(НачалоУчета,-1))))*12+MONTH(T$6)-MONTH(MAX(C12,EDATE(НачалоУчета,-1)))),2))-MIN(D12-F12,ROUND(D12/E12*MAX(0,(YEAR(T$6)-YEAR(MAX(C12,EDATE(НачалоУчета,-1))))*12+MONTH(T$6)-MONTH(MAX(C12,EDATE(НачалоУчета,-1)))-1),2))))) -> 0 | U12: =IF(A12="",0,IF(OR(E12<=0,U$6>ДатаОтчета,C12>=U$6),0,MAX(0,MIN(D12-F12,ROUND(D12/E12*MAX(0,(YEAR(U$6)-YEAR(MAX(C12,EDATE(НачалоУчета,-1))))*12+MONTH(U$6)-MONTH(MAX(C12,EDATE(НачалоУчета,-1)))),2))-MIN(D12-F12,ROUND(D12/E12*MAX(0,(YEAR(U$6)-YEAR(MAX(C12,EDATE(НачалоУчета,-1))))*12+MONTH(U$6)-MONTH(MAX(C12,EDATE(НачалоУчета,-1)))-1),2))))) -> 0 | V12: =IF(A12="",0,IF(OR(E12<=0,V$6>ДатаОтчета,C12>=V$6),0,MAX(0,MIN(D12-F12,ROUND(D12/E12*MAX(0,(YEAR(V$6)-YEAR(MAX(C12,EDATE(НачалоУчета,-1))))*12+MONTH(V$6)-MONTH(MAX(C12,EDATE(НачалоУчета,-1)))),2))-MIN(D12-F12,ROUND(D12/E12*MAX(0,(YEAR(V$6)-YEAR(MAX(C12,EDATE(НачалоУчета,-1))))*12+MONTH(V$6)-MONTH(MAX(C12,EDATE(НачалоУчета,-1)))-1),2))))) -> 0 | W12: =IF(A12="",IF(COUNTA(B12:F12)>0,"ОШИБКА",""),IF(OR(COUNTIF(Assets[ID],A12)<>1,B12="",NOT(ISNUMBER(C12)),NOT(ISNUMBER(D12)),D12<0,NOT(ISNUMBER(E12)),E12<=0,F12<0,F12>D12),"ОШИБКА","ОК"))
G13: =IF(A13="","",IF(C13>ДатаОтчета,0,IF(E13<=0,0,MIN(D13,F13+ROUND(D13/E13*MAX(0,(YEAR(ДатаОтчета)-YEAR(MAX(C13,EDATE(НачалоУчета,-1))))*12+MONTH(ДатаОтчета)-MONTH(MAX(C13,EDATE(НачалоУчета,-1)))),2))))) | H13: =IF(A13="","",IF(C13>ДатаОтчета,0,D13-G13)) | I13: =IF(A13="","",SUMIFS(Cash[Сумма],Cash[Дата],"<="&ДатаОтчета,Cash[Статус],"Проведён",Cash[Тип],"Покупка ОС",Cash[Документ],A13)) | J13: =IF(A13="","",IF(OR(C13>ДатаОтчета,C13<НачалоУчета),0,D13-I13)) | K13: =IF(A13="",0,IF(OR(E13<=0,K$6>ДатаОтчета,C13>=K$6),0,MAX(0,MIN(D13-F13,ROUND(D13/E13*MAX(0,(YEAR(K$6)-YEAR(MAX(C13,EDATE(НачалоУчета,-1))))*12+MONTH(K$6)-MONTH(MAX(C13,EDATE(НачалоУчета,-1)))),2))-MIN(D13-F13,ROUND(D13/E13*MAX(0,(YEAR(K$6)-YEAR(MAX(C13,EDATE(НачалоУчета,-1))))*12+MONTH(K$6)-MONTH(MAX(C13,EDATE(НачалоУчета,-1)))-1),2))))) -> 0 | L13: =IF(A13="",0,IF(OR(E13<=0,L$6>ДатаОтчета,C13>=L$6),0,MAX(0,MIN(D13-F13,ROUND(D13/E13*MAX(0,(YEAR(L$6)-YEAR(MAX(C13,EDATE(НачалоУчета,-1))))*12+MONTH(L$6)-MONTH(MAX(C13,EDATE(НачалоУчета,-1)))),2))-MIN(D13-F13,ROUND(D13/E13*MAX(0,(YEAR(L$6)-YEAR(MAX(C13,EDATE(НачалоУчета,-1))))*12+MONTH(L$6)-MONTH(MAX(C13,EDATE(НачалоУчета,-1)))-1),2))))) -> 0 | M13: =IF(A13="",0,IF(OR(E13<=0,M$6>ДатаОтчета,C13>=M$6),0,MAX(0,MIN(D13-F13,ROUND(D13/E13*MAX(0,(YEAR(M$6)-YEAR(MAX(C13,EDATE(НачалоУчета,-1))))*12+MONTH(M$6)-MONTH(MAX(C13,EDATE(НачалоУчета,-1)))),2))-MIN(D13-F13,ROUND(D13/E13*MAX(0,(YEAR(M$6)-YEAR(MAX(C13,EDATE(НачалоУчета,-1))))*12+MONTH(M$6)-MONTH(MAX(C13,EDATE(НачалоУчета,-1)))-1),2))))) -> 0 | N13: =IF(A13="",0,IF(OR(E13<=0,N$6>ДатаОтчета,C13>=N$6),0,MAX(0,MIN(D13-F13,ROUND(D13/E13*MAX(0,(YEAR(N$6)-YEAR(MAX(C13,EDATE(НачалоУчета,-1))))*12+MONTH(N$6)-MONTH(MAX(C13,EDATE(НачалоУчета,-1)))),2))-MIN(D13-F13,ROUND(D13/E13*MAX(0,(YEAR(N$6)-YEAR(MAX(C13,EDATE(НачалоУчета,-1))))*12+MONTH(N$6)-MONTH(MAX(C13,EDATE(НачалоУчета,-1)))-1),2))))) -> 0 | O13: =IF(A13="",0,IF(OR(E13<=0,O$6>ДатаОтчета,C13>=O$6),0,MAX(0,MIN(D13-F13,ROUND(D13/E13*MAX(0,(YEAR(O$6)-YEAR(MAX(C13,EDATE(НачалоУчета,-1))))*12+MONTH(O$6)-MONTH(MAX(C13,EDATE(НачалоУчета,-1)))),2))-MIN(D13-F13,ROUND(D13/E13*MAX(0,(YEAR(O$6)-YEAR(MAX(C13,EDATE(НачалоУчета,-1))))*12+MONTH(O$6)-MONTH(MAX(C13,EDATE(НачалоУчета,-1)))-1),2))))) -> 0 | P13: =IF(A13="",0,IF(OR(E13<=0,P$6>ДатаОтчета,C13>=P$6),0,MAX(0,MIN(D13-F13,ROUND(D13/E13*MAX(0,(YEAR(P$6)-YEAR(MAX(C13,EDATE(НачалоУчета,-1))))*12+MONTH(P$6)-MONTH(MAX(C13,EDATE(НачалоУчета,-1)))),2))-MIN(D13-F13,ROUND(D13/E13*MAX(0,(YEAR(P$6)-YEAR(MAX(C13,EDATE(НачалоУчета,-1))))*12+MONTH(P$6)-MONTH(MAX(C13,EDATE(НачалоУчета,-1)))-1),2))))) -> 0 | Q13: =IF(A13="",0,IF(OR(E13<=0,Q$6>ДатаОтчета,C13>=Q$6),0,MAX(0,MIN(D13-F13,ROUND(D13/E13*MAX(0,(YEAR(Q$6)-YEAR(MAX(C13,EDATE(НачалоУчета,-1))))*12+MONTH(Q$6)-MONTH(MAX(C13,EDATE(НачалоУчета,-1)))),2))-MIN(D13-F13,ROUND(D13/E13*MAX(0,(YEAR(Q$6)-YEAR(MAX(C13,EDATE(НачалоУчета,-1))))*12+MONTH(Q$6)-MONTH(MAX(C13,EDATE(НачалоУчета,-1)))-1),2))))) -> 0 | R13: =IF(A13="",0,IF(OR(E13<=0,R$6>ДатаОтчета,C13>=R$6),0,MAX(0,MIN(D13-F13,ROUND(D13/E13*MAX(0,(YEAR(R$6)-YEAR(MAX(C13,EDATE(НачалоУчета,-1))))*12+MONTH(R$6)-MONTH(MAX(C13,EDATE(НачалоУчета,-1)))),2))-MIN(D13-F13,ROUND(D13/E13*MAX(0,(YEAR(R$6)-YEAR(MAX(C13,EDATE(НачалоУчета,-1))))*12+MONTH(R$6)-MONTH(MAX(C13,EDATE(НачалоУчета,-1)))-1),2))))) -> 0 | S13: =IF(A13="",0,IF(OR(E13<=0,S$6>ДатаОтчета,C13>=S$6),0,MAX(0,MIN(D13-F13,ROUND(D13/E13*MAX(0,(YEAR(S$6)-YEAR(MAX(C13,EDATE(НачалоУчета,-1))))*12+MONTH(S$6)-MONTH(MAX(C13,EDATE(НачалоУчета,-1)))),2))-MIN(D13-F13,ROUND(D13/E13*MAX(0,(YEAR(S$6)-YEAR(MAX(C13,EDATE(НачалоУчета,-1))))*12+MONTH(S$6)-MONTH(MAX(C13,EDATE(НачалоУчета,-1)))-1),2))))) -> 0 | T13: =IF(A13="",0,IF(OR(E13<=0,T$6>ДатаОтчета,C13>=T$6),0,MAX(0,MIN(D13-F13,ROUND(D13/E13*MAX(0,(YEAR(T$6)-YEAR(MAX(C13,EDATE(НачалоУчета,-1))))*12+MONTH(T$6)-MONTH(MAX(C13,EDATE(НачалоУчета,-1)))),2))-MIN(D13-F13,ROUND(D13/E13*MAX(0,(YEAR(T$6)-YEAR(MAX(C13,EDATE(НачалоУчета,-1))))*12+MONTH(T$6)-MONTH(MAX(C13,EDATE(НачалоУчета,-1)))-1),2))))) -> 0 | U13: =IF(A13="",0,IF(OR(E13<=0,U$6>ДатаОтчета,C13>=U$6),0,MAX(0,MIN(D13-F13,ROUND(D13/E13*MAX(0,(YEAR(U$6)-YEAR(MAX(C13,EDATE(НачалоУчета,-1))))*12+MONTH(U$6)-MONTH(MAX(C13,EDATE(НачалоУчета,-1)))),2))-MIN(D13-F13,ROUND(D13/E13*MAX(0,(YEAR(U$6)-YEAR(MAX(C13,EDATE(НачалоУчета,-1))))*12+MONTH(U$6)-MONTH(MAX(C13,EDATE(НачалоУчета,-1)))-1),2))))) -> 0 | V13: =IF(A13="",0,IF(OR(E13<=0,V$6>ДатаОтчета,C13>=V$6),0,MAX(0,MIN(D13-F13,ROUND(D13/E13*MAX(0,(YEAR(V$6)-YEAR(MAX(C13,EDATE(НачалоУчета,-1))))*12+MONTH(V$6)-MONTH(MAX(C13,EDATE(НачалоУчета,-1)))),2))-MIN(D13-F13,ROUND(D13/E13*MAX(0,(YEAR(V$6)-YEAR(MAX(C13,EDATE(НачалоУчета,-1))))*12+MONTH(V$6)-MONTH(MAX(C13,EDATE(НачалоУчета,-1)))-1),2))))) -> 0 | W13: =IF(A13="",IF(COUNTA(B13:F13)>0,"ОШИБКА",""),IF(OR(COUNTIF(Assets[ID],A13)<>1,B13="",NOT(ISNUMBER(C13)),NOT(ISNUMBER(D13)),D13<0,NOT(ISNUMBER(E13)),E13<=0,F13<0,F13>D13),"ОШИБКА","ОК"))
G14: =IF(A14="","",IF(C14>ДатаОтчета,0,IF(E14<=0,0,MIN(D14,F14+ROUND(D14/E14*MAX(0,(YEAR(ДатаОтчета)-YEAR(MAX(C14,EDATE(НачалоУчета,-1))))*12+MONTH(ДатаОтчета)-MONTH(MAX(C14,EDATE(НачалоУчета,-1)))),2))))) | H14: =IF(A14="","",IF(C14>ДатаОтчета,0,D14-G14)) | I14: =IF(A14="","",SUMIFS(Cash[Сумма],Cash[Дата],"<="&ДатаОтчета,Cash[Статус],"Проведён",Cash[Тип],"Покупка ОС",Cash[Документ],A14)) | J14: =IF(A14="","",IF(OR(C14>ДатаОтчета,C14<НачалоУчета),0,D14-I14)) | K14: =IF(A14="",0,IF(OR(E14<=0,K$6>ДатаОтчета,C14>=K$6),0,MAX(0,MIN(D14-F14,ROUND(D14/E14*MAX(0,(YEAR(K$6)-YEAR(MAX(C14,EDATE(НачалоУчета,-1))))*12+MONTH(K$6)-MONTH(MAX(C14,EDATE(НачалоУчета,-1)))),2))-MIN(D14-F14,ROUND(D14/E14*MAX(0,(YEAR(K$6)-YEAR(MAX(C14,EDATE(НачалоУчета,-1))))*12+MONTH(K$6)-MONTH(MAX(C14,EDATE(НачалоУчета,-1)))-1),2))))) -> 0 | L14: =IF(A14="",0,IF(OR(E14<=0,L$6>ДатаОтчета,C14>=L$6),0,MAX(0,MIN(D14-F14,ROUND(D14/E14*MAX(0,(YEAR(L$6)-YEAR(MAX(C14,EDATE(НачалоУчета,-1))))*12+MONTH(L$6)-MONTH(MAX(C14,EDATE(НачалоУчета,-1)))),2))-MIN(D14-F14,ROUND(D14/E14*MAX(0,(YEAR(L$6)-YEAR(MAX(C14,EDATE(НачалоУчета,-1))))*12+MONTH(L$6)-MONTH(MAX(C14,EDATE(НачалоУчета,-1)))-1),2))))) -> 0 | M14: =IF(A14="",0,IF(OR(E14<=0,M$6>ДатаОтчета,C14>=M$6),0,MAX(0,MIN(D14-F14,ROUND(D14/E14*MAX(0,(YEAR(M$6)-YEAR(MAX(C14,EDATE(НачалоУчета,-1))))*12+MONTH(M$6)-MONTH(MAX(C14,EDATE(НачалоУчета,-1)))),2))-MIN(D14-F14,ROUND(D14/E14*MAX(0,(YEAR(M$6)-YEAR(MAX(C14,EDATE(НачалоУчета,-1))))*12+MONTH(M$6)-MONTH(MAX(C14,EDATE(НачалоУчета,-1)))-1),2))))) -> 0 | N14: =IF(A14="",0,IF(OR(E14<=0,N$6>ДатаОтчета,C14>=N$6),0,MAX(0,MIN(D14-F14,ROUND(D14/E14*MAX(0,(YEAR(N$6)-YEAR(MAX(C14,EDATE(НачалоУчета,-1))))*12+MONTH(N$6)-MONTH(MAX(C14,EDATE(НачалоУчета,-1)))),2))-MIN(D14-F14,ROUND(D14/E14*MAX(0,(YEAR(N$6)-YEAR(MAX(C14,EDATE(НачалоУчета,-1))))*12+MONTH(N$6)-MONTH(MAX(C14,EDATE(НачалоУчета,-1)))-1),2))))) -> 0 | O14: =IF(A14="",0,IF(OR(E14<=0,O$6>ДатаОтчета,C14>=O$6),0,MAX(0,MIN(D14-F14,ROUND(D14/E14*MAX(0,(YEAR(O$6)-YEAR(MAX(C14,EDATE(НачалоУчета,-1))))*12+MONTH(O$6)-MONTH(MAX(C14,EDATE(НачалоУчета,-1)))),2))-MIN(D14-F14,ROUND(D14/E14*MAX(0,(YEAR(O$6)-YEAR(MAX(C14,EDATE(НачалоУчета,-1))))*12+MONTH(O$6)-MONTH(MAX(C14,EDATE(НачалоУчета,-1)))-1),2))))) -> 0 | P14: =IF(A14="",0,IF(OR(E14<=0,P$6>ДатаОтчета,C14>=P$6),0,MAX(0,MIN(D14-F14,ROUND(D14/E14*MAX(0,(YEAR(P$6)-YEAR(MAX(C14,EDATE(НачалоУчета,-1))))*12+MONTH(P$6)-MONTH(MAX(C14,EDATE(НачалоУчета,-1)))),2))-MIN(D14-F14,ROUND(D14/E14*MAX(0,(YEAR(P$6)-YEAR(MAX(C14,EDATE(НачалоУчета,-1))))*12+MONTH(P$6)-MONTH(MAX(C14,EDATE(НачалоУчета,-1)))-1),2))))) -> 0 | Q14: =IF(A14="",0,IF(OR(E14<=0,Q$6>ДатаОтчета,C14>=Q$6),0,MAX(0,MIN(D14-F14,ROUND(D14/E14*MAX(0,(YEAR(Q$6)-YEAR(MAX(C14,EDATE(НачалоУчета,-1))))*12+MONTH(Q$6)-MONTH(MAX(C14,EDATE(НачалоУчета,-1)))),2))-MIN(D14-F14,ROUND(D14/E14*MAX(0,(YEAR(Q$6)-YEAR(MAX(C14,EDATE(НачалоУчета,-1))))*12+MONTH(Q$6)-MONTH(MAX(C14,EDATE(НачалоУчета,-1)))-1),2))))) -> 0 | R14: =IF(A14="",0,IF(OR(E14<=0,R$6>ДатаОтчета,C14>=R$6),0,MAX(0,MIN(D14-F14,ROUND(D14/E14*MAX(0,(YEAR(R$6)-YEAR(MAX(C14,EDATE(НачалоУчета,-1))))*12+MONTH(R$6)-MONTH(MAX(C14,EDATE(НачалоУчета,-1)))),2))-MIN(D14-F14,ROUND(D14/E14*MAX(0,(YEAR(R$6)-YEAR(MAX(C14,EDATE(НачалоУчета,-1))))*12+MONTH(R$6)-MONTH(MAX(C14,EDATE(НачалоУчета,-1)))-1),2))))) -> 0 | S14: =IF(A14="",0,IF(OR(E14<=0,S$6>ДатаОтчета,C14>=S$6),0,MAX(0,MIN(D14-F14,ROUND(D14/E14*MAX(0,(YEAR(S$6)-YEAR(MAX(C14,EDATE(НачалоУчета,-1))))*12+MONTH(S$6)-MONTH(MAX(C14,EDATE(НачалоУчета,-1)))),2))-MIN(D14-F14,ROUND(D14/E14*MAX(0,(YEAR(S$6)-YEAR(MAX(C14,EDATE(НачалоУчета,-1))))*12+MONTH(S$6)-MONTH(MAX(C14,EDATE(НачалоУчета,-1)))-1),2))))) -> 0 | T14: =IF(A14="",0,IF(OR(E14<=0,T$6>ДатаОтчета,C14>=T$6),0,MAX(0,MIN(D14-F14,ROUND(D14/E14*MAX(0,(YEAR(T$6)-YEAR(MAX(C14,EDATE(НачалоУчета,-1))))*12+MONTH(T$6)-MONTH(MAX(C14,EDATE(НачалоУчета,-1)))),2))-MIN(D14-F14,ROUND(D14/E14*MAX(0,(YEAR(T$6)-YEAR(MAX(C14,EDATE(НачалоУчета,-1))))*12+MONTH(T$6)-MONTH(MAX(C14,EDATE(НачалоУчета,-1)))-1),2))))) -> 0 | U14: =IF(A14="",0,IF(OR(E14<=0,U$6>ДатаОтчета,C14>=U$6),0,MAX(0,MIN(D14-F14,ROUND(D14/E14*MAX(0,(YEAR(U$6)-YEAR(MAX(C14,EDATE(НачалоУчета,-1))))*12+MONTH(U$6)-MONTH(MAX(C14,EDATE(НачалоУчета,-1)))),2))-MIN(D14-F14,ROUND(D14/E14*MAX(0,(YEAR(U$6)-YEAR(MAX(C14,EDATE(НачалоУчета,-1))))*12+MONTH(U$6)-MONTH(MAX(C14,EDATE(НачалоУчета,-1)))-1),2))))) -> 0 | V14: =IF(A14="",0,IF(OR(E14<=0,V$6>ДатаОтчета,C14>=V$6),0,MAX(0,MIN(D14-F14,ROUND(D14/E14*MAX(0,(YEAR(V$6)-YEAR(MAX(C14,EDATE(НачалоУчета,-1))))*12+MONTH(V$6)-MONTH(MAX(C14,EDATE(НачалоУчета,-1)))),2))-MIN(D14-F14,ROUND(D14/E14*MAX(0,(YEAR(V$6)-YEAR(MAX(C14,EDATE(НачалоУчета,-1))))*12+MONTH(V$6)-MONTH(MAX(C14,EDATE(НачалоУчета,-1)))-1),2))))) -> 0 | W14: =IF(A14="",IF(COUNTA(B14:F14)>0,"ОШИБКА",""),IF(OR(COUNTIF(Assets[ID],A14)<>1,B14="",NOT(ISNUMBER(C14)),NOT(ISNUMBER(D14)),D14<0,NOT(ISNUMBER(E14)),E14<=0,F14<0,F14>D14),"ОШИБКА","ОК"))
G15: =IF(A15="","",IF(C15>ДатаОтчета,0,IF(E15<=0,0,MIN(D15,F15+ROUND(D15/E15*MAX(0,(YEAR(ДатаОтчета)-YEAR(MAX(C15,EDATE(НачалоУчета,-1))))*12+MONTH(ДатаОтчета)-MONTH(MAX(C15,EDATE(НачалоУчета,-1)))),2))))) | H15: =IF(A15="","",IF(C15>ДатаОтчета,0,D15-G15)) | I15: =IF(A15="","",SUMIFS(Cash[Сумма],Cash[Дата],"<="&ДатаОтчета,Cash[Статус],"Проведён",Cash[Тип],"Покупка ОС",Cash[Документ],A15)) | J15: =IF(A15="","",IF(OR(C15>ДатаОтчета,C15<НачалоУчета),0,D15-I15)) | K15: =IF(A15="",0,IF(OR(E15<=0,K$6>ДатаОтчета,C15>=K$6),0,MAX(0,MIN(D15-F15,ROUND(D15/E15*MAX(0,(YEAR(K$6)-YEAR(MAX(C15,EDATE(НачалоУчета,-1))))*12+MONTH(K$6)-MONTH(MAX(C15,EDATE(НачалоУчета,-1)))),2))-MIN(D15-F15,ROUND(D15/E15*MAX(0,(YEAR(K$6)-YEAR(MAX(C15,EDATE(НачалоУчета,-1))))*12+MONTH(K$6)-MONTH(MAX(C15,EDATE(НачалоУчета,-1)))-1),2))))) -> 0 | L15: =IF(A15="",0,IF(OR(E15<=0,L$6>ДатаОтчета,C15>=L$6),0,MAX(0,MIN(D15-F15,ROUND(D15/E15*MAX(0,(YEAR(L$6)-YEAR(MAX(C15,EDATE(НачалоУчета,-1))))*12+MONTH(L$6)-MONTH(MAX(C15,EDATE(НачалоУчета,-1)))),2))-MIN(D15-F15,ROUND(D15/E15*MAX(0,(YEAR(L$6)-YEAR(MAX(C15,EDATE(НачалоУчета,-1))))*12+MONTH(L$6)-MONTH(MAX(C15,EDATE(НачалоУчета,-1)))-1),2))))) -> 0 | M15: =IF(A15="",0,IF(OR(E15<=0,M$6>ДатаОтчета,C15>=M$6),0,MAX(0,MIN(D15-F15,ROUND(D15/E15*MAX(0,(YEAR(M$6)-YEAR(MAX(C15,EDATE(НачалоУчета,-1))))*12+MONTH(M$6)-MONTH(MAX(C15,EDATE(НачалоУчета,-1)))),2))-MIN(D15-F15,ROUND(D15/E15*MAX(0,(YEAR(M$6)-YEAR(MAX(C15,EDATE(НачалоУчета,-1))))*12+MONTH(M$6)-MONTH(MAX(C15,EDATE(НачалоУчета,-1)))-1),2))))) -> 0 | N15: =IF(A15="",0,IF(OR(E15<=0,N$6>ДатаОтчета,C15>=N$6),0,MAX(0,MIN(D15-F15,ROUND(D15/E15*MAX(0,(YEAR(N$6)-YEAR(MAX(C15,EDATE(НачалоУчета,-1))))*12+MONTH(N$6)-MONTH(MAX(C15,EDATE(НачалоУчета,-1)))),2))-MIN(D15-F15,ROUND(D15/E15*MAX(0,(YEAR(N$6)-YEAR(MAX(C15,EDATE(НачалоУчета,-1))))*12+MONTH(N$6)-MONTH(MAX(C15,EDATE(НачалоУчета,-1)))-1),2))))) -> 0 | O15: =IF(A15="",0,IF(OR(E15<=0,O$6>ДатаОтчета,C15>=O$6),0,MAX(0,MIN(D15-F15,ROUND(D15/E15*MAX(0,(YEAR(O$6)-YEAR(MAX(C15,EDATE(НачалоУчета,-1))))*12+MONTH(O$6)-MONTH(MAX(C15,EDATE(НачалоУчета,-1)))),2))-MIN(D15-F15,ROUND(D15/E15*MAX(0,(YEAR(O$6)-YEAR(MAX(C15,EDATE(НачалоУчета,-1))))*12+MONTH(O$6)-MONTH(MAX(C15,EDATE(НачалоУчета,-1)))-1),2))))) -> 0 | P15: =IF(A15="",0,IF(OR(E15<=0,P$6>ДатаОтчета,C15>=P$6),0,MAX(0,MIN(D15-F15,ROUND(D15/E15*MAX(0,(YEAR(P$6)-YEAR(MAX(C15,EDATE(НачалоУчета,-1))))*12+MONTH(P$6)-MONTH(MAX(C15,EDATE(НачалоУчета,-1)))),2))-MIN(D15-F15,ROUND(D15/E15*MAX(0,(YEAR(P$6)-YEAR(MAX(C15,EDATE(НачалоУчета,-1))))*12+MONTH(P$6)-MONTH(MAX(C15,EDATE(НачалоУчета,-1)))-1),2))))) -> 0 | Q15: =IF(A15="",0,IF(OR(E15<=0,Q$6>ДатаОтчета,C15>=Q$6),0,MAX(0,MIN(D15-F15,ROUND(D15/E15*MAX(0,(YEAR(Q$6)-YEAR(MAX(C15,EDATE(НачалоУчета,-1))))*12+MONTH(Q$6)-MONTH(MAX(C15,EDATE(НачалоУчета,-1)))),2))-MIN(D15-F15,ROUND(D15/E15*MAX(0,(YEAR(Q$6)-YEAR(MAX(C15,EDATE(НачалоУчета,-1))))*12+MONTH(Q$6)-MONTH(MAX(C15,EDATE(НачалоУчета,-1)))-1),2))))) -> 0 | R15: =IF(A15="",0,IF(OR(E15<=0,R$6>ДатаОтчета,C15>=R$6),0,MAX(0,MIN(D15-F15,ROUND(D15/E15*MAX(0,(YEAR(R$6)-YEAR(MAX(C15,EDATE(НачалоУчета,-1))))*12+MONTH(R$6)-MONTH(MAX(C15,EDATE(НачалоУчета,-1)))),2))-MIN(D15-F15,ROUND(D15/E15*MAX(0,(YEAR(R$6)-YEAR(MAX(C15,EDATE(НачалоУчета,-1))))*12+MONTH(R$6)-MONTH(MAX(C15,EDATE(НачалоУчета,-1)))-1),2))))) -> 0 | S15: =IF(A15="",0,IF(OR(E15<=0,S$6>ДатаОтчета,C15>=S$6),0,MAX(0,MIN(D15-F15,ROUND(D15/E15*MAX(0,(YEAR(S$6)-YEAR(MAX(C15,EDATE(НачалоУчета,-1))))*12+MONTH(S$6)-MONTH(MAX(C15,EDATE(НачалоУчета,-1)))),2))-MIN(D15-F15,ROUND(D15/E15*MAX(0,(YEAR(S$6)-YEAR(MAX(C15,EDATE(НачалоУчета,-1))))*12+MONTH(S$6)-MONTH(MAX(C15,EDATE(НачалоУчета,-1)))-1),2))))) -> 0 | T15: =IF(A15="",0,IF(OR(E15<=0,T$6>ДатаОтчета,C15>=T$6),0,MAX(0,MIN(D15-F15,ROUND(D15/E15*MAX(0,(YEAR(T$6)-YEAR(MAX(C15,EDATE(НачалоУчета,-1))))*12+MONTH(T$6)-MONTH(MAX(C15,EDATE(НачалоУчета,-1)))),2))-MIN(D15-F15,ROUND(D15/E15*MAX(0,(YEAR(T$6)-YEAR(MAX(C15,EDATE(НачалоУчета,-1))))*12+MONTH(T$6)-MONTH(MAX(C15,EDATE(НачалоУчета,-1)))-1),2))))) -> 0 | U15: =IF(A15="",0,IF(OR(E15<=0,U$6>ДатаОтчета,C15>=U$6),0,MAX(0,MIN(D15-F15,ROUND(D15/E15*MAX(0,(YEAR(U$6)-YEAR(MAX(C15,EDATE(НачалоУчета,-1))))*12+MONTH(U$6)-MONTH(MAX(C15,EDATE(НачалоУчета,-1)))),2))-MIN(D15-F15,ROUND(D15/E15*MAX(0,(YEAR(U$6)-YEAR(MAX(C15,EDATE(НачалоУчета,-1))))*12+MONTH(U$6)-MONTH(MAX(C15,EDATE(НачалоУчета,-1)))-1),2))))) -> 0 | V15: =IF(A15="",0,IF(OR(E15<=0,V$6>ДатаОтчета,C15>=V$6),0,MAX(0,MIN(D15-F15,ROUND(D15/E15*MAX(0,(YEAR(V$6)-YEAR(MAX(C15,EDATE(НачалоУчета,-1))))*12+MONTH(V$6)-MONTH(MAX(C15,EDATE(НачалоУчета,-1)))),2))-MIN(D15-F15,ROUND(D15/E15*MAX(0,(YEAR(V$6)-YEAR(MAX(C15,EDATE(НачалоУчета,-1))))*12+MONTH(V$6)-MONTH(MAX(C15,EDATE(НачалоУчета,-1)))-1),2))))) -> 0 | W15: =IF(A15="",IF(COUNTA(B15:F15)>0,"ОШИБКА",""),IF(OR(COUNTIF(Assets[ID],A15)<>1,B15="",NOT(ISNUMBER(C15)),NOT(ISNUMBER(D15)),D15<0,NOT(ISNUMBER(E15)),E15<=0,F15<0,F15>D15),"ОШИБКА","ОК"))
G16: =IF(A16="","",IF(C16>ДатаОтчета,0,IF(E16<=0,0,MIN(D16,F16+ROUND(D16/E16*MAX(0,(YEAR(ДатаОтчета)-YEAR(MAX(C16,EDATE(НачалоУчета,-1))))*12+MONTH(ДатаОтчета)-MONTH(MAX(C16,EDATE(НачалоУчета,-1)))),2))))) | H16: =IF(A16="","",IF(C16>ДатаОтчета,0,D16-G16)) | I16: =IF(A16="","",SUMIFS(Cash[Сумма],Cash[Дата],"<="&ДатаОтчета,Cash[Статус],"Проведён",Cash[Тип],"Покупка ОС",Cash[Документ],A16)) | J16: =IF(A16="","",IF(OR(C16>ДатаОтчета,C16<НачалоУчета),0,D16-I16)) | K16: =IF(A16="",0,IF(OR(E16<=0,K$6>ДатаОтчета,C16>=K$6),0,MAX(0,MIN(D16-F16,ROUND(D16/E16*MAX(0,(YEAR(K$6)-YEAR(MAX(C16,EDATE(НачалоУчета,-1))))*12+MONTH(K$6)-MONTH(MAX(C16,EDATE(НачалоУчета,-1)))),2))-MIN(D16-F16,ROUND(D16/E16*MAX(0,(YEAR(K$6)-YEAR(MAX(C16,EDATE(НачалоУчета,-1))))*12+MONTH(K$6)-MONTH(MAX(C16,EDATE(НачалоУчета,-1)))-1),2))))) -> 0 | L16: =IF(A16="",0,IF(OR(E16<=0,L$6>ДатаОтчета,C16>=L$6),0,MAX(0,MIN(D16-F16,ROUND(D16/E16*MAX(0,(YEAR(L$6)-YEAR(MAX(C16,EDATE(НачалоУчета,-1))))*12+MONTH(L$6)-MONTH(MAX(C16,EDATE(НачалоУчета,-1)))),2))-MIN(D16-F16,ROUND(D16/E16*MAX(0,(YEAR(L$6)-YEAR(MAX(C16,EDATE(НачалоУчета,-1))))*12+MONTH(L$6)-MONTH(MAX(C16,EDATE(НачалоУчета,-1)))-1),2))))) -> 0 | M16: =IF(A16="",0,IF(OR(E16<=0,M$6>ДатаОтчета,C16>=M$6),0,MAX(0,MIN(D16-F16,ROUND(D16/E16*MAX(0,(YEAR(M$6)-YEAR(MAX(C16,EDATE(НачалоУчета,-1))))*12+MONTH(M$6)-MONTH(MAX(C16,EDATE(НачалоУчета,-1)))),2))-MIN(D16-F16,ROUND(D16/E16*MAX(0,(YEAR(M$6)-YEAR(MAX(C16,EDATE(НачалоУчета,-1))))*12+MONTH(M$6)-MONTH(MAX(C16,EDATE(НачалоУчета,-1)))-1),2))))) -> 0 | N16: =IF(A16="",0,IF(OR(E16<=0,N$6>ДатаОтчета,C16>=N$6),0,MAX(0,MIN(D16-F16,ROUND(D16/E16*MAX(0,(YEAR(N$6)-YEAR(MAX(C16,EDATE(НачалоУчета,-1))))*12+MONTH(N$6)-MONTH(MAX(C16,EDATE(НачалоУчета,-1)))),2))-MIN(D16-F16,ROUND(D16/E16*MAX(0,(YEAR(N$6)-YEAR(MAX(C16,EDATE(НачалоУчета,-1))))*12+MONTH(N$6)-MONTH(MAX(C16,EDATE(НачалоУчета,-1)))-1),2))))) -> 0 | O16: =IF(A16="",0,IF(OR(E16<=0,O$6>ДатаОтчета,C16>=O$6),0,MAX(0,MIN(D16-F16,ROUND(D16/E16*MAX(0,(YEAR(O$6)-YEAR(MAX(C16,EDATE(НачалоУчета,-1))))*12+MONTH(O$6)-MONTH(MAX(C16,EDATE(НачалоУчета,-1)))),2))-MIN(D16-F16,ROUND(D16/E16*MAX(0,(YEAR(O$6)-YEAR(MAX(C16,EDATE(НачалоУчета,-1))))*12+MONTH(O$6)-MONTH(MAX(C16,EDATE(НачалоУчета,-1)))-1),2))))) -> 0 | P16: =IF(A16="",0,IF(OR(E16<=0,P$6>ДатаОтчета,C16>=P$6),0,MAX(0,MIN(D16-F16,ROUND(D16/E16*MAX(0,(YEAR(P$6)-YEAR(MAX(C16,EDATE(НачалоУчета,-1))))*12+MONTH(P$6)-MONTH(MAX(C16,EDATE(НачалоУчета,-1)))),2))-MIN(D16-F16,ROUND(D16/E16*MAX(0,(YEAR(P$6)-YEAR(MAX(C16,EDATE(НачалоУчета,-1))))*12+MONTH(P$6)-MONTH(MAX(C16,EDATE(НачалоУчета,-1)))-1),2))))) -> 0 | Q16: =IF(A16="",0,IF(OR(E16<=0,Q$6>ДатаОтчета,C16>=Q$6),0,MAX(0,MIN(D16-F16,ROUND(D16/E16*MAX(0,(YEAR(Q$6)-YEAR(MAX(C16,EDATE(НачалоУчета,-1))))*12+MONTH(Q$6)-MONTH(MAX(C16,EDATE(НачалоУчета,-1)))),2))-MIN(D16-F16,ROUND(D16/E16*MAX(0,(YEAR(Q$6)-YEAR(MAX(C16,EDATE(НачалоУчета,-1))))*12+MONTH(Q$6)-MONTH(MAX(C16,EDATE(НачалоУчета,-1)))-1),2))))) -> 0 | R16: =IF(A16="",0,IF(OR(E16<=0,R$6>ДатаОтчета,C16>=R$6),0,MAX(0,MIN(D16-F16,ROUND(D16/E16*MAX(0,(YEAR(R$6)-YEAR(MAX(C16,EDATE(НачалоУчета,-1))))*12+MONTH(R$6)-MONTH(MAX(C16,EDATE(НачалоУчета,-1)))),2))-MIN(D16-F16,ROUND(D16/E16*MAX(0,(YEAR(R$6)-YEAR(MAX(C16,EDATE(НачалоУчета,-1))))*12+MONTH(R$6)-MONTH(MAX(C16,EDATE(НачалоУчета,-1)))-1),2))))) -> 0 | S16: =IF(A16="",0,IF(OR(E16<=0,S$6>ДатаОтчета,C16>=S$6),0,MAX(0,MIN(D16-F16,ROUND(D16/E16*MAX(0,(YEAR(S$6)-YEAR(MAX(C16,EDATE(НачалоУчета,-1))))*12+MONTH(S$6)-MONTH(MAX(C16,EDATE(НачалоУчета,-1)))),2))-MIN(D16-F16,ROUND(D16/E16*MAX(0,(YEAR(S$6)-YEAR(MAX(C16,EDATE(НачалоУчета,-1))))*12+MONTH(S$6)-MONTH(MAX(C16,EDATE(НачалоУчета,-1)))-1),2))))) -> 0 | T16: =IF(A16="",0,IF(OR(E16<=0,T$6>ДатаОтчета,C16>=T$6),0,MAX(0,MIN(D16-F16,ROUND(D16/E16*MAX(0,(YEAR(T$6)-YEAR(MAX(C16,EDATE(НачалоУчета,-1))))*12+MONTH(T$6)-MONTH(MAX(C16,EDATE(НачалоУчета,-1)))),2))-MIN(D16-F16,ROUND(D16/E16*MAX(0,(YEAR(T$6)-YEAR(MAX(C16,EDATE(НачалоУчета,-1))))*12+MONTH(T$6)-MONTH(MAX(C16,EDATE(НачалоУчета,-1)))-1),2))))) -> 0 | U16: =IF(A16="",0,IF(OR(E16<=0,U$6>ДатаОтчета,C16>=U$6),0,MAX(0,MIN(D16-F16,ROUND(D16/E16*MAX(0,(YEAR(U$6)-YEAR(MAX(C16,EDATE(НачалоУчета,-1))))*12+MONTH(U$6)-MONTH(MAX(C16,EDATE(НачалоУчета,-1)))),2))-MIN(D16-F16,ROUND(D16/E16*MAX(0,(YEAR(U$6)-YEAR(MAX(C16,EDATE(НачалоУчета,-1))))*12+MONTH(U$6)-MONTH(MAX(C16,EDATE(НачалоУчета,-1)))-1),2))))) -> 0 | V16: =IF(A16="",0,IF(OR(E16<=0,V$6>ДатаОтчета,C16>=V$6),0,MAX(0,MIN(D16-F16,ROUND(D16/E16*MAX(0,(YEAR(V$6)-YEAR(MAX(C16,EDATE(НачалоУчета,-1))))*12+MONTH(V$6)-MONTH(MAX(C16,EDATE(НачалоУчета,-1)))),2))-MIN(D16-F16,ROUND(D16/E16*MAX(0,(YEAR(V$6)-YEAR(MAX(C16,EDATE(НачалоУчета,-1))))*12+MONTH(V$6)-MONTH(MAX(C16,EDATE(НачалоУчета,-1)))-1),2))))) -> 0 | W16: =IF(A16="",IF(COUNTA(B16:F16)>0,"ОШИБКА",""),IF(OR(COUNTIF(Assets[ID],A16)<>1,B16="",NOT(ISNUMBER(C16)),NOT(ISNUMBER(D16)),D16<0,NOT(ISNUMBER(E16)),E16<=0,F16<0,F16>D16),"ОШИБКА","ОК"))
